Workbook

Sheet Cover
B1: Chemical Tanker Voyage Economics Model
A2: Independent analysis using publicly available data. Not affiliated with or endorsed by any organization named. | B2: Round-voyage TCE P&L, sensitivity/tornado, and break-even freight analysis — Sean Burgess, Sep-2026
B3: Independent analysis using publicly available data. Not affiliated with or endorsed by any organization named.
B4: SIMULATED / ESTIMATED INPUTS: freight rates, port costs, port days, vessel particulars and fuel-price conversion factors are analyst assumptions, not observed data. Canal tolls come from published tariff extracts; Brent and the freight index are public series.
B7: HEADLINE — ACTIVE SCENARIO
B8: Route | C8: =Voyage_PnL!B8 -> USG-ARA transatlantic
B9: Round-voyage days | C9: =Voyage_PnL!B20 -> 49.407407
B10: Gross freight | C10: =Voyage_PnL!B25 -> 2275200
B11: Total voyage costs | C11: =Voyage_PnL!B39 -> 1053581
B12: TCE ($/day) | C12: =Voyage_PnL!B43 -> 23574.178
B13: Vessel cost benchmark ($/day) | C13: =Benchmark -> 18000
B14: Voyage result after vessel cost | C14: =Voyage_PnL!B46 -> 275405.7
B15: Break-even fronthaul rate ($/t) | C15: =Voyage_PnL!B47 -> 42.76904
B16: Largest tornado driver | C16: =Sensitivity!A21 -> Freight rate (market)
B17: Model integrity check | C17: =Voyage_PnL!C60 -> OK
B20: HOW TO USE
B21: 1. Go to Inputs and change the five yellow scenario switches (route, bunker case, freight case, congestion, utilization).
B22: 2. Every assumption is a blue cell on Inputs / Routes / Canal_Tolls with its basis written next to it — overwrite any you disagree with.
B23: 3. Voyage_PnL shows the full cost build-up and TCE for the active scenario, plus all four routes side by side.
B24: 4. Sensitivity ranks the drivers (tornado) and shows leverage per +10% move; Breakeven shows break-even freight curves, a TCE heat-map and a speed curve.
B25: 5. Engine is the row-wise calculator behind the charts: one full voyage P&L per row. Do not edit it unless extending the model.
B27: COLOUR KEY
B28: Scenario switch
B29: Hardcoded input / assumption
B30: Key assumption
B31: Formula
B32: Link from another sheet
... B35: DEFINITIONS
B36: TCE | C36: (Gross freight - commissions - voyage costs) / voyage days. Converts a voyage charter into a $/day figure comparable with time-charter hire.
B37: Voyage costs | C37: Costs the shipowner bears on a voyage charter: bunkers, port disbursements, canal tolls, EU ETS allowances, misc.
B38: Fronthaul / backhaul | C38: Round voyage A->B (main cargo) then B->A (return cargo at lower utilization and rate). Backhaul utilization 0% = ballast return.
B39: Break-even rate | C39: Fronthaul $/t at which TCE equals the daily vessel-cost benchmark.
B40: ECA | C40: Emission Control Area — 0.10% sulphur limit, so MGO is burned inside (North American ECA, North Sea/Channel).
B42: SHEETS
B43: Inputs — switches and assumptions
B44: Routes — route & port-region tables
B45: Canal_Tolls — Panama & Suez per-transit build-up
B46: Voyage_PnL — detailed TCE build-up + route comparison
B47: Sensitivity — tornado + leverage
B48: Breakeven — break-even curves, TCE grid, speed curve
B49: Engine — row-wise calculator
B50: Data_Brent — FRED Brent monthly + statistics
B51: Data_PPI — BLS deep-sea freight PPI + percentile bands

Sheet Inputs
A1: Inputs & scenario switches
A2: Independent analysis using publicly available data. Not affiliated with or endorsed by any organization named.
A3: Yellow cells = scenario switches. Blue = hardcoded assumption (edit freely). Black = formula. Every assumption carries its basis in column D.
A5: SCENARIO SWITCHES
A6: Switch | B6: Selection | C6: Resolves to | D6: Options
A7: 1. Route | B7: 1 | C7: =INDEX(Routes!$B$6:$B$9,Sw_Route) -> USG-ARA transatlantic | D7: 1 USG-ARA transatlantic | 2 USG-Far East via Panama | 3 ARA-India WC via Suez | 4 ARA-India WC via Cape
A8: 2. Bunker price case | B8: 1 | C8: =TEXT(Brent,"$0.00")&"/bbl Brent" -> $82.01/bbl Brent | D8: 1 Trailing-12m avg | 2 Latest month | 3 5-yr avg | 4 5-yr P10 | 5 5-yr P90 | 6 Custom (below)
A9: 3. Freight market case | B9: 1 | C9: =TEXT(FreightMult,"0.00")&"x base rates" -> 1.00x base rates | D9: 1 Base rates | 2 Weak (PPI YoY P10) | 3 Strong (PPI YoY P90) | 4 Custom multiplier (below)
A10: 4. Port congestion case | B10: 1 | C10: =TEXT(PortMult,"0.00")&"x port days" -> 1.00x port days | D10: 1 Normal (1.0x port days) | 2 Congested (1.5x) | 3 Severe (2.0x) | 4 Custom (below)
A11: 5. Cargo utilization case | B11: 1 | C11: =TEXT(UtilFH,"0%")&" / "&TEXT(UtilBH,"0%") -> 85% / 50% | D11: 1 Base (85% / 50%) | 2 Soft (70% / 25%) | 3 Firm (95% / 75%) | 4 Custom (below) [fronthaul / backhaul]
A13: CUSTOM OVERRIDES (used only when a switch selects 'Custom')
A14: Item | B14: Value | C14: Unit | D14: Note
A15: Custom Brent | B15: 80 | C15: $/bbl | D15: User entry
A16: Custom freight multiplier | B16: 1 | C16: x base rate | D16: User entry
A17: Custom port-time multiplier | B17: 1 | C17: x base port days | D17: User entry
A18: Custom fronthaul utilization | B18: 0.85 | C18: % capacity | D18: User entry
A19: Custom backhaul utilization | B19: 0.5 | C19: % capacity | D19: User entry (0% = ballast return)
A21: ACTIVE LEVERS (what the P&L uses — formulas, do not overwrite)
A22: Lever | B22: Active value | C22: Unit | D22: How resolved
A23: Brent crude | B23: =CHOOSE(Sw_Bunker,Brent_TTM,Brent_Latest,Brent_5Y,Brent_P10,Brent_P90,Cust_Brent) -> 82.01 | C23: $/bbl | D23: Switch 2 -> Data_Brent statistics (FRED MCOILBRENTEU)
A24: Freight rate multiplier | B24: =CHOOSE(Sw_Freight,1,Freight_Low,Freight_High,Cust_Freight) -> 1 | C24: x base rate | D24: Switch 3 -> Data_PPI percentile bands
A25: Port-time multiplier | B25: =CHOOSE(Sw_Port,1,1.5,2,Cust_Port) -> 1 | C25: x base port days | D25: Switch 4 (scenario bands, not a pulled series — USACE LPMS delay microdata is not public)
A26: Fronthaul utilization | B26: =CHOOSE(Sw_Util,0.85,0.7,0.95,Cust_UtilFH) -> 0.85 | C26: % capacity | D26: Switch 5
A27: Backhaul utilization | B27: =CHOOSE(Sw_Util,0.5,0.25,0.75,Cust_UtilBH) -> 0.5 | C27: % capacity | D27: Switch 5
A29: VESSEL — generic 38,000 dwt IMO II stainless-steel parcel chemical tanker
A30: Assumption | B30: Value | C30: Unit | D30: Basis / judgment (ESTIMATE unless a source is named)
A31: Deadweight | B31: 38000 | C31: t | D31: Typical deep-sea parcel tanker size class (32-45k dwt). Generic, not a specific ship.
A32: Usable cargo capacity | B32: 36000 | C32: t | D32: DWT less ~2,000 t bunkers, fresh water, stores, constant.
A33: Operating speed | B33: 13.5 | C33: knots | D33: Lever. Typical laden service speed 13-14.5 kn for this class.
A34: Reference speed for consumption | B34: 13.5 | C34: knots | D34: Speed at which the consumption figures below apply.
A35: Sea consumption, laden | B35: 27 | C35: t/day | D35: At reference speed. Non-eco 2010s-built design; eco ships ~20-24 t/day.
A36: Sea consumption, ballast | B36: 24 | C36: t/day | D36: At reference speed; applies to backhaul leg only when backhaul utilization = 0%.
A37: Port / canal consumption (MGO) | B37: 6 | C37: t/day | D37: Cargo pumps, heating, inerting, hotel load. Canal transit days burn at this rate (simplification).
A38: Consumption-speed exponent | B38: 3 | D38: Admiralty (cube) law; fuel per mile scales with speed squared.
A39: Sea margin | B39: 0.05 | C39: % of distance | D39: Weather and routeing allowance.
A40: Panama Canal net tonnage (PC/UMS) | B40: 20000 | C40: t | D40: Estimate for class; use the ship's certificate in practice.
A41: Suez Canal net tonnage (SCNT) | B41: 20000 | C41: t | D41: Estimate for class; use the ship's certificate in practice.
A42: Hull & machinery value | B42: 35000000 | C42: $ | D42: Used only for war-risk additional premium. Estimate.
A44: FUEL, CARBON & COMMERCIAL
A45: Assumption | B45: Value | C45: Unit | D45: Basis / judgment
A46: VLSFO price per $1/bbl Brent | B46: 7.7 | C46: $/t per $/bbl | D46: ESTIMATE. ~7.3 bbl/t conversion x ~5% product premium. At $82 Brent -> ~$631/t VLSFO. Spot-check vs Ship & Bunker Houston/Rotterdam.
A47: MGO price per $1/bbl Brent | B47: 9.7 | C47: $/t per $/bbl | D47: ESTIMATE. Distillate premium over crude. At $82 Brent -> ~$795/t MGO. Used in ECAs and in port.
A48: Freight commission (address + brokerage) | B48: 0.025 | C48: % gross freight | D48: Market-standard 1.25% + 1.25%.
A49: Misc. voyage costs per round voyage | B49: 25000 | C49: $ | D49: Tank cleaning, surveys, nitrogen, sundries. ESTIMATE.
A50: Port disbursement multiplier | B50: 1 | C50: x | D50: Lever on all per-call port costs (Routes sheet).
A51: Daily vessel cost benchmark | B51: 18000 | C51: $/day | D51: ESTIMATE. Owner: OPEX ~$8.5k + capital recovery ~$9.5k. Operator: substitute your T/C-in hire. TCE above this = voyage adds value.
A52: EU ETS allowance price | B52: 75 | C52: EUR/t CO2 | D52: ESTIMATE — check ICE EUA futures on the day.
A53: USD per EUR | B53: 1.1 | C53: $/EUR | D53: ESTIMATE.
A54: ETS phase-in (2026) | B54: 1 | C54: % | D54: EU ETS maritime: 40% (2024), 70% (2025), 100% from 2026 emissions.
A55: CO2 factor, VLSFO | B55: 3.114 | C55: t CO2 / t fuel | D55: EU MRV / IMO emission factor for HFO-type fuels.
A56: CO2 factor, MGO | B56: 3.206 | C56: t CO2 / t fuel | D56: EU MRV / IMO emission factor for MDO/MGO.
A58: VESSEL TONNAGE & DIMENSIONS USED BY PORT TARIFFS
A59: Assumption | B59: Value | C59: Unit | D59: Basis / judgment
A60: Gross tonnage (GT) | B60: 23500 | C60: GT | D60: Estimate for class. Port of Rotterdam's own worked example uses a 23,230 GT chemical tanker, which corroborates the order of magnitude.
A61: Length overall | B61: 600 | C61: feet | D61: ~183 m. Sets the Port Houston dockage band (600-650 ft).
A63: CANAL-RELATED
A64: Assumption | B64: Value | C64: Unit | D64: Basis / judgment
A65: USD per SDR | B65: 1.35 | C65: $/SDR | D65: ESTIMATE — check IMF daily rate (imf.org rms_five).
A66: Suez chemical-tanker surcharge, laden | B66: 0.2 | C66: % | D66: SCA Circular 7/2023 as reported (20% for chemical tankers). Applied on petroleum-product-tanker bands as proxy.
A67: Suez surcharge, ballast | B67: 0.15 | C67: % | D67: SCA Circular 7/2023 as reported.
A68: Suez ancillary costs per transit | B68: 40000 | C68: $ | D68: Pilotage, tugs, mooring, agency. ESTIMATE.
A69: War-risk additional premium per Suez transit | B69: 0.0025 | C69: % hull value | D69: ILLUSTRATIVE. Red Sea AP has swung widely since 2023; set to 0 to test a normalized Suez.
A70: Panama linehandlers per transit | B70: 8 | C70: count | D70: ESTIMATE.

Sheet Routes
A1: Routes and port regions
A2: Independent analysis using publicly available data. Not affiliated with or endorsed by any organization named.
A3: Round voyage: fronthaul A->B laden, backhaul B->A. Distances APPROXIMATE (verify with a distance table). Freight rates are CALIBRATED ASSUMPTIONS, not observed fixtures. Port costs come from the Port_Tariffs sheet.
A5: # | B5: Route | C5: Region A | D5: Region B | E5: Distance per leg (nm) | F5: ECA miles per leg (nm) | G5: Canal | H5: Canal days per transit | I5: EU ETS share of sea emissions | J5: Base freight fronthaul ($/t) | K5: Base freight backhaul ($/t) | L5: Port days per op, A | M5: Port days per op, B | N5: Fixed port cost per op, A ($) | O5: Fixed port cost per op, B ($) | P5: EU port A (1/0) | Q5: EU port B (1/0) | R5: Canal cost per laden transit ($) | S5: Canal cost per ballast transit ($) | T5: Cargo-based port rate A ($/t) | U5: Cargo-based port rate B ($/t) | V5: Cargo-component cap A ($) | W5: Cargo-component cap B ($) | X5: Berth-day share A | Y5: Berth-day share B
A6: 1 | B6: USG-ARA transatlantic | C6: USG | D6: ARA | E6: 5000 | F6: 650 | G6: None | H6: 0 | I6: 0.5 | J6: 52 | K6: 38 | L6: =INDEX($C$15:$C$18,MATCH(C6,$A$15:$A$18,0)) -> 5 | M6: =INDEX($C$15:$C$18,MATCH(D6,$A$15:$A$18,0)) -> 3.5 | N6: =INDEX($D$15:$D$18,MATCH(C6,$A$15:$A$18,0)) -> 45813.4 | O6: =INDEX($D$15:$D$18,MATCH(D6,$A$15:$A$18,0)) -> 44845.748 | P6: =INDEX($H$15:$H$18,MATCH(C6,$A$15:$A$18,0)) -> 0 | Q6: =INDEX($H$15:$H$18,MATCH(D6,$A$15:$A$18,0)) -> 1 | R6: =IF(G6="Panama",Canal_Tolls!$C$20,IF(G6="Suez",Canal_Tolls!$C$45,0)) -> 0 | S6: =IF(G6="Panama",Canal_Tolls!$D$20,IF(G6="Suez",Canal_Tolls!$D$45,0)) -> 0 | T6: =INDEX($E$15:$E$18,MATCH(C6,$A$15:$A$18,0)) -> 0 | U6: =INDEX($E$15:$E$18,MATCH(D6,$A$15:$A$18,0)) -> 0.655776 | V6: =INDEX($F$15:$F$18,MATCH(C6,$A$15:$A$18,0)) -> 0 | W6: =INDEX($F$15:$F$18,MATCH(D6,$A$15:$A$18,0)) -> 20542.511 | X6: =INDEX($G$15:$G$18,MATCH(C6,$A$15:$A$18,0)) -> 0.6 | Y6: =INDEX($G$15:$G$18,MATCH(D6,$A$15:$A$18,0)) -> 0
A7: 2 | B7: USG-Far East via Panama | C7: USG | D7: FEA | E7: 9650 | F7: 200 | G7: Panama | H7: 1.5 | I7: 0 | J7: 92 | K7: 52 | L7: =INDEX($C$15:$C$18,MATCH(C7,$A$15:$A$18,0)) -> 5 | M7: =INDEX($C$15:$C$18,MATCH(D7,$A$15:$A$18,0)) -> 3.5 | N7: =INDEX($D$15:$D$18,MATCH(C7,$A$15:$A$18,0)) -> 45813.4 | O7: =INDEX($D$15:$D$18,MATCH(D7,$A$15:$A$18,0)) -> 65000 | P7: =INDEX($H$15:$H$18,MATCH(C7,$A$15:$A$18,0)) -> 0 | Q7: =INDEX($H$15:$H$18,MATCH(D7,$A$15:$A$18,0)) -> 0 | R7: =IF(G7="Panama",Canal_Tolls!$C$20,IF(G7="Suez",Canal_Tolls!$C$45,0)) -> 213460 | S7: =IF(G7="Panama",Canal_Tolls!$D$20,IF(G7="Suez",Canal_Tolls!$D$45,0)) -> 186460 | T7: =INDEX($E$15:$E$18,MATCH(C7,$A$15:$A$18,0)) -> 0 | U7: =INDEX($E$15:$E$18,MATCH(D7,$A$15:$A$18,0)) -> 0 | V7: =INDEX($F$15:$F$18,MATCH(C7,$A$15:$A$18,0)) -> 0 | W7: =INDEX($F$15:$F$18,MATCH(D7,$A$15:$A$18,0)) -> 0 | X7: =INDEX($G$15:$G$18,MATCH(C7,$A$15:$A$18,0)) -> 0.6 | Y7: =INDEX($G$15:$G$18,MATCH(D7,$A$15:$A$18,0)) -> 0
A8: 3 | B8: ARA-India WC via Suez | C8: ARA | D8: IND | E8: 6350 | F8: 450 | G8: Suez | H8: 1 | I8: 0.5 | J8: 75 | K8: 55 | L8: =INDEX($C$15:$C$18,MATCH(C8,$A$15:$A$18,0)) -> 3.5 | M8: =INDEX($C$15:$C$18,MATCH(D8,$A$15:$A$18,0)) -> 4 | N8: =INDEX($D$15:$D$18,MATCH(C8,$A$15:$A$18,0)) -> 44845.748 | O8: =INDEX($D$15:$D$18,MATCH(D8,$A$15:$A$18,0)) -> 55000 | P8: =INDEX($H$15:$H$18,MATCH(C8,$A$15:$A$18,0)) -> 1 | Q8: =INDEX($H$15:$H$18,MATCH(D8,$A$15:$A$18,0)) -> 0 | R8: =IF(G8="Panama",Canal_Tolls!$C$20,IF(G8="Suez",Canal_Tolls!$C$45,0)) -> 376008 | S8: =IF(G8="Panama",Canal_Tolls!$D$20,IF(G8="Suez",Canal_Tolls!$D$45,0)) -> 330256.5 | T8: =INDEX($E$15:$E$18,MATCH(C8,$A$15:$A$18,0)) -> 0.655776 | U8: =INDEX($E$15:$E$18,MATCH(D8,$A$15:$A$18,0)) -> 0 | V8: =INDEX($F$15:$F$18,MATCH(C8,$A$15:$A$18,0)) -> 20542.511 | W8: =INDEX($F$15:$F$18,MATCH(D8,$A$15:$A$18,0)) -> 0 | X8: =INDEX($G$15:$G$18,MATCH(C8,$A$15:$A$18,0)) -> 0 | Y8: =INDEX($G$15:$G$18,MATCH(D8,$A$15:$A$18,0)) -> 0
A9: 4 | B9: ARA-India WC via Cape | C9: ARA | D9: IND | E9: 10850 | F9: 450 | G9: None | H9: 0 | I9: 0.5 | J9: 75 | K9: 55 | L9: =INDEX($C$15:$C$18,MATCH(C9,$A$15:$A$18,0)) -> 3.5 | M9: =INDEX($C$15:$C$18,MATCH(D9,$A$15:$A$18,0)) -> 4 | N9: =INDEX($D$15:$D$18,MATCH(C9,$A$15:$A$18,0)) -> 44845.748 | O9: =INDEX($D$15:$D$18,MATCH(D9,$A$15:$A$18,0)) -> 55000 | P9: =INDEX($H$15:$H$18,MATCH(C9,$A$15:$A$18,0)) -> 1 | Q9: =INDEX($H$15:$H$18,MATCH(D9,$A$15:$A$18,0)) -> 0 | R9: =IF(G9="Panama",Canal_Tolls!$C$20,IF(G9="Suez",Canal_Tolls!$C$45,0)) -> 0 | S9: =IF(G9="Panama",Canal_Tolls!$D$20,IF(G9="Suez",Canal_Tolls!$D$45,0)) -> 0 | T9: =INDEX($E$15:$E$18,MATCH(C9,$A$15:$A$18,0)) -> 0.655776 | U9: =INDEX($E$15:$E$18,MATCH(D9,$A$15:$A$18,0)) -> 0 | V9: =INDEX($F$15:$F$18,MATCH(C9,$A$15:$A$18,0)) -> 20542.511 | W9: =INDEX($F$15:$F$18,MATCH(D9,$A$15:$A$18,0)) -> 0 | X9: =INDEX($G$15:$G$18,MATCH(C9,$A$15:$A$18,0)) -> 0 | Y9: =INDEX($G$15:$G$18,MATCH(D9,$A$15:$A$18,0)) -> 0
B10: Distances: approximate great-circle/standard routeing figures (Houston-Rotterdam ~5,000 nm; Houston-Ulsan via Panama ~9,650 nm; Rotterdam-Mumbai ~6,350 nm via Suez / ~10,850 nm via Cape). Verify with a distance table (e.g., Netpas, BP Shipping Marine Distances).
A13: PORT REGIONS — port cost per operation = fixed + MIN(cargo tonnes x cargo rate, cap) + dockage (Port_Tariffs sheet)
A14: Code | B14: Region | C14: Port days per operation (incl. waiting) | D14: Fixed cost per op ($) | E14: Cargo rate ($/t) | F14: Cargo cap ($) | G14: Berth-day share | H14: EU port (1/0) | I14: Basis
A15: USG | B15: US Gulf (Houston) | C15: 5 | D15: =Port_Tariffs!$C$14 -> 45813.4 | E15: 0 | F15: 0 | G15: =Port_Tariffs!$C$11 -> 0.6 | H15: 0 | I15: PUBLISHED: Port Houston Tariff 14 harbor fee + LOA-based dockage (see Port_Tariffs). Pilotage, tugs, linesmen, agency and private-terminal charges are an estimate.
A16: ARA | B16: Amsterdam-Rotterdam-Antwerp | C16: 3.5 | D16: =Port_Tariffs!$C$29 -> 44845.748 | E16: =Port_Tariffs!$C$30 -> 0.655776 | F16: =Port_Tariffs!$C$31 -> 20542.511 | G16: 0 | H16: 1 | I16: PUBLISHED: Port of Rotterdam seaport dues — GT component + cargo component (capped) + sustainability component, 2025 schedule indexed 3.5% for 2026. Pilotage, tugs, boatmen and agency are an estimate.
A17: FEA | B17: Far East Asia (Korea/China) | C17: 3.5 | D17: 65000 | E17: 0 | F17: 0 | G17: 0 | H17: 0 | I17: ESTIMATE for Korea/China discharge — no published schedule transcribed.
A18: IND | B18: India West Coast | C18: 4 | D18: 55000 | E18: 0 | F18: 0 | G18: 0 | H18: 0 | I18: ESTIMATE for Kandla/Mumbai/JNPT discharge — no published schedule transcribed.

Sheet Port_Tariffs
A1: Port cost build-up from published tariffs
A2: Independent analysis using publicly available data. Not affiliated with or endorsed by any organization named.
A3: Blue cells are published tariff rates (sources named in column E) or estimated ancillary costs. Only the US Gulf and ARA legs have transcribed published schedules; Far East and India are lump-sum estimates.
A5: PORT HOUSTON — Tariff No. 14, effective 1 January 2025
A6: Source: porthouston.com/toolbox/rates/tariffs (Tariff 14 PDF), Subrules 095 (dockage) and 096 (harbor fee)
A7: Item | C7: Value | E7: Source / note
A8: Harbor fee, vessels 250 ft and over | C8: 813.4 | E8: Subrule 096, per entry into the Port Authority's jurisdictional limits. Published rate.
A9: Dockage rate, LOA 600-650 ft band | C9: 11.24 | E9: Subrule 095, $ per foot of LOA per 24 hours. Published rate. Applies at Port Authority wharves; private liquid terminals set their own dockage.
A10: Length overall (feet) | C10: =LOA_ft -> 600 | E10: From Inputs.
A11: Share of port days alongside (rest is waiting) | C11: 0.6 | E11: ESTIMATE. Waiting at anchorage incurs no dockage, so only berth time is charged.
A12: Berth days per operation, at the active port-time case | C12: =Routes!$C$15*C11*PortMult -> 3 | E12: Region port days x berth share x port-time multiplier.
A13: Dockage day-factor (tariff taper) | C13: =IF(C12<=2,C12,IF(C12<=3,2+0.9*(C12-2),IF(C12<=4,2.9+0.75*(C12-3),IF(C12<=5,3.65+0.6*(C12-4),4.25+0.5*(C12-5))))) -> 2.9 | E13: Subrule 095: days 1-2 at full rate, day 3 at 90%, day 4 at 75%, day 5 at 60%, day 6+ at 50%.
A14: FIXED cost per operation (harbor fee + ancillary) | C14: =C8+C15 -> 45813.4 | E14: Dockage is added per operation inside the model, because it moves with the congestion case.
A15: Ancillary: pilotage in/out, tugs, linesmen, agency, terminal | C15: 45000 | E15: ESTIMATE — replace with an agency proforma disbursement account.
A16: Illustrative dockage at the active case | C16: =LOA_ft*C9*C13 -> 19557.6 | E16: For reference; the model computes this per operation.
A20: PORT OF ROTTERDAM (ARA) — seaport dues, 2025 schedule indexed for 2026
A21: Source: Port of Rotterdam 'General terms and conditions including port tariffs', Annex 1 Tables 1-3 and the 133.3% chemical-tanker efficiency cap; portofrotterdam.com/en/port-dues-tariffs
A22: Item | C22: Value | E22: Source / note
A23: GT tariff, chemical/gas tanker (EUR per GT) | C23: 0.303 | E23: Table 1, rate type C. Published rate.
A24: Sustainability component (EUR per GT) | C24: 0.065 | E24: Table 3. No ESI or Green Award discount assumed — a Green Award certificate would cut this component by 70%.
A25: Cargo rate, other liquid bulk (EUR per tonne) | C25: 0.576 | E25: Table 2, commodity type 07. Published rate.
A26: Cargo-component cap, chemical tankers | C26: 1.333 | E26: Efficiency discount: cargo dues capped at GT x 133.3% x cargo rate. Published rule.
A27: 2026 indexation | C27: 1.035 | E27: Port of Rotterdam published a 3.5% indexation of port tariffs for 2026; applied to the 2025 schedule.
A28: Ancillary: pilotage, tugs, boatmen, agency, terminal | C28: 35000 | E28: ESTIMATE — replace with an agency proforma disbursement account.
A29: FIXED cost per operation ($) | C29: =GT*(C23+C24)*C27*FX+C28 -> 44845.748 | E29: Vessel and sustainability components, converted at the USD/EUR rate on Inputs.
A30: Cargo rate per tonne ($) | C30: =C25*C27*FX -> 0.655776 | E30: Applied to the tonnes loaded or discharged at this port.
A31: Cargo-component cap ($) | C31: =GT*C26*C25*C27*FX -> 20542.511
A32: Illustrative dues, 30,600 t discharge | C32: =C29-C28+MIN(30600*C30,C31) -> 29912.494 | E32: Sanity check against the worked example in the port's own annex.
A36: FAR EAST AND INDIA — no published schedule transcribed; lump-sum estimates on the Routes sheet.

Sheet Canal_Tolls
A1: Canal toll build-up (per transit)
A2: Independent analysis using publicly available data. Not affiliated with or endorsed by any organization named.
A3: Tariff values in blue are taken from the supplied extracts of official schedules (see data/README.md). Vessel tonnages and ancillaries are estimates.
A5: PANAMA CANAL — 'Super' vessel (beam > 91 ft), chemical tanker
A6: Item | B6: Tariff | C6: Laden ($) | D6: Ballast ($) | F6: Source / note
A7: Fixed tariff per transit (1010.FS01) | B7: 100000 | C7: =B7 -> 100000 | D7: =B7*$B$18 -> 85000 | F7: ACP tariff schedule; ballast pays 85% (1010.BA01)
A8: Capacity tariff per PC/UMS t, chemical (1010.QS01) | B8: 4 | C8: =B8*PCUMS -> 80000 | D8: =B8*PCUMS*$B$18 -> 68000 | F8: ACP tariff schedule x PC/UMS (Inputs)
A9: Mandatory tug, complete transit (Panamax locks) | B9: 7000 | C9: =B9 -> 7000 | D9: =B9 -> 7000 | F9: ACP schedule (regular-vessel rate used as proxy)
A10: Linehandling per linehandler (Panamax locks) | B10: 270 | C10: =B10*Linehandlers -> 2160 | D10: =B10*Linehandlers -> 2160 | F10: ACP schedule x linehandler count (Inputs)
A11: Transit reservation (Panamax) | B11: 10500 | C11: =B11 -> 10500 | D11: =B11 -> 10500 | F11: ACP schedule; optional in practice, included as base
A12: Security charge (PC/UMS >= 3,000) | B12: 1250 | C12: =B12 -> 1250 | D12: =B12 -> 1250 | F12: ACP schedule
A13: Fresh water surcharge, fixed (LOA > 91.44 m) | B13: 10000 | C13: =B13 -> 10000 | D13: =B13 -> 10000 | F13: ACP schedule; variable portion omitted
A14: Port pilotage, per call (x2: each end) | B14: 1275 | C14: =B14*2 -> 2550 | D14: =B14*2 -> 2550 | F14: ACP schedule
A18: Ballast factor (1010.BA01) | B18: 0.85
A20: Panama total per transit | C20: =SUM(C7:C14) -> 213460 | D20: =SUM(D7:D14) -> 186460
A24: SUEZ CANAL — petroleum-product-tanker bands (SDR per SCNT), Circular 7/2023
A25: Band | B25: Band size (SCNT) | C25: Laden SDR/t | D25: Ballast SDR/t | E25: SCNT in band | F25: Note
A26: First 5,000 | B26: 5000 | C26: 11.04 | D26: 9.4 | E26: =MAX(0,MIN(B26,SCNT-0)) -> 5000 | F26: Source: SCA Circular 7/2023 (eff. 15-Jan-2024) via shipping-agent mirror; see data/README.md
A27: Next 5,000 | B27: 5000 | C27: 7.82 | D27: 6.64 | E27: =MAX(0,MIN(B27,SCNT-SUM($B$26:B26))) -> 5000
A28: Next 10,000 | B28: 10000 | C28: 5.91 | D28: 5.04 | E28: =MAX(0,MIN(B28,SCNT-SUM($B$26:B27))) -> 10000
A29: Next 20,000 | B29: 20000 | C29: 3.93 | D29: 2.5 | E29: =MAX(0,MIN(B29,SCNT-SUM($B$26:B28))) -> 0
A30: Next 30,000 | B30: 30000 | C30: 3.84 | D30: 2.14 | E30: =MAX(0,MIN(B30,SCNT-SUM($B$26:B29))) -> 0
A31: Next 50,000 | B31: 50000 | C31: 3.46 | D31: 1.85 | E31: =MAX(0,MIN(B31,SCNT-SUM($B$26:B30))) -> 0
A32: The rest | B32: 1000000000 | C32: 3.34 | D32: 1.82 | E32: =MAX(0,MIN(B32,SCNT-SUM($B$26:B31))) -> 0
C34: Laden | D34: Ballast
A35: Base dues (SDR) | C35: =SUMPRODUCT(C26:C32,$E$26:$E$32) -> 153400 | D35: =SUMPRODUCT(D26:D32,$E$26:$E$32) -> 130600
A36: Tanker surcharge | C36: =SuezSurL -> 0.2 | D36: =SuezSurB -> 0.15 | F36: Chemical-tanker surcharge per safety4sea reporting of the same circular; bands are the product-tanker schedule (closest published proxy).
A37: Dues incl. surcharge (SDR) | C37: =C35*(1+C36) -> 184080 | D37: =D35*(1+D36) -> 150190
A38: USD per SDR | C38: =SDR_USD -> 1.35 | D38: =SDR_USD -> 1.35
A39: Transit dues ($) | C39: =C37*C38 -> 248508 | D39: =D37*D38 -> 202756.5
A40: Ancillaries: pilotage, tugs, mooring, agency ($, estimate) | C40: =SuezAnc -> 40000 | D40: =SuezAnc -> 40000
A41: War-risk additional premium ($, illustrative) | C41: =WarAP*HullValue -> 87500 | D41: =WarAP*HullValue -> 87500
A45: Suez total per transit | C45: =SUM(C39:C41) -> 376008 | D45: =SUM(D39:D41) -> 330256.5

Sheet Voyage_PnL
A1: Voyage P&L — Time Charter Equivalent build-up (active scenario)
A2: Independent analysis using publicly available data. Not affiliated with or endorsed by any organization named.
A3: Change scenario switches on the Inputs sheet. All values are formulas.
F6: ROUTE COMPARISON — active levers applied to every route
A7: SCENARIO | F7: Route | G7: Days | H7: Gross freight | I7: Bunkers | J7: Port | K7: Canal | L7: EU ETS | M7: Misc | N7: TCE $/day | O7: Result $ | P7: Break-even FH $/t
A8: Route | B8: =INDEX(Routes!$B$6:$B$9,Sw_Route) -> USG-ARA transatlantic | F8: =INDEX(Routes!$B$6:$B$9,1) -> USG-ARA transatlantic | G8: =Engine!AJ36 -> 49.407407 | H8: =Engine!AG36 -> 2275200 | I8: =Engine!Y36 -> 652340.34 | J8: =Engine!Z36 -> 252304.21 | K8: =Engine!AA36 -> 0 | L8: =Engine!AB36 -> 123936.41 | M8: =MiscVoy -> 25000 | N8: =Engine!AK36 -> 23574.178 | O8: =Engine!AL36 -> 275405.7 | P8: =Engine!AM36 -> 42.76904
A9: Brent / VLSFO / MGO | B9: =Brent -> 82.01 | C9: =TEXT(Brent*VLSFO_Mult,"$#,##0")&" / "&TEXT(Brent*MGO_Mult,"$#,##0")&" per t" -> $631 / $795 per t | D9: $/bbl; bunker $/t derived | F9: =INDEX(Routes!$B$6:$B$9,2) -> USG-Far East via Panama | G9: =Engine!AJ37 -> 82.546296 | H9: =Engine!AG37 -> 3751200 | I9: =Engine!Y37 -> 1167607.1 | J9: =Engine!Z37 -> 260742 | K9: =Engine!AA37 -> 426920 | L9: =Engine!AB37 -> 0 | M9: =MiscVoy -> 25000 | N9: =Engine!AK37 -> 21529.141 | O9: =Engine!AL37 -> 291317.54 | P9: =Engine!AM37 -> 82.235712
A10: Freight multiplier / port-time multiplier | B10: =FreightMult -> 1 | C10: =PortMult -> 1 | F10: =INDEX(Routes!$B$6:$B$9,3) -> ARA-India WC via Suez | G10: =Engine!AJ38 -> 58.157407 | H10: =Engine!AG38 -> 3285000 | I10: =Engine!Y38 -> 795786.09 | J10: =Engine!Z38 -> 231562.21 | K10: =Engine!AA38 -> 752016 | L10: =Engine!AB38 -> 154150.49 | M10: =MiscVoy -> 25000 | N10: =Engine!AK38 -> 21396.418 | O10: =Engine!AL38 -> 197526.88 | P10: =Engine!AM38 -> 68.379357
A11: Utilization fronthaul / backhaul | B11: =UtilFH -> 0.85 | C11: =UtilBH -> 0.5 | F11: =INDEX(Routes!$B$6:$B$9,4) -> ARA-India WC via Cape | G11: =Engine!AJ39 -> 85.324074 | H11: =Engine!AG39 -> 3285000 | I11: =Engine!Y39 -> 1283528.3 | J11: =Engine!Z39 -> 231562.21 | K11: =Engine!AA39 -> 0 | L11: =Engine!AB39 -> 255306.83 | M11: =MiscVoy -> 25000 | N11: =Engine!AK39 -> 16495.669 | O11: =Engine!AL39 -> -128355.63 | P11: =Engine!AM39 -> 79.302183
A13: VOYAGE TIME | B13: Days
A14: Distance per leg (nm) | B14: =INDEX(Routes!$E$6:$E$9,Sw_Route) -> 5000 | D14: Routes sheet
A15: Sea days, fronthaul | B15: =B14*(1+SeaMargin)/(Speed*24) -> 16.203704 | D15: distance x (1 + sea margin) / (speed x 24)
A16: Sea days, backhaul | B16: =B15 -> 16.203704 | D16: same distance
A17: Port days, region A | B17: =INDEX(Routes!$L$6:$L$9,Sw_Route)*(1+IF(UtilBH>0,1,0))*PortMult -> 10 | D17: days per operation x operations x port-time multiplier
A18: Port days, region B | B18: =INDEX(Routes!$M$6:$M$9,Sw_Route)*(1+IF(UtilBH>0,1,0))*PortMult -> 7 | D18: an operation = a load or a discharge; a backhaul cargo adds one at each end
A19: Canal days | B19: =INDEX(Routes!$H$6:$H$9,Sw_Route)*2 -> 0 | D19: two transits
A20: Total voyage days | B20: =SUM(B15:B19) -> 49.407407
A22: REVENUE | B22: $
A23: Fronthaul cargo (t) x rate ($/t) | B23: =Capacity*UtilFH -> 30600 | C23: =INDEX(Routes!$J$6:$J$9,Sw_Route)*FreightMult -> 52 | D23: B = tonnes, C = $/t
A24: Backhaul cargo (t) x rate ($/t) | B24: =Capacity*UtilBH -> 18000 | C24: =INDEX(Routes!$K$6:$K$9,Sw_Route)*FreightMult -> 38
A25: Gross freight | B25: =B23*C23+B24*C24 -> 2275200
A26: Less: commissions | B26: =-B25*Commission -> -56880 | D26: address + brokerage
A27: Net freight | B27: =B25+B26 -> 2218320
A29: VOYAGE COSTS | B29: $ | C29: t
A30: Speed factor (consumption vs reference) | B30: =(Speed/RefSpeed)^SpeedExp -> 1 | D30: cube law
A31: Sea fuel, both legs (t) | B31: =B15*B30*ConsLaden+B16*B30*IF(UtilBH>0,ConsLaden,ConsBallast) -> 875
A32: ECA share of sea miles | B32: =INDEX(Routes!$F$6:$F$9,Sw_Route)/B14 -> 0.13 | D32: burns MGO
A33: VLSFO cost (sea, outside ECA) | B33: =C33*Brent*VLSFO_Mult -> 480711.87 | C33: =B31*(1-B32) -> 761.25 | D33: C = tonnes
A34: MGO cost (ECA + port + canal) | B34: =C34*Brent*MGO_Mult -> 171628.48 | C34: =B31*B32+(B17+B18+B19)*ConsPort -> 215.75 | D34: C = tonnes
A35: Port disbursements | B35: =(INDEX(Routes!$N$6:$N$9,Sw_Route)+LOA_ft*Port_Tariffs!$C$9*IF((INDEX(Routes!$L$6:$L$9,Sw_Route)*INDEX(Routes!$X$6:$X$9,Sw_Route)*PortMult)<=2,(INDEX(Routes!$L$6:$L$9,Sw_Route)*INDEX(Routes!$X$6:$X$9,Sw_Route)*PortMult),IF((INDEX(Routes!$L$6:$L$9,Sw_Route)*INDEX(Routes!$X$6:$X$9,Sw_Route)*PortMult)<=3,2+0.9*((INDEX(Routes!$L$6:$L$9,Sw_Route)*INDEX(Routes!$X$6:$X$9,Sw_Route)*PortMult)-2),IF((INDEX(Routes!$L$6:$L$9,Sw_Route)*INDEX(Routes!$X$6:$X$9,Sw_Route)*PortMult)<=4,2.9+0.75*((INDEX(Routes!$L$6:$L$9,Sw_Route)*INDEX(Routes!$X$6:$X$9,Sw_Route)*PortMult)-3),IF((INDEX(Routes!$L$6:$L$9,Sw_Route)*INDEX(Routes!$X$6:$X$9,Sw_Route)*PortMult)<=5,3.65+0.6*((INDEX(Routes!$L$6:$L$9,Sw_Route)*INDEX(Routes!$X$6:$X$9,Sw_Route)*PortMult)-4),4.25+0.5*((INDEX(Routes!$L$6:$L$9,Sw_Route)*INDEX(Routes!$X$6:$X$9,Sw_Route)*PortMult)-5)))))+MIN(B23*INDEX(Routes!$T$6:$T$9,Sw_Route),INDEX(Routes!$V$6:$V$9,Sw_Route))+INDEX(Routes!$O$6:$O$9,Sw_Route)+LOA_ft*Port_Tariffs!$C$9*IF((INDEX(Routes!$M$6:$M$9,Sw_Route)*INDEX(Routes!$Y$6:$Y$9,Sw_Route)*PortMult)<=2,(INDEX(Routes!$M$6:$M$9,Sw_Route)*INDEX(Routes!$Y$6:$Y$9,Sw_Route)*PortMult),IF((INDEX(Routes!$M$6:$M$9,Sw_Route)*INDEX(Routes!$Y$6:$Y$9,Sw_Route)*PortMult)<=3,2+0.9*((INDEX(Routes!$M$6:$M$9,Sw_Route)*INDEX(Routes!$Y$6:$Y$9,Sw_Route)*PortMult)-2),IF((INDEX(Routes!$M$6:$M$9,Sw_Route)*INDEX(Routes!$Y$6:$Y$9,Sw_Route)*PortMult)<=4,2.9+0.75*((INDEX(Routes!$M$6:$M$9,Sw_Route)*INDEX(Routes!$Y$6:$Y$9,Sw_Route)*PortMult)-3),IF((INDEX(Routes!$M$6:$M$9,Sw_Route)*INDEX(Routes!$Y$6:$Y$9,Sw_Route)*PortMult)<=5,3.65+0.6*((INDEX(Routes!$M$6:$M$9,Sw_Route)*INDEX(Routes!$Y$6:$Y$9,Sw_Route)*PortMult)-4),4.25+0.5*((INDEX(Routes!$M$6:$M$9,Sw_Route)*INDEX(Routes!$Y$6:$Y$9,Sw_Route)*PortMult)-5)))))+MIN(B23*INDEX(Routes!$U$6:$U$9,Sw_Route),INDEX(Routes!$W$6:$W$9,Sw_Route))+IF(UtilBH>0,INDEX(Routes!$N$6:$N$9,Sw_Route)+LOA_ft*Port_Tariffs!$C$9*IF((INDEX(Routes!$L$6:$L$9,Sw_Route)*INDEX(Routes!$X$6:$X$9,Sw_Route)*PortMult)<=2,(INDEX(Routes!$L$6:$L$9,Sw_Route)*INDEX(Routes!$X$6:$X$9,Sw_Route)*PortMult),IF((INDEX(Routes!$L$6:$L$9,Sw_Route)*INDEX(Routes!$X$6:$X$9,Sw_Route)*PortMult)<=3,2+0.9*((INDEX(Routes!$L$6:$L$9,Sw_Route)*INDEX(Routes!$X$6:$X$9,Sw_Route)*PortMult)-2),IF((INDEX(Routes!$L$6:$L$9,Sw_Route)*INDEX(Routes!$X$6:$X$9,Sw_Route)*PortMult)<=4,2.9+0.75*((INDEX(Routes!$L$6:$L$9,Sw_Route)*INDEX(Routes!$X$6:$X$9,Sw_Route)*PortMult)-3),IF((INDEX(Routes!$L$6:$L$9,Sw_Route)*INDEX(Routes!$X$6:$X$9,Sw_Route)*PortMult)<=5,3.65+0.6*((INDEX(Routes!$L$6:$L$9,Sw_Route)*INDEX(Routes!$X$6:$X$9,Sw_Route)*PortMult)-4),4.25+0.5*((INDEX(Routes!$L$6:$L$9,Sw_Route)*INDEX(Routes!$X$6:$X$9,Sw_Route)*PortMult)-5)))))+MIN(B24*INDEX(Routes!$T$6:$T$9,Sw_Route),INDEX(Routes!$V$6:$V$9,Sw_Route))+INDEX(Routes!$O$6:$O$9,Sw_Route)+LOA_ft*Port_Tariffs!$C$9*IF((INDEX(Routes!$M$6:$M$9,Sw_Route)*INDEX(Routes!$Y$6:$Y$9,Sw_Route)*PortMult)<=2,(INDEX(Routes!$M$6:$M$9,Sw_Route)*INDEX(Routes!$Y$6:$Y$9,Sw_Route)*PortMult),IF((INDEX(Routes!$M$6:$M$9,Sw_Route)*INDEX(Routes!$Y$6:$Y$9,Sw_Route)*PortMult)<=3,2+0.9*((INDEX(Routes!$M$6:$M$9,Sw_Route)*INDEX(Routes!$Y$6:$Y$9,Sw_Route)*PortMult)-2),IF((INDEX(Routes!$M$6:$M$9,Sw_Route)*INDEX(Routes!$Y$6:$Y$9,Sw_Route)*PortMult)<=4,2.9+0.75*((INDEX(Routes!$M$6:$M$9,Sw_Route)*INDEX(Routes!$Y$6:$Y$9,Sw_Route)*PortMult)-3),IF((INDEX(Routes!$M$6:$M$9,Sw_Route)*INDEX(Routes!$Y$6:$Y$9,Sw_Route)*PortMult)<=5,3.65+0.6*((INDEX(Routes!$M$6:$M$9,Sw_Route)*INDEX(Routes!$Y$6:$Y$9,Sw_Route)*PortMult)-4),4.25+0.5*((INDEX(Routes!$M$6:$M$9,Sw_Route)*INDEX(Routes!$Y$6:$Y$9,Sw_Route)*PortMult)-5)))))+MIN(B24*INDEX(Routes!$U$6:$U$9,Sw_Route),INDEX(Routes!$W$6:$W$9,Sw_Route)),0))*PortCostMult -> 252304.21 | D35: Published Port Houston / Rotterdam tariffs + estimated ancillaries (Port_Tariffs sheet)
A36: Canal tolls & transit costs | B36: =INDEX(Routes!$R$6:$R$9,Sw_Route)+IF(UtilBH>0,INDEX(Routes!$R$6:$R$9,Sw_Route),INDEX(Routes!$S$6:$S$9,Sw_Route)) -> 0 | D36: Canal_Tolls sheet
A37: EU ETS allowances | B37: =((C33*CO2_VLSFO+B31*B32*CO2_MGO)*INDEX(Routes!$I$6:$I$9,Sw_Route)+(B17*INDEX(Routes!$P$6:$P$9,Sw_Route)+B18*INDEX(Routes!$Q$6:$Q$9,Sw_Route))*ConsPort*CO2_MGO)*PhaseIn*EUA*FX -> 123936.41 | D37: 50% of extra-EU voyage emissions + 100% at EU berth
A38: Misc. voyage costs | B38: =MiscVoy -> 25000
A39: Total voyage costs | B39: =SUM(B33:B38) -> 1053581
A41: RESULT
A42: Voyage net revenue (net freight - voyage costs) | B42: =B27-B39 -> 1164739
A43: TIME CHARTER EQUIVALENT ($/day) | B43: =B42/B20 -> 23574.178 | D43: the headline commercial metric
A44: Daily vessel cost benchmark ($/day) | B44: =Benchmark -> 18000 | D44: OPEX + capital, or T/C-in hire
A45: TCE margin over benchmark ($/day) | B45: =B43-B44 -> 5574.1784
A46: Voyage result after vessel cost ($) | B46: =B45*B20 -> 275405.7
A47: Break-even fronthaul freight rate ($/t) | B47: =((B44*B20+B39)/(1-Commission)-B24*C24)/B23 -> 42.76904 | D47: rate at which TCE = benchmark
A48: Headroom: base fronthaul rate vs break-even | B48: =C23/B47-1 -> 0.21583277 | D48: how far the rate can fall before the voyage stops covering vessel cost
A50: COST STRUCTURE (% of total voyage costs)
A51: Bunkers | B51: =(B33+B34)/B39 -> 0.61916489
A52: Port | B52: =B35/B39 -> 0.23947301
A53: Canal | B53: =B36/B39 -> 0
A54: EU ETS | B54: =B37/B39 -> 0.11763349
A55: Misc | B55: =B38/B39 -> 0.023728599
A56: Voyage costs as % of net freight | B56: =B39/B27 -> 0.47494544
A58: MODEL CHECK
A59: Engine TCE (active-scenario row) | B59: =Engine!AK7 -> 23574.178
A60: Difference (must be 0) | B60: =ROUND(B43-B59,6) -> 0 | C60: =IF(B60=0,"OK","CHECK") -> OK

Sheet Sensitivity
A1: Sensitivity — what drives TCE?
A2: Independent analysis using publicly available data. Not affiliated with or endorsed by any organization named.
A3: Tornado: each lever moved across a plausible range with everything else at the active scenario. Freight and Brent ranges are data-derived (Data_PPI, Data_Brent); the rest are judgment bands.
A5: Base TCE (active scenario) | B5: =Engine!AK7 -> 23574.178
A7: A. Tornado input table (unsorted)
A8: Lever | B8: Low value | C8: High value | D8: Unit | E8: TCE at low | F8: TCE at high | G8: Swing $/day | H8: Sort key
A9: Freight rate (market) | B9: =Engine!E9 -> 0.91 | C9: =Engine!E10 -> 1.25 | D9: x base rate | E9: =Engine!AK9 -> 19533.311 | F9: =Engine!AK10 -> 34798.811 | G9: =ABS(F9-E9) -> 15265.5 | H9: =G9+ROW()/1000000 -> 15265.5
A10: Bunker price (Brent) | B10: =Engine!D11 -> 67.98 | C10: =Engine!D12 -> 104.84 | D10: $/bbl | E10: =Engine!AK11 -> 25832.954 | F10: =Engine!AK12 -> 19898.637 | G10: =ABS(F10-E10) -> 5934.3163 | H10: =G10+ROW()/1000000 -> 5934.3163
A11: Port time (congestion) | B11: =Engine!F13 -> 0.75 | C11: =Engine!F14 -> 1.75 | D11: x base port days | E11: =Engine!AK13 -> 26505.193 | F11: =Engine!AK14 -> 17305.373 | G11: =ABS(F11-E11) -> 9199.8201 | H11: =G11+ROW()/1000000 -> 9199.8202
A12: Fronthaul utilization | B12: =Engine!G15 -> 0.7 | C12: =Engine!G16 -> 0.95 | D12: % capacity | E12: =Engine!AK15 -> 18104.577 | F12: =Engine!AK16 -> 27258.732 | G12: =ABS(F12-E12) -> 9154.1546 | H12: =G12+ROW()/1000000 -> 9154.1546
A13: Backhaul utilization | B13: =Engine!H17 -> 0.25 | C13: =Engine!H18 -> 0.75 | D13: % capacity | E13: =Engine!AK17 -> 16944.646 | F13: =Engine!AK18 -> 30203.711 | G13: =ABS(F13-E13) -> 13259.065 | H13: =G13+ROW()/1000000 -> 13259.065
A14: Service speed | B14: =Engine!I19 -> 12 | C14: =Engine!I20 -> 14.5 | D14: knots | E14: =Engine!AK19 -> 24473.272 | F14: =Engine!AK20 -> 22463.307 | G14: =ABS(F14-E14) -> 2009.9644 | H14: =G14+ROW()/1000000 -> 2009.9644
A15: Port disbursements | B15: =Engine!J21 -> 0.75 | C15: =Engine!J22 -> 1.25 | D15: x base | E15: =Engine!AK21 -> 24850.83 | F15: =Engine!AK22 -> 22297.527 | G15: =ABS(F15-E15) -> 2553.3035 | H15: =G15+ROW()/1000000 -> 2553.3035
A16: EU carbon price (EUA) | B16: =Engine!K23 -> 50 | C16: =Engine!K24 -> 110 | D16: EUR/t | E16: =Engine!AK23 -> 24410.331 | F16: =Engine!AK24 -> 22403.565 | G16: =ABS(F16-E16) -> 2006.7664 | H16: =G16+ROW()/1000000 -> 2006.7665
A19: B. Tornado — ranked by swing (chart source)
A20: Lever | B20: Low -> TCE change | C20: High -> TCE change | D20: Swing $/day | E20: Low value | F20: High value | G20: Rank
A21: =INDEX($A$9:$A$16,MATCH(LARGE($H$9:$H$16,1),$H$9:$H$16,0)) -> Freight rate (market) | B21: =INDEX($E$9:$E$16,MATCH(LARGE($H$9:$H$16,1),$H$9:$H$16,0))-$B$5 -> -4040.8678 | C21: =INDEX($F$9:$F$16,MATCH(LARGE($H$9:$H$16,1),$H$9:$H$16,0))-$B$5 -> 11224.633 | D21: =INDEX($G$9:$G$16,MATCH(LARGE($H$9:$H$16,1),$H$9:$H$16,0)) -> 15265.5 | E21: =INDEX($B$9:$B$16,MATCH(LARGE($H$9:$H$16,1),$H$9:$H$16,0)) -> 0.91 | F21: =INDEX($C$9:$C$16,MATCH(LARGE($H$9:$H$16,1),$H$9:$H$16,0)) -> 1.25 | G21: 1
A22: =INDEX($A$9:$A$16,MATCH(LARGE($H$9:$H$16,2),$H$9:$H$16,0)) -> Backhaul utilization | B22: =INDEX($E$9:$E$16,MATCH(LARGE($H$9:$H$16,2),$H$9:$H$16,0))-$B$5 -> -6629.5326 | C22: =INDEX($F$9:$F$16,MATCH(LARGE($H$9:$H$16,2),$H$9:$H$16,0))-$B$5 -> 6629.5326 | D22: =INDEX($G$9:$G$16,MATCH(LARGE($H$9:$H$16,2),$H$9:$H$16,0)) -> 13259.065 | E22: =INDEX($B$9:$B$16,MATCH(LARGE($H$9:$H$16,2),$H$9:$H$16,0)) -> 0.25 | F22: =INDEX($C$9:$C$16,MATCH(LARGE($H$9:$H$16,2),$H$9:$H$16,0)) -> 0.75 | G22: 2
A23: =INDEX($A$9:$A$16,MATCH(LARGE($H$9:$H$16,3),$H$9:$H$16,0)) -> Port time (congestion) | B23: =INDEX($E$9:$E$16,MATCH(LARGE($H$9:$H$16,3),$H$9:$H$16,0))-$B$5 -> 2931.0148 | C23: =INDEX($F$9:$F$16,MATCH(LARGE($H$9:$H$16,3),$H$9:$H$16,0))-$B$5 -> -6268.8053 | D23: =INDEX($G$9:$G$16,MATCH(LARGE($H$9:$H$16,3),$H$9:$H$16,0)) -> 9199.8201 | E23: =INDEX($B$9:$B$16,MATCH(LARGE($H$9:$H$16,3),$H$9:$H$16,0)) -> 0.75 | F23: =INDEX($C$9:$C$16,MATCH(LARGE($H$9:$H$16,3),$H$9:$H$16,0)) -> 1.75 | G23: 3
A24: =INDEX($A$9:$A$16,MATCH(LARGE($H$9:$H$16,4),$H$9:$H$16,0)) -> Fronthaul utilization | B24: =INDEX($E$9:$E$16,MATCH(LARGE($H$9:$H$16,4),$H$9:$H$16,0))-$B$5 -> -5469.6011 | C24: =INDEX($F$9:$F$16,MATCH(LARGE($H$9:$H$16,4),$H$9:$H$16,0))-$B$5 -> 3684.5535 | D24: =INDEX($G$9:$G$16,MATCH(LARGE($H$9:$H$16,4),$H$9:$H$16,0)) -> 9154.1546 | E24: =INDEX($B$9:$B$16,MATCH(LARGE($H$9:$H$16,4),$H$9:$H$16,0)) -> 0.7 | F24: =INDEX($C$9:$C$16,MATCH(LARGE($H$9:$H$16,4),$H$9:$H$16,0)) -> 0.95 | G24: 4
A25: =INDEX($A$9:$A$16,MATCH(LARGE($H$9:$H$16,5),$H$9:$H$16,0)) -> Bunker price (Brent) | B25: =INDEX($E$9:$E$16,MATCH(LARGE($H$9:$H$16,5),$H$9:$H$16,0))-$B$5 -> 2258.7753 | C25: =INDEX($F$9:$F$16,MATCH(LARGE($H$9:$H$16,5),$H$9:$H$16,0))-$B$5 -> -3675.541 | D25: =INDEX($G$9:$G$16,MATCH(LARGE($H$9:$H$16,5),$H$9:$H$16,0)) -> 5934.3163 | E25: =INDEX($B$9:$B$16,MATCH(LARGE($H$9:$H$16,5),$H$9:$H$16,0)) -> 67.98 | F25: =INDEX($C$9:$C$16,MATCH(LARGE($H$9:$H$16,5),$H$9:$H$16,0)) -> 104.84 | G25: 5
A26: =INDEX($A$9:$A$16,MATCH(LARGE($H$9:$H$16,6),$H$9:$H$16,0)) -> Port disbursements | B26: =INDEX($E$9:$E$16,MATCH(LARGE($H$9:$H$16,6),$H$9:$H$16,0))-$B$5 -> 1276.6517 | C26: =INDEX($F$9:$F$16,MATCH(LARGE($H$9:$H$16,6),$H$9:$H$16,0))-$B$5 -> -1276.6517 | D26: =INDEX($G$9:$G$16,MATCH(LARGE($H$9:$H$16,6),$H$9:$H$16,0)) -> 2553.3035 | E26: =INDEX($B$9:$B$16,MATCH(LARGE($H$9:$H$16,6),$H$9:$H$16,0)) -> 0.75 | F26: =INDEX($C$9:$C$16,MATCH(LARGE($H$9:$H$16,6),$H$9:$H$16,0)) -> 1.25 | G26: 6
A27: =INDEX($A$9:$A$16,MATCH(LARGE($H$9:$H$16,7),$H$9:$H$16,0)) -> Service speed | B27: =INDEX($E$9:$E$16,MATCH(LARGE($H$9:$H$16,7),$H$9:$H$16,0))-$B$5 -> 899.09328 | C27: =INDEX($F$9:$F$16,MATCH(LARGE($H$9:$H$16,7),$H$9:$H$16,0))-$B$5 -> -1110.8711 | D27: =INDEX($G$9:$G$16,MATCH(LARGE($H$9:$H$16,7),$H$9:$H$16,0)) -> 2009.9644 | E27: =INDEX($B$9:$B$16,MATCH(LARGE($H$9:$H$16,7),$H$9:$H$16,0)) -> 12 | F27: =INDEX($C$9:$C$16,MATCH(LARGE($H$9:$H$16,7),$H$9:$H$16,0)) -> 14.5 | G27: 7
A28: =INDEX($A$9:$A$16,MATCH(LARGE($H$9:$H$16,8),$H$9:$H$16,0)) -> EU carbon price (EUA) | B28: =INDEX($E$9:$E$16,MATCH(LARGE($H$9:$H$16,8),$H$9:$H$16,0))-$B$5 -> 836.15268 | C28: =INDEX($F$9:$F$16,MATCH(LARGE($H$9:$H$16,8),$H$9:$H$16,0))-$B$5 -> -1170.6138 | D28: =INDEX($G$9:$G$16,MATCH(LARGE($H$9:$H$16,8),$H$9:$H$16,0)) -> 2006.7664 | E28: =INDEX($B$9:$B$16,MATCH(LARGE($H$9:$H$16,8),$H$9:$H$16,0)) -> 50 | F28: =INDEX($C$9:$C$16,MATCH(LARGE($H$9:$H$16,8),$H$9:$H$16,0)) -> 110 | G28: 8
A32: C. Leverage — TCE change for a +10% move in each lever (apples-to-apples)
A33: Lever | B33: Base value | C33: +10% value | D33: TCE change $/day | E33: Per 1% move $/day
A34: Freight rate | B34: =FreightMult -> 1 | C34: =Engine!E27 -> 1.1 | D34: =Engine!AK27-$B$5 -> 4489.8531 | E34: =D34/10 -> 448.98531
A35: Bunker price | B35: =Brent -> 82.01 | C35: =Engine!D28 -> 90.211 | D35: =Engine!AK28-$B$5 -> -1320.329 | E35: =D35/10 -> -132.0329
A36: Port time | B36: =PortMult -> 1 | C36: =Engine!F29 -> 1.1 | D36: =Engine!AK29-$B$5 -> -1024.0365 | E36: =D36/10 -> -102.40365
A37: Fronthaul utilization | B37: =UtilFH -> 0.85 | C37: =Engine!G30 -> 0.935 | D37: =Engine!AK30-$B$5 -> 3130.426 | E37: =D37/10 -> 313.0426
A38: Backhaul utilization | B38: =UtilBH -> 0.5 | C38: =Engine!H31 -> 0.55 | D38: =Engine!AK31-$B$5 -> 1325.9065 | E38: =D38/10 -> 132.59065
A39: Service speed | B39: =Speed -> 13.5 | C39: =Engine!I32 -> 14.85 | D39: =Engine!AK32-$B$5 -> -1596.882 | E39: =D39/10 -> -159.6882
A40: Port disbursements | B40: =PortCostMult -> 1 | C40: =Engine!J33 -> 1.1 | D40: =Engine!AK33-$B$5 -> -510.66069 | E40: =D40/10 -> -51.066069
A43: Reading the two views together: the tornado answers 'what moved results most over realistic ranges'; the +10% table answers 'where does one unit of effort buy the most TCE'. Utilization and speed are partly controllable; freight and bunker prices are mostly not.

Sheet Breakeven
A1: Break-even fronthaul freight rate ($/t) — the rate at which TCE equals the daily vessel cost benchmark
A2: Independent analysis using publicly available data. Not affiliated with or endorsed by any organization named.
A3: Curves hold the active route and levers constant except the ones named. Linear in Brent because bunker cost is linear in price.
A5: A. By port-time multiplier (active route)
A6: Brent $/bbl | B6: 1.0x port time | C6: 1.5x port time | D6: 2.0x port time
A7: 50 | B7: =Engine!AM42 -> 34.234756 | C7: =Engine!AM51 -> 40.852882 | D7: =Engine!AM60 -> 47.357987
A8: 60 | B8: =Engine!AM43 -> 36.900887 | C8: =Engine!AM52 -> 43.684825 | D8: =Engine!AM61 -> 50.355741
A9: 70 | B9: =Engine!AM44 -> 39.567017 | C9: =Engine!AM53 -> 46.516767 | D9: =Engine!AM62 -> 53.353496
A10: 80 | B10: =Engine!AM45 -> 42.233147 | C10: =Engine!AM54 -> 49.348709 | D10: =Engine!AM63 -> 56.35125
A11: 90 | B11: =Engine!AM46 -> 44.899278 | C11: =Engine!AM55 -> 52.180652 | D11: =Engine!AM64 -> 59.349004
A12: 100 | B12: =Engine!AM47 -> 47.565408 | C12: =Engine!AM56 -> 55.012594 | D12: =Engine!AM65 -> 62.346759
A13: 110 | B13: =Engine!AM48 -> 50.231539 | C13: =Engine!AM57 -> 57.844537 | D13: =Engine!AM66 -> 65.344513
A14: 120 | B14: =Engine!AM49 -> 52.897669 | C14: =Engine!AM58 -> 60.676479 | D14: =Engine!AM67 -> 68.342267
A15: 130 | B15: =Engine!AM50 -> 55.563799 | C15: =Engine!AM59 -> 63.508421 | D15: =Engine!AM68 -> 71.340022
A19: B. By fronthaul utilization (active route)
A20: Brent $/bbl | B20: 70% utilization | C20: 85% utilization | D20: 95% utilization
A21: 50 | B21: =Engine!AM69 -> 41.426649 | C21: =Engine!AM78 -> 34.234756 | D21: =Engine!AM87 -> 30.645366
A22: 60 | B22: =Engine!AM70 -> 44.664093 | C22: =Engine!AM79 -> 36.900887 | D22: =Engine!AM88 -> 33.030851
A23: 70 | B23: =Engine!AM71 -> 47.901537 | C23: =Engine!AM80 -> 39.567017 | D23: =Engine!AM89 -> 35.416336
A24: 80 | B24: =Engine!AM72 -> 51.138981 | C24: =Engine!AM81 -> 42.233147 | D24: =Engine!AM90 -> 37.801821
A25: 90 | B25: =Engine!AM73 -> 54.376425 | C25: =Engine!AM82 -> 44.899278 | D25: =Engine!AM91 -> 40.187306
A26: 100 | B26: =Engine!AM74 -> 57.613869 | C26: =Engine!AM83 -> 47.565408 | D26: =Engine!AM92 -> 42.572791
A27: 110 | B27: =Engine!AM75 -> 60.851313 | C27: =Engine!AM84 -> 50.231539 | D27: =Engine!AM93 -> 44.958276
A28: 120 | B28: =Engine!AM76 -> 64.088757 | C28: =Engine!AM85 -> 52.897669 | D28: =Engine!AM94 -> 47.343761
A29: 130 | B29: =Engine!AM77 -> 67.326201 | C29: =Engine!AM86 -> 55.563799 | D29: =Engine!AM95 -> 49.729246
A33: C. By route (active levers)
A34: Brent $/bbl | B34: =Routes!B6 -> USG-ARA transatlantic | C34: =Routes!B7 -> USG-Far East via Panama | D34: =Routes!B8 -> ARA-India WC via Suez | E34: =Routes!B9 -> ARA-India WC via Cape | F34: Base rate R1 | G34: Base rate R2 | H34: Base rate R3 | I34: Base rate R4
A35: 50 | B35: =Engine!AM96 -> 34.234756 | C35: =Engine!AM105 -> 66.960418 | D35: =Engine!AM114 -> 57.968436 | E35: =Engine!AM123 -> 62.510344 | F35: =Routes!$J$6*FreightMult -> 52 | G35: =Routes!$J$7*FreightMult -> 92 | H35: =Routes!$J$8*FreightMult -> 75 | I35: =Routes!$J$9*FreightMult -> 75
A36: 60 | B36: =Engine!AM97 -> 36.900887 | C36: =Engine!AM106 -> 71.732456 | D36: =Engine!AM115 -> 61.220832 | E36: =Engine!AM124 -> 67.756155 | F36: =Routes!$J$6*FreightMult -> 52 | G36: =Routes!$J$7*FreightMult -> 92 | H36: =Routes!$J$8*FreightMult -> 75 | I36: =Routes!$J$9*FreightMult -> 75
A37: 70 | B37: =Engine!AM98 -> 39.567017 | C37: =Engine!AM107 -> 76.504494 | D37: =Engine!AM116 -> 64.473229 | E37: =Engine!AM125 -> 73.001965 | F37: =Routes!$J$6*FreightMult -> 52 | G37: =Routes!$J$7*FreightMult -> 92 | H37: =Routes!$J$8*FreightMult -> 75 | I37: =Routes!$J$9*FreightMult -> 75
A38: 80 | B38: =Engine!AM99 -> 42.233147 | C38: =Engine!AM108 -> 81.276532 | D38: =Engine!AM117 -> 67.725625 | E38: =Engine!AM126 -> 78.247775 | F38: =Routes!$J$6*FreightMult -> 52 | G38: =Routes!$J$7*FreightMult -> 92 | H38: =Routes!$J$8*FreightMult -> 75 | I38: =Routes!$J$9*FreightMult -> 75
A39: 90 | B39: =Engine!AM100 -> 44.899278 | C39: =Engine!AM109 -> 86.04857 | D39: =Engine!AM118 -> 70.978022 | E39: =Engine!AM127 -> 83.493586 | F39: =Routes!$J$6*FreightMult -> 52 | G39: =Routes!$J$7*FreightMult -> 92 | H39: =Routes!$J$8*FreightMult -> 75 | I39: =Routes!$J$9*FreightMult -> 75
A40: 100 | B40: =Engine!AM101 -> 47.565408 | C40: =Engine!AM110 -> 90.820608 | D40: =Engine!AM119 -> 74.230418 | E40: =Engine!AM128 -> 88.739396 | F40: =Routes!$J$6*FreightMult -> 52 | G40: =Routes!$J$7*FreightMult -> 92 | H40: =Routes!$J$8*FreightMult -> 75 | I40: =Routes!$J$9*FreightMult -> 75
A41: 110 | B41: =Engine!AM102 -> 50.231539 | C41: =Engine!AM111 -> 95.592646 | D41: =Engine!AM120 -> 77.482815 | E41: =Engine!AM129 -> 93.985206 | F41: =Routes!$J$6*FreightMult -> 52 | G41: =Routes!$J$7*FreightMult -> 92 | H41: =Routes!$J$8*FreightMult -> 75 | I41: =Routes!$J$9*FreightMult -> 75
A42: 120 | B42: =Engine!AM103 -> 52.897669 | C42: =Engine!AM112 -> 100.36468 | D42: =Engine!AM121 -> 80.735211 | E42: =Engine!AM130 -> 99.231016 | F42: =Routes!$J$6*FreightMult -> 52 | G42: =Routes!$J$7*FreightMult -> 92 | H42: =Routes!$J$8*FreightMult -> 75 | I42: =Routes!$J$9*FreightMult -> 75
A43: 130 | B43: =Engine!AM104 -> 55.563799 | C43: =Engine!AM113 -> 105.13672 | D43: =Engine!AM122 -> 83.987608 | E43: =Engine!AM131 -> 104.47683 | F43: =Routes!$J$6*FreightMult -> 52 | G43: =Routes!$J$7*FreightMult -> 92 | H43: =Routes!$J$8*FreightMult -> 75 | I43: =Routes!$J$9*FreightMult -> 75
A47: D. TCE grid ($/day): freight multiplier (rows) x Brent (columns), active route
A48: Freight mult \ Brent | B48: $60 | C48: $70 | D48: $80 | E48: $90 | F48: $100 | G48: $110 | H48: $120
A49: 0.8 | B49: =Engine!AK134 -> 18137.996 | C49: =Engine!AK135 -> 16528.035 | D49: =Engine!AK136 -> 14918.074 | E49: =Engine!AK137 -> 13308.113 | F49: =Engine!AK138 -> 11698.152 | G49: =Engine!AK139 -> 10088.191 | H49: =Engine!AK140 -> 8478.2304
A50: 0.9 | B50: =Engine!AK141 -> 22627.85 | C50: =Engine!AK142 -> 21017.889 | D50: =Engine!AK143 -> 19407.928 | E50: =Engine!AK144 -> 17797.966 | F50: =Engine!AK145 -> 16188.005 | G50: =Engine!AK146 -> 14578.044 | H50: =Engine!AK147 -> 12968.083
A51: 1 | B51: =Engine!AK148 -> 27117.703 | C51: =Engine!AK149 -> 25507.742 | D51: =Engine!AK150 -> 23897.781 | E51: =Engine!AK151 -> 22287.82 | F51: =Engine!AK152 -> 20677.859 | G51: =Engine!AK153 -> 19067.898 | H51: =Engine!AK154 -> 17457.937
A52: 1.1 | B52: =Engine!AK155 -> 31607.556 | C52: =Engine!AK156 -> 29997.595 | D52: =Engine!AK157 -> 28387.634 | E52: =Engine!AK158 -> 26777.673 | F52: =Engine!AK159 -> 25167.712 | G52: =Engine!AK160 -> 23557.751 | H52: =Engine!AK161 -> 21947.79
A53: 1.2 | B53: =Engine!AK162 -> 36097.409 | C53: =Engine!AK163 -> 34487.448 | D53: =Engine!AK164 -> 32877.487 | E53: =Engine!AK165 -> 31267.526 | F53: =Engine!AK166 -> 29657.565 | G53: =Engine!AK167 -> 28047.604 | H53: =Engine!AK168 -> 26437.643
A54: 1.3 | B54: =Engine!AK169 -> 40587.262 | C54: =Engine!AK170 -> 38977.301 | D54: =Engine!AK171 -> 37367.34 | E54: =Engine!AK172 -> 35757.379 | F54: =Engine!AK173 -> 34147.418 | G54: =Engine!AK174 -> 32537.457 | H54: =Engine!AK175 -> 30927.496
A56: Colour midpoint = $18,000/day benchmark (white). Red = below vessel cost; green = above.
A59: E. Speed optimization: TCE ($/day) by service speed and Brent (active route)
A60: Speed (kn) | B60: Brent $65 | C60: Brent $82 | D60: Brent $104
A61: 10 | B61: =Engine!AK178 -> 25601.301 | C61: =Engine!AK189 -> 24254.993 | D61: =Engine!AK200 -> 22512.711
A62: 10.5 | B62: =Engine!AK179 -> 25968.266 | C62: =Engine!AK190 -> 24460.637 | D62: =Engine!AK201 -> 22509.589
A63: 11 | B63: =Engine!AK180 -> 26246.978 | C63: =Engine!AK191 -> 24566.036 | D63: =Engine!AK202 -> 22390.7
A64: 11.5 | B64: =Engine!AK181 -> 26437.316 | C64: =Engine!AK192 -> 24570.781 | D64: =Engine!AK203 -> 22155.266
A65: 12 | B65: =Engine!AK182 -> 26539.167 | C65: =Engine!AK193 -> 24474.486 | D65: =Engine!AK204 -> 21802.547
A66: 12.5 | B66: =Engine!AK183 -> 26552.419 | C66: =Engine!AK194 -> 24276.784 | D66: =Engine!AK205 -> 21331.845
A67: 13 | B67: =Engine!AK184 -> 26476.97 | C67: =Engine!AK195 -> 23977.328 | D67: =Engine!AK206 -> 20742.497
A68: 13.5 | B68: =Engine!AK185 -> 26312.722 | C68: =Engine!AK196 -> 23575.788 | D68: =Engine!AK207 -> 20033.874
A69: 14 | B69: =Engine!AK186 -> 26059.581 | C69: =Engine!AK197 -> 23071.852 | D69: =Engine!AK208 -> 19205.378
A70: 14.5 | B70: =Engine!AK187 -> 25717.459 | C70: =Engine!AK198 -> 22465.22 | D70: =Engine!AK209 -> 18256.44
A71: 15 | B71: =Engine!AK188 -> 25286.272 | C71: =Engine!AK199 -> 21755.612 | D71: =Engine!AK210 -> 17186.522
A72: TCE-maximizing speed | B72: =INDEX($A$61:$A$71,MATCH(MAX(B61:B71),B61:B71,0)) -> 12.5 | C72: =INDEX($A$61:$A$71,MATCH(MAX(C61:C71),C61:C71,0)) -> 11.5 | D72: =INDEX($A$61:$A$71,MATCH(MAX(D61:D71),D61:D71,0)) -> 10

Sheet Engine
A1: Calculation engine — one full round-voyage P&L per row
A2: Independent analysis using publicly available data. Not affiliated with or endorsed by any organization named.
A3: Each row recomputes the whole voyage with its own lever values (cols C-K). Sensitivity and Breakeven sheets read from here. Row 7 = active scenario and must equal Voyage_PnL (check on that sheet).
A6: Case | B6: Group | C6: Route # | D6: Brent $/bbl | E6: Freight mult | F6: Port-time mult | G6: Util FH | H6: Util BH | I6: Speed kn | J6: Port-cost mult | K6: EUA EUR/t | L6: Distance/leg nm | M6: ECA share | N6: Sea days (both legs) | O6: Speed factor | P6: Backhaul laden? | Q6: Sea fuel t | R6: VLSFO t | S6: MGO sea t | T6: Port ops per region | U6: Port days A | V6: Port days B | W6: Canal days | X6: MGO port t | Y6: Bunker cost $ | Z6: Port cost $ | AA6: Canal cost $ | AB6: EU ETS cost $ | AC6: Qty FH t | AD6: Qty BH t | AE6: Rate FH $/t | AF6: Rate BH $/t | AG6: Gross freight $ | AH6: Commission $ | AI6: Voyage costs $ | AJ6: Voyage days | AK6: TCE $/day | AL6: Voyage result $ | AM6: Break-even FH rate $/t
A7: Active scenario | B7: base | C7: =Sw_Route -> 1 | D7: =Brent -> 82.01 | E7: =FreightMult -> 1 | F7: =PortMult -> 1 | G7: =UtilFH -> 0.85 | H7: =UtilBH -> 0.5 | I7: =Speed -> 13.5 | J7: =PortCostMult -> 1 | K7: =EUA -> 75 | L7: =INDEX(Routes!$E$6:$E$9,$C7) -> 5000 | M7: =INDEX(Routes!$F$6:$F$9,$C7)/L7 -> 0.13 | N7: =2*L7*(1+SeaMargin)/(I7*24) -> 32.407407 | O7: =(I7/RefSpeed)^SpeedExp -> 1 | P7: =IF(H7>0,1,0) -> 1 | Q7: =N7/2*O7*(ConsLaden+IF(P7=1,ConsLaden,ConsBallast)) -> 875 | R7: =Q7*(1-M7) -> 761.25 | S7: =Q7*M7 -> 113.75 | T7: =1+P7 -> 2 | U7: =INDEX(Routes!$L$6:$L$9,$C7)*T7*F7 -> 10 | V7: =INDEX(Routes!$M$6:$M$9,$C7)*T7*F7 -> 7 | W7: =INDEX(Routes!$H$6:$H$9,$C7)*2 -> 0 | X7: =(U7+V7+W7)*ConsPort -> 102 | Y7: =R7*D7*VLSFO_Mult+(S7+X7)*D7*MGO_Mult -> 652340.34 | Z7: =(INDEX(Routes!$N$6:$N$9,$C7)+AN7+MIN(AC7*INDEX(Routes!$T$6:$T$9,$C7),INDEX(Routes!$V$6:$V$9,$C7))+INDEX(Routes!$O$6:$O$9,$C7)+AO7+MIN(AC7*INDEX(Routes!$U$6:$U$9,$C7),INDEX(Routes!$W$6:$W$9,$C7))+IF(P7=1,INDEX(Routes!$N$6:$N$9,$C7)+AN7+MIN(AD7*INDEX(Routes!$T$6:$T$9,$C7),INDEX(Routes!$V$6:$V$9,$C7))+INDEX(Routes!$O$6:$O$9,$C7)+AO7+MIN(AD7*INDEX(Routes!$U$6:$U$9,$C7),INDEX(Routes!$W$6:$W$9,$C7)),0))*J7 -> 252304.21 | AA7: =INDEX(Routes!$R$6:$R$9,$C7)+IF(P7=1,INDEX(Routes!$R$6:$R$9,$C7),INDEX(Routes!$S$6:$S$9,$C7)) -> 0 | AB7: =((R7*CO2_VLSFO+S7*CO2_MGO)*INDEX(Routes!$I$6:$I$9,$C7)+(U7*INDEX(Routes!$P$6:$P$9,$C7)+V7*INDEX(Routes!$Q$6:$Q$9,$C7))*ConsPort*CO2_MGO)*PhaseIn*K7*FX -> 123936.41 | AC7: =Capacity*G7 -> 30600 | AD7: =Capacity*H7 -> 18000 | AE7: =INDEX(Routes!$J$6:$J$9,$C7)*E7 -> 52 | AF7: =INDEX(Routes!$K$6:$K$9,$C7)*E7 -> 38 | AG7: =AC7*AE7+AD7*AF7 -> 2275200 | AH7: =AG7*Commission -> 56880 | AI7: =Y7+Z7+AA7+AB7+MiscVoy -> 1053581 | AJ7: =N7+U7+V7+W7 -> 49.407407 | AK7: =(AG7-AH7-AI7)/AJ7 -> 23574.178 | AL7: =AG7-AH7-AI7-Benchmark*AJ7 -> 275405.7 | AM7: =IF(AC7>0,((Benchmark*AJ7+AI7)/(1-Commission)-AD7*AF7)/AC7,0) -> 42.76904 | AN7: =LOA_ft*Port_Tariffs!$C$9*IF((INDEX(Routes!$L$6:$L$9,$C7)*INDEX(Routes!$X$6:$X$9,$C7)*F7)<=2,(INDEX(Routes!$L$6:$L$9,$C7)*INDEX(Routes!$X$6:$X$9,$C7)*F7),IF((INDEX(Routes!$L$6:$L$9,$C7)*INDEX(Routes!$X$6:$X$9,$C7)*F7)<=3,2+0.9*((INDEX(Routes!$L$6:$L$9,$C7)*INDEX(Routes!$X$6:$X$9,$C7)*F7)-2),IF((INDEX(Routes!$L$6:$L$9,$C7)*INDEX(Routes!$X$6:$X$9,$C7)*F7)<=4,2.9+0.75*((INDEX(Routes!$L$6:$L$9,$C7)*INDEX(Routes!$X$6:$X$9,$C7)*F7)-3),IF((INDEX(Routes!$L$6:$L$9,$C7)*INDEX(Routes!$X$6:$X$9,$C7)*F7)<=5,3.65+0.6*((INDEX(Routes!$L$6:$L$9,$C7)*INDEX(Routes!$X$6:$X$9,$C7)*F7)-4),4.25+0.5*((INDEX(Routes!$L$6:$L$9,$C7)*INDEX(Routes!$X$6:$X$9,$C7)*F7)-5))))) -> 19557.6 | AO7: =LOA_ft*Port_Tariffs!$C$9*IF((INDEX(Routes!$M$6:$M$9,$C7)*INDEX(Routes!$Y$6:$Y$9,$C7)*F7)<=2,(INDEX(Routes!$M$6:$M$9,$C7)*INDEX(Routes!$Y$6:$Y$9,$C7)*F7),IF((INDEX(Routes!$M$6:$M$9,$C7)*INDEX(Routes!$Y$6:$Y$9,$C7)*F7)<=3,2+0.9*((INDEX(Routes!$M$6:$M$9,$C7)*INDEX(Routes!$Y$6:$Y$9,$C7)*F7)-2),IF((INDEX(Routes!$M$6:$M$9,$C7)*INDEX(Routes!$Y$6:$Y$9,$C7)*F7)<=4,2.9+0.75*((INDEX(Routes!$M$6:$M$9,$C7)*INDEX(Routes!$Y$6:$Y$9,$C7)*F7)-3),IF((INDEX(Routes!$M$6:$M$9,$C7)*INDEX(Routes!$Y$6:$Y$9,$C7)*F7)<=5,3.65+0.6*((INDEX(Routes!$M$6:$M$9,$C7)*INDEX(Routes!$Y$6:$Y$9,$C7)*F7)-4),4.25+0.5*((INDEX(Routes!$M$6:$M$9,$C7)*INDEX(Routes!$Y$6:$Y$9,$C7)*F7)-5))))) -> 0
A8: TORNADO CASES (one lever flexed, all others at active values)
A9: Freight rate (market) — low | B9: tornado | C9: =Sw_Route -> 1 | D9: =Brent -> 82.01 | E9: =Freight_Low -> 0.91 | F9: =PortMult -> 1 | G9: =UtilFH -> 0.85 | H9: =UtilBH -> 0.5 | I9: =Speed -> 13.5 | J9: =PortCostMult -> 1 | K9: =EUA -> 75 | L9: =INDEX(Routes!$E$6:$E$9,$C9) -> 5000 | M9: =INDEX(Routes!$F$6:$F$9,$C9)/L9 -> 0.13 | N9: =2*L9*(1+SeaMargin)/(I9*24) -> 32.407407 | O9: =(I9/RefSpeed)^SpeedExp -> 1 | P9: =IF(H9>0,1,0) -> 1 | Q9: =N9/2*O9*(ConsLaden+IF(P9=1,ConsLaden,ConsBallast)) -> 875 | R9: =Q9*(1-M9) -> 761.25 | S9: =Q9*M9 -> 113.75 | T9: =1+P9 -> 2 | U9: =INDEX(Routes!$L$6:$L$9,$C9)*T9*F9 -> 10 | V9: =INDEX(Routes!$M$6:$M$9,$C9)*T9*F9 -> 7 | W9: =INDEX(Routes!$H$6:$H$9,$C9)*2 -> 0 | X9: =(U9+V9+W9)*ConsPort -> 102 | Y9: =R9*D9*VLSFO_Mult+(S9+X9)*D9*MGO_Mult -> 652340.34 | Z9: =(INDEX(Routes!$N$6:$N$9,$C9)+AN9+MIN(AC9*INDEX(Routes!$T$6:$T$9,$C9),INDEX(Routes!$V$6:$V$9,$C9))+INDEX(Routes!$O$6:$O$9,$C9)+AO9+MIN(AC9*INDEX(Routes!$U$6:$U$9,$C9),INDEX(Routes!$W$6:$W$9,$C9))+IF(P9=1,INDEX(Routes!$N$6:$N$9,$C9)+AN9+MIN(AD9*INDEX(Routes!$T$6:$T$9,$C9),INDEX(Routes!$V$6:$V$9,$C9))+INDEX(Routes!$O$6:$O$9,$C9)+AO9+MIN(AD9*INDEX(Routes!$U$6:$U$9,$C9),INDEX(Routes!$W$6:$W$9,$C9)),0))*J9 -> 252304.21 | AA9: =INDEX(Routes!$R$6:$R$9,$C9)+IF(P9=1,INDEX(Routes!$R$6:$R$9,$C9),INDEX(Routes!$S$6:$S$9,$C9)) -> 0 | AB9: =((R9*CO2_VLSFO+S9*CO2_MGO)*INDEX(Routes!$I$6:$I$9,$C9)+(U9*INDEX(Routes!$P$6:$P$9,$C9)+V9*INDEX(Routes!$Q$6:$Q$9,$C9))*ConsPort*CO2_MGO)*PhaseIn*K9*FX -> 123936.41 | AC9: =Capacity*G9 -> 30600 | AD9: =Capacity*H9 -> 18000 | AE9: =INDEX(Routes!$J$6:$J$9,$C9)*E9 -> 47.32 | AF9: =INDEX(Routes!$K$6:$K$9,$C9)*E9 -> 34.58 | AG9: =AC9*AE9+AD9*AF9 -> 2070432 | AH9: =AG9*Commission -> 51760.8 | AI9: =Y9+Z9+AA9+AB9+MiscVoy -> 1053581 | AJ9: =N9+U9+V9+W9 -> 49.407407 | AK9: =(AG9-AH9-AI9)/AJ9 -> 19533.311 | AL9: =AG9-AH9-AI9-Benchmark*AJ9 -> 75756.904 | AM9: =IF(AC9>0,((Benchmark*AJ9+AI9)/(1-Commission)-AD9*AF9)/AC9,0) -> 44.780804 | AN9: =LOA_ft*Port_Tariffs!$C$9*IF((INDEX(Routes!$L$6:$L$9,$C9)*INDEX(Routes!$X$6:$X$9,$C9)*F9)<=2,(INDEX(Routes!$L$6:$L$9,$C9)*INDEX(Routes!$X$6:$X$9,$C9)*F9),IF((INDEX(Routes!$L$6:$L$9,$C9)*INDEX(Routes!$X$6:$X$9,$C9)*F9)<=3,2+0.9*((INDEX(Routes!$L$6:$L$9,$C9)*INDEX(Routes!$X$6:$X$9,$C9)*F9)-2),IF((INDEX(Routes!$L$6:$L$9,$C9)*INDEX(Routes!$X$6:$X$9,$C9)*F9)<=4,2.9+0.75*((INDEX(Routes!$L$6:$L$9,$C9)*INDEX(Routes!$X$6:$X$9,$C9)*F9)-3),IF((INDEX(Routes!$L$6:$L$9,$C9)*INDEX(Routes!$X$6:$X$9,$C9)*F9)<=5,3.65+0.6*((INDEX(Routes!$L$6:$L$9,$C9)*INDEX(Routes!$X$6:$X$9,$C9)*F9)-4),4.25+0.5*((INDEX(Routes!$L$6:$L$9,$C9)*INDEX(Routes!$X$6:$X$9,$C9)*F9)-5))))) -> 19557.6 | AO9: =LOA_ft*Port_Tariffs!$C$9*IF((INDEX(Routes!$M$6:$M$9,$C9)*INDEX(Routes!$Y$6:$Y$9,$C9)*F9)<=2,(INDEX(Routes!$M$6:$M$9,$C9)*INDEX(Routes!$Y$6:$Y$9,$C9)*F9),IF((INDEX(Routes!$M$6:$M$9,$C9)*INDEX(Routes!$Y$6:$Y$9,$C9)*F9)<=3,2+0.9*((INDEX(Routes!$M$6:$M$9,$C9)*INDEX(Routes!$Y$6:$Y$9,$C9)*F9)-2),IF((INDEX(Routes!$M$6:$M$9,$C9)*INDEX(Routes!$Y$6:$Y$9,$C9)*F9)<=4,2.9+0.75*((INDEX(Routes!$M$6:$M$9,$C9)*INDEX(Routes!$Y$6:$Y$9,$C9)*F9)-3),IF((INDEX(Routes!$M$6:$M$9,$C9)*INDEX(Routes!$Y$6:$Y$9,$C9)*F9)<=5,3.65+0.6*((INDEX(Routes!$M$6:$M$9,$C9)*INDEX(Routes!$Y$6:$Y$9,$C9)*F9)-4),4.25+0.5*((INDEX(Routes!$M$6:$M$9,$C9)*INDEX(Routes!$Y$6:$Y$9,$C9)*F9)-5))))) -> 0
A10: Freight rate (market) — high | B10: tornado | C10: =Sw_Route -> 1 | D10: =Brent -> 82.01 | E10: =Freight_High -> 1.25 | F10: =PortMult -> 1 | G10: =UtilFH -> 0.85 | H10: =UtilBH -> 0.5 | I10: =Speed -> 13.5 | J10: =PortCostMult -> 1 | K10: =EUA -> 75 | L10: =INDEX(Routes!$E$6:$E$9,$C10) -> 5000 | M10: =INDEX(Routes!$F$6:$F$9,$C10)/L10 -> 0.13 | N10: =2*L10*(1+SeaMargin)/(I10*24) -> 32.407407 | O10: =(I10/RefSpeed)^SpeedExp -> 1 | P10: =IF(H10>0,1,0) -> 1 | Q10: =N10/2*O10*(ConsLaden+IF(P10=1,ConsLaden,ConsBallast)) -> 875 | R10: =Q10*(1-M10) -> 761.25 | S10: =Q10*M10 -> 113.75 | T10: =1+P10 -> 2 | U10: =INDEX(Routes!$L$6:$L$9,$C10)*T10*F10 -> 10 | V10: =INDEX(Routes!$M$6:$M$9,$C10)*T10*F10 -> 7 | W10: =INDEX(Routes!$H$6:$H$9,$C10)*2 -> 0 | X10: =(U10+V10+W10)*ConsPort -> 102 | Y10: =R10*D10*VLSFO_Mult+(S10+X10)*D10*MGO_Mult -> 652340.34 | Z10: =(INDEX(Routes!$N$6:$N$9,$C10)+AN10+MIN(AC10*INDEX(Routes!$T$6:$T$9,$C10),INDEX(Routes!$V$6:$V$9,$C10))+INDEX(Routes!$O$6:$O$9,$C10)+AO10+MIN(AC10*INDEX(Routes!$U$6:$U$9,$C10),INDEX(Routes!$W$6:$W$9,$C10))+IF(P10=1,INDEX(Routes!$N$6:$N$9,$C10)+AN10+MIN(AD10*INDEX(Routes!$T$6:$T$9,$C10),INDEX(Routes!$V$6:$V$9,$C10))+INDEX(Routes!$O$6:$O$9,$C10)+AO10+MIN(AD10*INDEX(Routes!$U$6:$U$9,$C10),INDEX(Routes!$W$6:$W$9,$C10)),0))*J10 -> 252304.21 | AA10: =INDEX(Routes!$R$6:$R$9,$C10)+IF(P10=1,INDEX(Routes!$R$6:$R$9,$C10),INDEX(Routes!$S$6:$S$9,$C10)) -> 0 | AB10: =((R10*CO2_VLSFO+S10*CO2_MGO)*INDEX(Routes!$I$6:$I$9,$C10)+(U10*INDEX(Routes!$P$6:$P$9,$C10)+V10*INDEX(Routes!$Q$6:$Q$9,$C10))*ConsPort*CO2_MGO)*PhaseIn*K10*FX -> 123936.41 | AC10: =Capacity*G10 -> 30600 | AD10: =Capacity*H10 -> 18000 | AE10: =INDEX(Routes!$J$6:$J$9,$C10)*E10 -> 65 | AF10: =INDEX(Routes!$K$6:$K$9,$C10)*E10 -> 47.5 | AG10: =AC10*AE10+AD10*AF10 -> 2844000 | AH10: =AG10*Commission -> 71100 | AI10: =Y10+Z10+AA10+AB10+MiscVoy -> 1053581 | AJ10: =N10+U10+V10+W10 -> 49.407407 | AK10: =(AG10-AH10-AI10)/AJ10 -> 34798.811 | AL10: =AG10-AH10-AI10-Benchmark*AJ10 -> 829985.7 | AM10: =IF(AC10>0,((Benchmark*AJ10+AI10)/(1-Commission)-AD10*AF10)/AC10,0) -> 37.180804 | AN10: =LOA_ft*Port_Tariffs!$C$9*IF((INDEX(Routes!$L$6:$L$9,$C10)*INDEX(Routes!$X$6:$X$9,$C10)*F10)<=2,(INDEX(Routes!$L$6:$L$9,$C10)*INDEX(Routes!$X$6:$X$9,$C10)*F10),IF((INDEX(Routes!$L$6:$L$9,$C10)*INDEX(Routes!$X$6:$X$9,$C10)*F10)<=3,2+0.9*((INDEX(Routes!$L$6:$L$9,$C10)*INDEX(Routes!$X$6:$X$9,$C10)*F10)-2),IF((INDEX(Routes!$L$6:$L$9,$C10)*INDEX(Routes!$X$6:$X$9,$C10)*F10)<=4,2.9+0.75*((INDEX(Routes!$L$6:$L$9,$C10)*INDEX(Routes!$X$6:$X$9,$C10)*F10)-3),IF((INDEX(Routes!$L$6:$L$9,$C10)*INDEX(Routes!$X$6:$X$9,$C10)*F10)<=5,3.65+0.6*((INDEX(Routes!$L$6:$L$9,$C10)*INDEX(Routes!$X$6:$X$9,$C10)*F10)-4),4.25+0.5*((INDEX(Routes!$L$6:$L$9,$C10)*INDEX(Routes!$X$6:$X$9,$C10)*F10)-5))))) -> 19557.6 | AO10: =LOA_ft*Port_Tariffs!$C$9*IF((INDEX(Routes!$M$6:$M$9,$C10)*INDEX(Routes!$Y$6:$Y$9,$C10)*F10)<=2,(INDEX(Routes!$M$6:$M$9,$C10)*INDEX(Routes!$Y$6:$Y$9,$C10)*F10),IF((INDEX(Routes!$M$6:$M$9,$C10)*INDEX(Routes!$Y$6:$Y$9,$C10)*F10)<=3,2+0.9*((INDEX(Routes!$M$6:$M$9,$C10)*INDEX(Routes!$Y$6:$Y$9,$C10)*F10)-2),IF((INDEX(Routes!$M$6:$M$9,$C10)*INDEX(Routes!$Y$6:$Y$9,$C10)*F10)<=4,2.9+0.75*((INDEX(Routes!$M$6:$M$9,$C10)*INDEX(Routes!$Y$6:$Y$9,$C10)*F10)-3),IF((INDEX(Routes!$M$6:$M$9,$C10)*INDEX(Routes!$Y$6:$Y$9,$C10)*F10)<=5,3.65+0.6*((INDEX(Routes!$M$6:$M$9,$C10)*INDEX(Routes!$Y$6:$Y$9,$C10)*F10)-4),4.25+0.5*((INDEX(Routes!$M$6:$M$9,$C10)*INDEX(Routes!$Y$6:$Y$9,$C10)*F10)-5))))) -> 0
A11: Bunker price (Brent) — low | B11: tornado | C11: =Sw_Route -> 1 | D11: =Brent_P10 -> 67.98 | E11: =FreightMult -> 1 | F11: =PortMult -> 1 | G11: =UtilFH -> 0.85 | H11: =UtilBH -> 0.5 | I11: =Speed -> 13.5 | J11: =PortCostMult -> 1 | K11: =EUA -> 75 | L11: =INDEX(Routes!$E$6:$E$9,$C11) -> 5000 | M11: =INDEX(Routes!$F$6:$F$9,$C11)/L11 -> 0.13 | N11: =2*L11*(1+SeaMargin)/(I11*24) -> 32.407407 | O11: =(I11/RefSpeed)^SpeedExp -> 1 | P11: =IF(H11>0,1,0) -> 1 | Q11: =N11/2*O11*(ConsLaden+IF(P11=1,ConsLaden,ConsBallast)) -> 875 | R11: =Q11*(1-M11) -> 761.25 | S11: =Q11*M11 -> 113.75 | T11: =1+P11 -> 2 | U11: =INDEX(Routes!$L$6:$L$9,$C11)*T11*F11 -> 10 | V11: =INDEX(Routes!$M$6:$M$9,$C11)*T11*F11 -> 7 | W11: =INDEX(Routes!$H$6:$H$9,$C11)*2 -> 0 | X11: =(U11+V11+W11)*ConsPort -> 102 | Y11: =R11*D11*VLSFO_Mult+(S11+X11)*D11*MGO_Mult -> 540740.11 | Z11: =(INDEX(Routes!$N$6:$N$9,$C11)+AN11+MIN(AC11*INDEX(Routes!$T$6:$T$9,$C11),INDEX(Routes!$V$6:$V$9,$C11))+INDEX(Routes!$O$6:$O$9,$C11)+AO11+MIN(AC11*INDEX(Routes!$U$6:$U$9,$C11),INDEX(Routes!$W$6:$W$9,$C11))+IF(P11=1,INDEX(Routes!$N$6:$N$9,$C11)+AN11+MIN(AD11*INDEX(Routes!$T$6:$T$9,$C11),INDEX(Routes!$V$6:$V$9,$C11))+INDEX(Routes!$O$6:$O$9,$C11)+AO11+MIN(AD11*INDEX(Routes!$U$6:$U$9,$C11),INDEX(Routes!$W$6:$W$9,$C11)),0))*J11 -> 252304.21 | AA11: =INDEX(Routes!$R$6:$R$9,$C11)+IF(P11=1,INDEX(Routes!$R$6:$R$9,$C11),INDEX(Routes!$S$6:$S$9,$C11)) -> 0 | AB11: =((R11*CO2_VLSFO+S11*CO2_MGO)*INDEX(Routes!$I$6:$I$9,$C11)+(U11*INDEX(Routes!$P$6:$P$9,$C11)+V11*INDEX(Routes!$Q$6:$Q$9,$C11))*ConsPort*CO2_MGO)*PhaseIn*K11*FX -> 123936.41 | AC11: =Capacity*G11 -> 30600 | AD11: =Capacity*H11 -> 18000 | AE11: =INDEX(Routes!$J$6:$J$9,$C11)*E11 -> 52 | AF11: =INDEX(Routes!$K$6:$K$9,$C11)*E11 -> 38 | AG11: =AC11*AE11+AD11*AF11 -> 2275200 | AH11: =AG11*Commission -> 56880 | AI11: =Y11+Z11+AA11+AB11+MiscVoy -> 941980.73 | AJ11: =N11+U11+V11+W11 -> 49.407407 | AK11: =(AG11-AH11-AI11)/AJ11 -> 25832.954 | AL11: =AG11-AH11-AI11-Benchmark*AJ11 -> 387005.94 | AM11: =IF(AC11>0,((Benchmark*AJ11+AI11)/(1-Commission)-AD11*AF11)/AC11,0) -> 39.028459 | AN11: =LOA_ft*Port_Tariffs!$C$9*IF((INDEX(Routes!$L$6:$L$9,$C11)*INDEX(Routes!$X$6:$X$9,$C11)*F11)<=2,(INDEX(Routes!$L$6:$L$9,$C11)*INDEX(Routes!$X$6:$X$9,$C11)*F11),IF((INDEX(Routes!$L$6:$L$9,$C11)*INDEX(Routes!$X$6:$X$9,$C11)*F11)<=3,2+0.9*((INDEX(Routes!$L$6:$L$9,$C11)*INDEX(Routes!$X$6:$X$9,$C11)*F11)-2),IF((INDEX(Routes!$L$6:$L$9,$C11)*INDEX(Routes!$X$6:$X$9,$C11)*F11)<=4,2.9+0.75*((INDEX(Routes!$L$6:$L$9,$C11)*INDEX(Routes!$X$6:$X$9,$C11)*F11)-3),IF((INDEX(Routes!$L$6:$L$9,$C11)*INDEX(Routes!$X$6:$X$9,$C11)*F11)<=5,3.65+0.6*((INDEX(Routes!$L$6:$L$9,$C11)*INDEX(Routes!$X$6:$X$9,$C11)*F11)-4),4.25+0.5*((INDEX(Routes!$L$6:$L$9,$C11)*INDEX(Routes!$X$6:$X$9,$C11)*F11)-5))))) -> 19557.6 | AO11: =LOA_ft*Port_Tariffs!$C$9*IF((INDEX(Routes!$M$6:$M$9,$C11)*INDEX(Routes!$Y$6:$Y$9,$C11)*F11)<=2,(INDEX(Routes!$M$6:$M$9,$C11)*INDEX(Routes!$Y$6:$Y$9,$C11)*F11),IF((INDEX(Routes!$M$6:$M$9,$C11)*INDEX(Routes!$Y$6:$Y$9,$C11)*F11)<=3,2+0.9*((INDEX(Routes!$M$6:$M$9,$C11)*INDEX(Routes!$Y$6:$Y$9,$C11)*F11)-2),IF((INDEX(Routes!$M$6:$M$9,$C11)*INDEX(Routes!$Y$6:$Y$9,$C11)*F11)<=4,2.9+0.75*((INDEX(Routes!$M$6:$M$9,$C11)*INDEX(Routes!$Y$6:$Y$9,$C11)*F11)-3),IF((INDEX(Routes!$M$6:$M$9,$C11)*INDEX(Routes!$Y$6:$Y$9,$C11)*F11)<=5,3.65+0.6*((INDEX(Routes!$M$6:$M$9,$C11)*INDEX(Routes!$Y$6:$Y$9,$C11)*F11)-4),4.25+0.5*((INDEX(Routes!$M$6:$M$9,$C11)*INDEX(Routes!$Y$6:$Y$9,$C11)*F11)-5))))) -> 0
A12: Bunker price (Brent) — high | B12: tornado | C12: =Sw_Route -> 1 | D12: =Brent_P90 -> 104.84 | E12: =FreightMult -> 1 | F12: =PortMult -> 1 | G12: =UtilFH -> 0.85 | H12: =UtilBH -> 0.5 | I12: =Speed -> 13.5 | J12: =PortCostMult -> 1 | K12: =EUA -> 75 | L12: =INDEX(Routes!$E$6:$E$9,$C12) -> 5000 | M12: =INDEX(Routes!$F$6:$F$9,$C12)/L12 -> 0.13 | N12: =2*L12*(1+SeaMargin)/(I12*24) -> 32.407407 | O12: =(I12/RefSpeed)^SpeedExp -> 1 | P12: =IF(H12>0,1,0) -> 1 | Q12: =N12/2*O12*(ConsLaden+IF(P12=1,ConsLaden,ConsBallast)) -> 875 | R12: =Q12*(1-M12) -> 761.25 | S12: =Q12*M12 -> 113.75 | T12: =1+P12 -> 2 | U12: =INDEX(Routes!$L$6:$L$9,$C12)*T12*F12 -> 10 | V12: =INDEX(Routes!$M$6:$M$9,$C12)*T12*F12 -> 7 | W12: =INDEX(Routes!$H$6:$H$9,$C12)*2 -> 0 | X12: =(U12+V12+W12)*ConsPort -> 102 | Y12: =R12*D12*VLSFO_Mult+(S12+X12)*D12*MGO_Mult -> 833939.3 | Z12: =(INDEX(Routes!$N$6:$N$9,$C12)+AN12+MIN(AC12*INDEX(Routes!$T$6:$T$9,$C12),INDEX(Routes!$V$6:$V$9,$C12))+INDEX(Routes!$O$6:$O$9,$C12)+AO12+MIN(AC12*INDEX(Routes!$U$6:$U$9,$C12),INDEX(Routes!$W$6:$W$9,$C12))+IF(P12=1,INDEX(Routes!$N$6:$N$9,$C12)+AN12+MIN(AD12*INDEX(Routes!$T$6:$T$9,$C12),INDEX(Routes!$V$6:$V$9,$C12))+INDEX(Routes!$O$6:$O$9,$C12)+AO12+MIN(AD12*INDEX(Routes!$U$6:$U$9,$C12),INDEX(Routes!$W$6:$W$9,$C12)),0))*J12 -> 252304.21 | AA12: =INDEX(Routes!$R$6:$R$9,$C12)+IF(P12=1,INDEX(Routes!$R$6:$R$9,$C12),INDEX(Routes!$S$6:$S$9,$C12)) -> 0 | AB12: =((R12*CO2_VLSFO+S12*CO2_MGO)*INDEX(Routes!$I$6:$I$9,$C12)+(U12*INDEX(Routes!$P$6:$P$9,$C12)+V12*INDEX(Routes!$Q$6:$Q$9,$C12))*ConsPort*CO2_MGO)*PhaseIn*K12*FX -> 123936.41 | AC12: =Capacity*G12 -> 30600 | AD12: =Capacity*H12 -> 18000 | AE12: =INDEX(Routes!$J$6:$J$9,$C12)*E12 -> 52 | AF12: =INDEX(Routes!$K$6:$K$9,$C12)*E12 -> 38 | AG12: =AC12*AE12+AD12*AF12 -> 2275200 | AH12: =AG12*Commission -> 56880 | AI12: =Y12+Z12+AA12+AB12+MiscVoy -> 1235179.9 | AJ12: =N12+U12+V12+W12 -> 49.407407 | AK12: =(AG12-AH12-AI12)/AJ12 -> 19898.637 | AL12: =AG12-AH12-AI12-Benchmark*AJ12 -> 93806.752 | AM12: =IF(AC12>0,((Benchmark*AJ12+AI12)/(1-Commission)-AD12*AF12)/AC12,0) -> 48.855815 | AN12: =LOA_ft*Port_Tariffs!$C$9*IF((INDEX(Routes!$L$6:$L$9,$C12)*INDEX(Routes!$X$6:$X$9,$C12)*F12)<=2,(INDEX(Routes!$L$6:$L$9,$C12)*INDEX(Routes!$X$6:$X$9,$C12)*F12),IF((INDEX(Routes!$L$6:$L$9,$C12)*INDEX(Routes!$X$6:$X$9,$C12)*F12)<=3,2+0.9*((INDEX(Routes!$L$6:$L$9,$C12)*INDEX(Routes!$X$6:$X$9,$C12)*F12)-2),IF((INDEX(Routes!$L$6:$L$9,$C12)*INDEX(Routes!$X$6:$X$9,$C12)*F12)<=4,2.9+0.75*((INDEX(Routes!$L$6:$L$9,$C12)*INDEX(Routes!$X$6:$X$9,$C12)*F12)-3),IF((INDEX(Routes!$L$6:$L$9,$C12)*INDEX(Routes!$X$6:$X$9,$C12)*F12)<=5,3.65+0.6*((INDEX(Routes!$L$6:$L$9,$C12)*INDEX(Routes!$X$6:$X$9,$C12)*F12)-4),4.25+0.5*((INDEX(Routes!$L$6:$L$9,$C12)*INDEX(Routes!$X$6:$X$9,$C12)*F12)-5))))) -> 19557.6 | AO12: =LOA_ft*Port_Tariffs!$C$9*IF((INDEX(Routes!$M$6:$M$9,$C12)*INDEX(Routes!$Y$6:$Y$9,$C12)*F12)<=2,(INDEX(Routes!$M$6:$M$9,$C12)*INDEX(Routes!$Y$6:$Y$9,$C12)*F12),IF((INDEX(Routes!$M$6:$M$9,$C12)*INDEX(Routes!$Y$6:$Y$9,$C12)*F12)<=3,2+0.9*((INDEX(Routes!$M$6:$M$9,$C12)*INDEX(Routes!$Y$6:$Y$9,$C12)*F12)-2),IF((INDEX(Routes!$M$6:$M$9,$C12)*INDEX(Routes!$Y$6:$Y$9,$C12)*F12)<=4,2.9+0.75*((INDEX(Routes!$M$6:$M$9,$C12)*INDEX(Routes!$Y$6:$Y$9,$C12)*F12)-3),IF((INDEX(Routes!$M$6:$M$9,$C12)*INDEX(Routes!$Y$6:$Y$9,$C12)*F12)<=5,3.65+0.6*((INDEX(Routes!$M$6:$M$9,$C12)*INDEX(Routes!$Y$6:$Y$9,$C12)*F12)-4),4.25+0.5*((INDEX(Routes!$M$6:$M$9,$C12)*INDEX(Routes!$Y$6:$Y$9,$C12)*F12)-5))))) -> 0
A13: Port time (congestion) — low | B13: tornado | C13: =Sw_Route -> 1 | D13: =Brent -> 82.01 | E13: =FreightMult -> 1 | F13: 0.75 | G13: =UtilFH -> 0.85 | H13: =UtilBH -> 0.5 | I13: =Speed -> 13.5 | J13: =PortCostMult -> 1 | K13: =EUA -> 75 | L13: =INDEX(Routes!$E$6:$E$9,$C13) -> 5000 | M13: =INDEX(Routes!$F$6:$F$9,$C13)/L13 -> 0.13 | N13: =2*L13*(1+SeaMargin)/(I13*24) -> 32.407407 | O13: =(I13/RefSpeed)^SpeedExp -> 1 | P13: =IF(H13>0,1,0) -> 1 | Q13: =N13/2*O13*(ConsLaden+IF(P13=1,ConsLaden,ConsBallast)) -> 875 | R13: =Q13*(1-M13) -> 761.25 | S13: =Q13*M13 -> 113.75 | T13: =1+P13 -> 2 | U13: =INDEX(Routes!$L$6:$L$9,$C13)*T13*F13 -> 7.5 | V13: =INDEX(Routes!$M$6:$M$9,$C13)*T13*F13 -> 5.25 | W13: =INDEX(Routes!$H$6:$H$9,$C13)*2 -> 0 | X13: =(U13+V13+W13)*ConsPort -> 76.5 | Y13: =R13*D13*VLSFO_Mult+(S13+X13)*D13*MGO_Mult -> 632055.17 | Z13: =(INDEX(Routes!$N$6:$N$9,$C13)+AN13+MIN(AC13*INDEX(Routes!$T$6:$T$9,$C13),INDEX(Routes!$V$6:$V$9,$C13))+INDEX(Routes!$O$6:$O$9,$C13)+AO13+MIN(AC13*INDEX(Routes!$U$6:$U$9,$C13),INDEX(Routes!$W$6:$W$9,$C13))+IF(P13=1,INDEX(Routes!$N$6:$N$9,$C13)+AN13+MIN(AD13*INDEX(Routes!$T$6:$T$9,$C13),INDEX(Routes!$V$6:$V$9,$C13))+INDEX(Routes!$O$6:$O$9,$C13)+AO13+MIN(AD13*INDEX(Routes!$U$6:$U$9,$C13),INDEX(Routes!$W$6:$W$9,$C13)),0))*J13 -> 243199.81 | AA13: =INDEX(Routes!$R$6:$R$9,$C13)+IF(P13=1,INDEX(Routes!$R$6:$R$9,$C13),INDEX(Routes!$S$6:$S$9,$C13)) -> 0 | AB13: =((R13*CO2_VLSFO+S13*CO2_MGO)*INDEX(Routes!$I$6:$I$9,$C13)+(U13*INDEX(Routes!$P$6:$P$9,$C13)+V13*INDEX(Routes!$Q$6:$Q$9,$C13))*ConsPort*CO2_MGO)*PhaseIn*K13*FX -> 121159.21 | AC13: =Capacity*G13 -> 30600 | AD13: =Capacity*H13 -> 18000 | AE13: =INDEX(Routes!$J$6:$J$9,$C13)*E13 -> 52 | AF13: =INDEX(Routes!$K$6:$K$9,$C13)*E13 -> 38 | AG13: =AC13*AE13+AD13*AF13 -> 2275200 | AH13: =AG13*Commission -> 56880 | AI13: =Y13+Z13+AA13+AB13+MiscVoy -> 1021414.2 | AJ13: =N13+U13+V13+W13 -> 45.157407 | AK13: =(AG13-AH13-AI13)/AJ13 -> 26505.193 | AL13: =AG13-AH13-AI13-Benchmark*AJ13 -> 384072.48 | AM13: =IF(AC13>0,((Benchmark*AJ13+AI13)/(1-Commission)-AD13*AF13)/AC13,0) -> 39.126781 | AN13: =LOA_ft*Port_Tariffs!$C$9*IF((INDEX(Routes!$L$6:$L$9,$C13)*INDEX(Routes!$X$6:$X$9,$C13)*F13)<=2,(INDEX(Routes!$L$6:$L$9,$C13)*INDEX(Routes!$X$6:$X$9,$C13)*F13),IF((INDEX(Routes!$L$6:$L$9,$C13)*INDEX(Routes!$X$6:$X$9,$C13)*F13)<=3,2+0.9*((INDEX(Routes!$L$6:$L$9,$C13)*INDEX(Routes!$X$6:$X$9,$C13)*F13)-2),IF((INDEX(Routes!$L$6:$L$9,$C13)*INDEX(Routes!$X$6:$X$9,$C13)*F13)<=4,2.9+0.75*((INDEX(Routes!$L$6:$L$9,$C13)*INDEX(Routes!$X$6:$X$9,$C13)*F13)-3),IF((INDEX(Routes!$L$6:$L$9,$C13)*INDEX(Routes!$X$6:$X$9,$C13)*F13)<=5,3.65+0.6*((INDEX(Routes!$L$6:$L$9,$C13)*INDEX(Routes!$X$6:$X$9,$C13)*F13)-4),4.25+0.5*((INDEX(Routes!$L$6:$L$9,$C13)*INDEX(Routes!$X$6:$X$9,$C13)*F13)-5))))) -> 15005.4 | AO13: =LOA_ft*Port_Tariffs!$C$9*IF((INDEX(Routes!$M$6:$M$9,$C13)*INDEX(Routes!$Y$6:$Y$9,$C13)*F13)<=2,(INDEX(Routes!$M$6:$M$9,$C13)*INDEX(Routes!$Y$6:$Y$9,$C13)*F13),IF((INDEX(Routes!$M$6:$M$9,$C13)*INDEX(Routes!$Y$6:$Y$9,$C13)*F13)<=3,2+0.9*((INDEX(Routes!$M$6:$M$9,$C13)*INDEX(Routes!$Y$6:$Y$9,$C13)*F13)-2),IF((INDEX(Routes!$M$6:$M$9,$C13)*INDEX(Routes!$Y$6:$Y$9,$C13)*F13)<=4,2.9+0.75*((INDEX(Routes!$M$6:$M$9,$C13)*INDEX(Routes!$Y$6:$Y$9,$C13)*F13)-3),IF((INDEX(Routes!$M$6:$M$9,$C13)*INDEX(Routes!$Y$6:$Y$9,$C13)*F13)<=5,3.65+0.6*((INDEX(Routes!$M$6:$M$9,$C13)*INDEX(Routes!$Y$6:$Y$9,$C13)*F13)-4),4.25+0.5*((INDEX(Routes!$M$6:$M$9,$C13)*INDEX(Routes!$Y$6:$Y$9,$C13)*F13)-5))))) -> 0
A14: Port time (congestion) — high | B14: tornado | C14: =Sw_Route -> 1 | D14: =Brent -> 82.01 | E14: =FreightMult -> 1 | F14: 1.75 | G14: =UtilFH -> 0.85 | H14: =UtilBH -> 0.5 | I14: =Speed -> 13.5 | J14: =PortCostMult -> 1 | K14: =EUA -> 75 | L14: =INDEX(Routes!$E$6:$E$9,$C14) -> 5000 | M14: =INDEX(Routes!$F$6:$F$9,$C14)/L14 -> 0.13 | N14: =2*L14*(1+SeaMargin)/(I14*24) -> 32.407407 | O14: =(I14/RefSpeed)^SpeedExp -> 1 | P14: =IF(H14>0,1,0) -> 1 | Q14: =N14/2*O14*(ConsLaden+IF(P14=1,ConsLaden,ConsBallast)) -> 875 | R14: =Q14*(1-M14) -> 761.25 | S14: =Q14*M14 -> 113.75 | T14: =1+P14 -> 2 | U14: =INDEX(Routes!$L$6:$L$9,$C14)*T14*F14 -> 17.5 | V14: =INDEX(Routes!$M$6:$M$9,$C14)*T14*F14 -> 12.25 | W14: =INDEX(Routes!$H$6:$H$9,$C14)*2 -> 0 | X14: =(U14+V14+W14)*ConsPort -> 178.5 | Y14: =R14*D14*VLSFO_Mult+(S14+X14)*D14*MGO_Mult -> 713195.86 | Z14: =(INDEX(Routes!$N$6:$N$9,$C14)+AN14+MIN(AC14*INDEX(Routes!$T$6:$T$9,$C14),INDEX(Routes!$V$6:$V$9,$C14))+INDEX(Routes!$O$6:$O$9,$C14)+AO14+MIN(AC14*INDEX(Routes!$U$6:$U$9,$C14),INDEX(Routes!$W$6:$W$9,$C14))+IF(P14=1,INDEX(Routes!$N$6:$N$9,$C14)+AN14+MIN(AD14*INDEX(Routes!$T$6:$T$9,$C14),INDEX(Routes!$V$6:$V$9,$C14))+INDEX(Routes!$O$6:$O$9,$C14)+AO14+MIN(AD14*INDEX(Routes!$U$6:$U$9,$C14),INDEX(Routes!$W$6:$W$9,$C14)),0))*J14 -> 272199.01 | AA14: =INDEX(Routes!$R$6:$R$9,$C14)+IF(P14=1,INDEX(Routes!$R$6:$R$9,$C14),INDEX(Routes!$S$6:$S$9,$C14)) -> 0 | AB14: =((R14*CO2_VLSFO+S14*CO2_MGO)*INDEX(Routes!$I$6:$I$9,$C14)+(U14*INDEX(Routes!$P$6:$P$9,$C14)+V14*INDEX(Routes!$Q$6:$Q$9,$C14))*ConsPort*CO2_MGO)*PhaseIn*K14*FX -> 132268 | AC14: =Capacity*G14 -> 30600 | AD14: =Capacity*H14 -> 18000 | AE14: =INDEX(Routes!$J$6:$J$9,$C14)*E14 -> 52 | AF14: =INDEX(Routes!$K$6:$K$9,$C14)*E14 -> 38 | AG14: =AC14*AE14+AD14*AF14 -> 2275200 | AH14: =AG14*Commission -> 56880 | AI14: =Y14+Z14+AA14+AB14+MiscVoy -> 1142662.9 | AJ14: =N14+U14+V14+W14 -> 62.157407 | AK14: =(AG14-AH14-AI14)/AJ14 -> 17305.373 | AL14: =AG14-AH14-AI14-Benchmark*AJ14 -> -43176.209 | AM14: =IF(AC14>0,((Benchmark*AJ14+AI14)/(1-Commission)-AD14*AF14)/AC14,0) -> 53.447166 | AN14: =LOA_ft*Port_Tariffs!$C$9*IF((INDEX(Routes!$L$6:$L$9,$C14)*INDEX(Routes!$X$6:$X$9,$C14)*F14)<=2,(INDEX(Routes!$L$6:$L$9,$C14)*INDEX(Routes!$X$6:$X$9,$C14)*F14),IF((INDEX(Routes!$L$6:$L$9,$C14)*INDEX(Routes!$X$6:$X$9,$C14)*F14)<=3,2+0.9*((INDEX(Routes!$L$6:$L$9,$C14)*INDEX(Routes!$X$6:$X$9,$C14)*F14)-2),IF((INDEX(Routes!$L$6:$L$9,$C14)*INDEX(Routes!$X$6:$X$9,$C14)*F14)<=4,2.9+0.75*((INDEX(Routes!$L$6:$L$9,$C14)*INDEX(Routes!$X$6:$X$9,$C14)*F14)-3),IF((INDEX(Routes!$L$6:$L$9,$C14)*INDEX(Routes!$X$6:$X$9,$C14)*F14)<=5,3.65+0.6*((INDEX(Routes!$L$6:$L$9,$C14)*INDEX(Routes!$X$6:$X$9,$C14)*F14)-4),4.25+0.5*((INDEX(Routes!$L$6:$L$9,$C14)*INDEX(Routes!$X$6:$X$9,$C14)*F14)-5))))) -> 29505 | AO14: =LOA_ft*Port_Tariffs!$C$9*IF((INDEX(Routes!$M$6:$M$9,$C14)*INDEX(Routes!$Y$6:$Y$9,$C14)*F14)<=2,(INDEX(Routes!$M$6:$M$9,$C14)*INDEX(Routes!$Y$6:$Y$9,$C14)*F14),IF((INDEX(Routes!$M$6:$M$9,$C14)*INDEX(Routes!$Y$6:$Y$9,$C14)*F14)<=3,2+0.9*((INDEX(Routes!$M$6:$M$9,$C14)*INDEX(Routes!$Y$6:$Y$9,$C14)*F14)-2),IF((INDEX(Routes!$M$6:$M$9,$C14)*INDEX(Routes!$Y$6:$Y$9,$C14)*F14)<=4,2.9+0.75*((INDEX(Routes!$M$6:$M$9,$C14)*INDEX(Routes!$Y$6:$Y$9,$C14)*F14)-3),IF((INDEX(Routes!$M$6:$M$9,$C14)*INDEX(Routes!$Y$6:$Y$9,$C14)*F14)<=5,3.65+0.6*((INDEX(Routes!$M$6:$M$9,$C14)*INDEX(Routes!$Y$6:$Y$9,$C14)*F14)-4),4.25+0.5*((INDEX(Routes!$M$6:$M$9,$C14)*INDEX(Routes!$Y$6:$Y$9,$C14)*F14)-5))))) -> 0
A15: Fronthaul utilization — low | B15: tornado | C15: =Sw_Route -> 1 | D15: =Brent -> 82.01 | E15: =FreightMult -> 1 | F15: =PortMult -> 1 | G15: 0.7 | H15: =UtilBH -> 0.5 | I15: =Speed -> 13.5 | J15: =PortCostMult -> 1 | K15: =EUA -> 75 | L15: =INDEX(Routes!$E$6:$E$9,$C15) -> 5000 | M15: =INDEX(Routes!$F$6:$F$9,$C15)/L15 -> 0.13 | N15: =2*L15*(1+SeaMargin)/(I15*24) -> 32.407407 | O15: =(I15/RefSpeed)^SpeedExp -> 1 | P15: =IF(H15>0,1,0) -> 1 | Q15: =N15/2*O15*(ConsLaden+IF(P15=1,ConsLaden,ConsBallast)) -> 875 | R15: =Q15*(1-M15) -> 761.25 | S15: =Q15*M15 -> 113.75 | T15: =1+P15 -> 2 | U15: =INDEX(Routes!$L$6:$L$9,$C15)*T15*F15 -> 10 | V15: =INDEX(Routes!$M$6:$M$9,$C15)*T15*F15 -> 7 | W15: =INDEX(Routes!$H$6:$H$9,$C15)*2 -> 0 | X15: =(U15+V15+W15)*ConsPort -> 102 | Y15: =R15*D15*VLSFO_Mult+(S15+X15)*D15*MGO_Mult -> 652340.34 | Z15: =(INDEX(Routes!$N$6:$N$9,$C15)+AN15+MIN(AC15*INDEX(Routes!$T$6:$T$9,$C15),INDEX(Routes!$V$6:$V$9,$C15))+INDEX(Routes!$O$6:$O$9,$C15)+AO15+MIN(AC15*INDEX(Routes!$U$6:$U$9,$C15),INDEX(Routes!$W$6:$W$9,$C15))+IF(P15=1,INDEX(Routes!$N$6:$N$9,$C15)+AN15+MIN(AD15*INDEX(Routes!$T$6:$T$9,$C15),INDEX(Routes!$V$6:$V$9,$C15))+INDEX(Routes!$O$6:$O$9,$C15)+AO15+MIN(AD15*INDEX(Routes!$U$6:$U$9,$C15),INDEX(Routes!$W$6:$W$9,$C15)),0))*J15 -> 248763.02 | AA15: =INDEX(Routes!$R$6:$R$9,$C15)+IF(P15=1,INDEX(Routes!$R$6:$R$9,$C15),INDEX(Routes!$S$6:$S$9,$C15)) -> 0 | AB15: =((R15*CO2_VLSFO+S15*CO2_MGO)*INDEX(Routes!$I$6:$I$9,$C15)+(U15*INDEX(Routes!$P$6:$P$9,$C15)+V15*INDEX(Routes!$Q$6:$Q$9,$C15))*ConsPort*CO2_MGO)*PhaseIn*K15*FX -> 123936.41 | AC15: =Capacity*G15 -> 25200 | AD15: =Capacity*H15 -> 18000 | AE15: =INDEX(Routes!$J$6:$J$9,$C15)*E15 -> 52 | AF15: =INDEX(Routes!$K$6:$K$9,$C15)*E15 -> 38 | AG15: =AC15*AE15+AD15*AF15 -> 1994400 | AH15: =AG15*Commission -> 49860 | AI15: =Y15+Z15+AA15+AB15+MiscVoy -> 1050039.8 | AJ15: =N15+U15+V15+W15 -> 49.407407 | AK15: =(AG15-AH15-AI15)/AJ15 -> 18104.577 | AL15: =AG15-AH15-AI15-Benchmark*AJ15 -> 5166.8947 | AM15: =IF(AC15>0,((Benchmark*AJ15+AI15)/(1-Commission)-AD15*AF15)/AC15,0) -> 51.789707 | AN15: =LOA_ft*Port_Tariffs!$C$9*IF((INDEX(Routes!$L$6:$L$9,$C15)*INDEX(Routes!$X$6:$X$9,$C15)*F15)<=2,(INDEX(Routes!$L$6:$L$9,$C15)*INDEX(Routes!$X$6:$X$9,$C15)*F15),IF((INDEX(Routes!$L$6:$L$9,$C15)*INDEX(Routes!$X$6:$X$9,$C15)*F15)<=3,2+0.9*((INDEX(Routes!$L$6:$L$9,$C15)*INDEX(Routes!$X$6:$X$9,$C15)*F15)-2),IF((INDEX(Routes!$L$6:$L$9,$C15)*INDEX(Routes!$X$6:$X$9,$C15)*F15)<=4,2.9+0.75*((INDEX(Routes!$L$6:$L$9,$C15)*INDEX(Routes!$X$6:$X$9,$C15)*F15)-3),IF((INDEX(Routes!$L$6:$L$9,$C15)*INDEX(Routes!$X$6:$X$9,$C15)*F15)<=5,3.65+0.6*((INDEX(Routes!$L$6:$L$9,$C15)*INDEX(Routes!$X$6:$X$9,$C15)*F15)-4),4.25+0.5*((INDEX(Routes!$L$6:$L$9,$C15)*INDEX(Routes!$X$6:$X$9,$C15)*F15)-5))))) -> 19557.6 | AO15: =LOA_ft*Port_Tariffs!$C$9*IF((INDEX(Routes!$M$6:$M$9,$C15)*INDEX(Routes!$Y$6:$Y$9,$C15)*F15)<=2,(INDEX(Routes!$M$6:$M$9,$C15)*INDEX(Routes!$Y$6:$Y$9,$C15)*F15),IF((INDEX(Routes!$M$6:$M$9,$C15)*INDEX(Routes!$Y$6:$Y$9,$C15)*F15)<=3,2+0.9*((INDEX(Routes!$M$6:$M$9,$C15)*INDEX(Routes!$Y$6:$Y$9,$C15)*F15)-2),IF((INDEX(Routes!$M$6:$M$9,$C15)*INDEX(Routes!$Y$6:$Y$9,$C15)*F15)<=4,2.9+0.75*((INDEX(Routes!$M$6:$M$9,$C15)*INDEX(Routes!$Y$6:$Y$9,$C15)*F15)-3),IF((INDEX(Routes!$M$6:$M$9,$C15)*INDEX(Routes!$Y$6:$Y$9,$C15)*F15)<=5,3.65+0.6*((INDEX(Routes!$M$6:$M$9,$C15)*INDEX(Routes!$Y$6:$Y$9,$C15)*F15)-4),4.25+0.5*((INDEX(Routes!$M$6:$M$9,$C15)*INDEX(Routes!$Y$6:$Y$9,$C15)*F15)-5))))) -> 0
A16: Fronthaul utilization — high | B16: tornado | C16: =Sw_Route -> 1 | D16: =Brent -> 82.01 | E16: =FreightMult -> 1 | F16: =PortMult -> 1 | G16: 0.95 | H16: =UtilBH -> 0.5 | I16: =Speed -> 13.5 | J16: =PortCostMult -> 1 | K16: =EUA -> 75 | L16: =INDEX(Routes!$E$6:$E$9,$C16) -> 5000 | M16: =INDEX(Routes!$F$6:$F$9,$C16)/L16 -> 0.13 | N16: =2*L16*(1+SeaMargin)/(I16*24) -> 32.407407 | O16: =(I16/RefSpeed)^SpeedExp -> 1 | P16: =IF(H16>0,1,0) -> 1 | Q16: =N16/2*O16*(ConsLaden+IF(P16=1,ConsLaden,ConsBallast)) -> 875 | R16: =Q16*(1-M16) -> 761.25 | S16: =Q16*M16 -> 113.75 | T16: =1+P16 -> 2 | U16: =INDEX(Routes!$L$6:$L$9,$C16)*T16*F16 -> 10 | V16: =INDEX(Routes!$M$6:$M$9,$C16)*T16*F16 -> 7 | W16: =INDEX(Routes!$H$6:$H$9,$C16)*2 -> 0 | X16: =(U16+V16+W16)*ConsPort -> 102 | Y16: =R16*D16*VLSFO_Mult+(S16+X16)*D16*MGO_Mult -> 652340.34 | Z16: =(INDEX(Routes!$N$6:$N$9,$C16)+AN16+MIN(AC16*INDEX(Routes!$T$6:$T$9,$C16),INDEX(Routes!$V$6:$V$9,$C16))+INDEX(Routes!$O$6:$O$9,$C16)+AO16+MIN(AC16*INDEX(Routes!$U$6:$U$9,$C16),INDEX(Routes!$W$6:$W$9,$C16))+IF(P16=1,INDEX(Routes!$N$6:$N$9,$C16)+AN16+MIN(AD16*INDEX(Routes!$T$6:$T$9,$C16),INDEX(Routes!$V$6:$V$9,$C16))+INDEX(Routes!$O$6:$O$9,$C16)+AO16+MIN(AD16*INDEX(Routes!$U$6:$U$9,$C16),INDEX(Routes!$W$6:$W$9,$C16)),0))*J16 -> 252779.98 | AA16: =INDEX(Routes!$R$6:$R$9,$C16)+IF(P16=1,INDEX(Routes!$R$6:$R$9,$C16),INDEX(Routes!$S$6:$S$9,$C16)) -> 0 | AB16: =((R16*CO2_VLSFO+S16*CO2_MGO)*INDEX(Routes!$I$6:$I$9,$C16)+(U16*INDEX(Routes!$P$6:$P$9,$C16)+V16*INDEX(Routes!$Q$6:$Q$9,$C16))*ConsPort*CO2_MGO)*PhaseIn*K16*FX -> 123936.41 | AC16: =Capacity*G16 -> 34200 | AD16: =Capacity*H16 -> 18000 | AE16: =INDEX(Routes!$J$6:$J$9,$C16)*E16 -> 52 | AF16: =INDEX(Routes!$K$6:$K$9,$C16)*E16 -> 38 | AG16: =AC16*AE16+AD16*AF16 -> 2462400 | AH16: =AG16*Commission -> 61560 | AI16: =Y16+Z16+AA16+AB16+MiscVoy -> 1054056.7 | AJ16: =N16+U16+V16+W16 -> 49.407407 | AK16: =(AG16-AH16-AI16)/AJ16 -> 27258.732 | AL16: =AG16-AH16-AI16-Benchmark*AJ16 -> 457449.94 | AM16: =IF(AC16>0,((Benchmark*AJ16+AI16)/(1-Commission)-AD16*AF16)/AC16,0) -> 38.281303 | AN16: =LOA_ft*Port_Tariffs!$C$9*IF((INDEX(Routes!$L$6:$L$9,$C16)*INDEX(Routes!$X$6:$X$9,$C16)*F16)<=2,(INDEX(Routes!$L$6:$L$9,$C16)*INDEX(Routes!$X$6:$X$9,$C16)*F16),IF((INDEX(Routes!$L$6:$L$9,$C16)*INDEX(Routes!$X$6:$X$9,$C16)*F16)<=3,2+0.9*((INDEX(Routes!$L$6:$L$9,$C16)*INDEX(Routes!$X$6:$X$9,$C16)*F16)-2),IF((INDEX(Routes!$L$6:$L$9,$C16)*INDEX(Routes!$X$6:$X$9,$C16)*F16)<=4,2.9+0.75*((INDEX(Routes!$L$6:$L$9,$C16)*INDEX(Routes!$X$6:$X$9,$C16)*F16)-3),IF((INDEX(Routes!$L$6:$L$9,$C16)*INDEX(Routes!$X$6:$X$9,$C16)*F16)<=5,3.65+0.6*((INDEX(Routes!$L$6:$L$9,$C16)*INDEX(Routes!$X$6:$X$9,$C16)*F16)-4),4.25+0.5*((INDEX(Routes!$L$6:$L$9,$C16)*INDEX(Routes!$X$6:$X$9,$C16)*F16)-5))))) -> 19557.6 | AO16: =LOA_ft*Port_Tariffs!$C$9*IF((INDEX(Routes!$M$6:$M$9,$C16)*INDEX(Routes!$Y$6:$Y$9,$C16)*F16)<=2,(INDEX(Routes!$M$6:$M$9,$C16)*INDEX(Routes!$Y$6:$Y$9,$C16)*F16),IF((INDEX(Routes!$M$6:$M$9,$C16)*INDEX(Routes!$Y$6:$Y$9,$C16)*F16)<=3,2+0.9*((INDEX(Routes!$M$6:$M$9,$C16)*INDEX(Routes!$Y$6:$Y$9,$C16)*F16)-2),IF((INDEX(Routes!$M$6:$M$9,$C16)*INDEX(Routes!$Y$6:$Y$9,$C16)*F16)<=4,2.9+0.75*((INDEX(Routes!$M$6:$M$9,$C16)*INDEX(Routes!$Y$6:$Y$9,$C16)*F16)-3),IF((INDEX(Routes!$M$6:$M$9,$C16)*INDEX(Routes!$Y$6:$Y$9,$C16)*F16)<=5,3.65+0.6*((INDEX(Routes!$M$6:$M$9,$C16)*INDEX(Routes!$Y$6:$Y$9,$C16)*F16)-4),4.25+0.5*((INDEX(Routes!$M$6:$M$9,$C16)*INDEX(Routes!$Y$6:$Y$9,$C16)*F16)-5))))) -> 0
A17: Backhaul utilization — low | B17: tornado | C17: =Sw_Route -> 1 | D17: =Brent -> 82.01 | E17: =FreightMult -> 1 | F17: =PortMult -> 1 | G17: =UtilFH -> 0.85 | H17: 0.25 | I17: =Speed -> 13.5 | J17: =PortCostMult -> 1 | K17: =EUA -> 75 | L17: =INDEX(Routes!$E$6:$E$9,$C17) -> 5000 | M17: =INDEX(Routes!$F$6:$F$9,$C17)/L17 -> 0.13 | N17: =2*L17*(1+SeaMargin)/(I17*24) -> 32.407407 | O17: =(I17/RefSpeed)^SpeedExp -> 1 | P17: =IF(H17>0,1,0) -> 1 | Q17: =N17/2*O17*(ConsLaden+IF(P17=1,ConsLaden,ConsBallast)) -> 875 | R17: =Q17*(1-M17) -> 761.25 | S17: =Q17*M17 -> 113.75 | T17: =1+P17 -> 2 | U17: =INDEX(Routes!$L$6:$L$9,$C17)*T17*F17 -> 10 | V17: =INDEX(Routes!$M$6:$M$9,$C17)*T17*F17 -> 7 | W17: =INDEX(Routes!$H$6:$H$9,$C17)*2 -> 0 | X17: =(U17+V17+W17)*ConsPort -> 102 | Y17: =R17*D17*VLSFO_Mult+(S17+X17)*D17*MGO_Mult -> 652340.34 | Z17: =(INDEX(Routes!$N$6:$N$9,$C17)+AN17+MIN(AC17*INDEX(Routes!$T$6:$T$9,$C17),INDEX(Routes!$V$6:$V$9,$C17))+INDEX(Routes!$O$6:$O$9,$C17)+AO17+MIN(AC17*INDEX(Routes!$U$6:$U$9,$C17),INDEX(Routes!$W$6:$W$9,$C17))+IF(P17=1,INDEX(Routes!$N$6:$N$9,$C17)+AN17+MIN(AD17*INDEX(Routes!$T$6:$T$9,$C17),INDEX(Routes!$V$6:$V$9,$C17))+INDEX(Routes!$O$6:$O$9,$C17)+AO17+MIN(AD17*INDEX(Routes!$U$6:$U$9,$C17),INDEX(Routes!$W$6:$W$9,$C17)),0))*J17 -> 246402.23 | AA17: =INDEX(Routes!$R$6:$R$9,$C17)+IF(P17=1,INDEX(Routes!$R$6:$R$9,$C17),INDEX(Routes!$S$6:$S$9,$C17)) -> 0 | AB17: =((R17*CO2_VLSFO+S17*CO2_MGO)*INDEX(Routes!$I$6:$I$9,$C17)+(U17*INDEX(Routes!$P$6:$P$9,$C17)+V17*INDEX(Routes!$Q$6:$Q$9,$C17))*ConsPort*CO2_MGO)*PhaseIn*K17*FX -> 123936.41 | AC17: =Capacity*G17 -> 30600 | AD17: =Capacity*H17 -> 9000 | AE17: =INDEX(Routes!$J$6:$J$9,$C17)*E17 -> 52 | AF17: =INDEX(Routes!$K$6:$K$9,$C17)*E17 -> 38 | AG17: =AC17*AE17+AD17*AF17 -> 1933200 | AH17: =AG17*Commission -> 48330 | AI17: =Y17+Z17+AA17+AB17+MiscVoy -> 1047679 | AJ17: =N17+U17+V17+W17 -> 49.407407 | AK17: =(AG17-AH17-AI17)/AJ17 -> 16944.646 | AL17: =AG17-AH17-AI17-Benchmark*AJ17 -> -52142.312 | AM17: =IF(AC17>0,((Benchmark*AJ17+AI17)/(1-Commission)-AD17*AF17)/AC17,0) -> 53.747689 | AN17: =LOA_ft*Port_Tariffs!$C$9*IF((INDEX(Routes!$L$6:$L$9,$C17)*INDEX(Routes!$X$6:$X$9,$C17)*F17)<=2,(INDEX(Routes!$L$6:$L$9,$C17)*INDEX(Routes!$X$6:$X$9,$C17)*F17),IF((INDEX(Routes!$L$6:$L$9,$C17)*INDEX(Routes!$X$6:$X$9,$C17)*F17)<=3,2+0.9*((INDEX(Routes!$L$6:$L$9,$C17)*INDEX(Routes!$X$6:$X$9,$C17)*F17)-2),IF((INDEX(Routes!$L$6:$L$9,$C17)*INDEX(Routes!$X$6:$X$9,$C17)*F17)<=4,2.9+0.75*((INDEX(Routes!$L$6:$L$9,$C17)*INDEX(Routes!$X$6:$X$9,$C17)*F17)-3),IF((INDEX(Routes!$L$6:$L$9,$C17)*INDEX(Routes!$X$6:$X$9,$C17)*F17)<=5,3.65+0.6*((INDEX(Routes!$L$6:$L$9,$C17)*INDEX(Routes!$X$6:$X$9,$C17)*F17)-4),4.25+0.5*((INDEX(Routes!$L$6:$L$9,$C17)*INDEX(Routes!$X$6:$X$9,$C17)*F17)-5))))) -> 19557.6 | AO17: =LOA_ft*Port_Tariffs!$C$9*IF((INDEX(Routes!$M$6:$M$9,$C17)*INDEX(Routes!$Y$6:$Y$9,$C17)*F17)<=2,(INDEX(Routes!$M$6:$M$9,$C17)*INDEX(Routes!$Y$6:$Y$9,$C17)*F17),IF((INDEX(Routes!$M$6:$M$9,$C17)*INDEX(Routes!$Y$6:$Y$9,$C17)*F17)<=3,2+0.9*((INDEX(Routes!$M$6:$M$9,$C17)*INDEX(Routes!$Y$6:$Y$9,$C17)*F17)-2),IF((INDEX(Routes!$M$6:$M$9,$C17)*INDEX(Routes!$Y$6:$Y$9,$C17)*F17)<=4,2.9+0.75*((INDEX(Routes!$M$6:$M$9,$C17)*INDEX(Routes!$Y$6:$Y$9,$C17)*F17)-3),IF((INDEX(Routes!$M$6:$M$9,$C17)*INDEX(Routes!$Y$6:$Y$9,$C17)*F17)<=5,3.65+0.6*((INDEX(Routes!$M$6:$M$9,$C17)*INDEX(Routes!$Y$6:$Y$9,$C17)*F17)-4),4.25+0.5*((INDEX(Routes!$M$6:$M$9,$C17)*INDEX(Routes!$Y$6:$Y$9,$C17)*F17)-5))))) -> 0
A18: Backhaul utilization — high | B18: tornado | C18: =Sw_Route -> 1 | D18: =Brent -> 82.01 | E18: =FreightMult -> 1 | F18: =PortMult -> 1 | G18: =UtilFH -> 0.85 | H18: 0.75 | I18: =Speed -> 13.5 | J18: =PortCostMult -> 1 | K18: =EUA -> 75 | L18: =INDEX(Routes!$E$6:$E$9,$C18) -> 5000 | M18: =INDEX(Routes!$F$6:$F$9,$C18)/L18 -> 0.13 | N18: =2*L18*(1+SeaMargin)/(I18*24) -> 32.407407 | O18: =(I18/RefSpeed)^SpeedExp -> 1 | P18: =IF(H18>0,1,0) -> 1 | Q18: =N18/2*O18*(ConsLaden+IF(P18=1,ConsLaden,ConsBallast)) -> 875 | R18: =Q18*(1-M18) -> 761.25 | S18: =Q18*M18 -> 113.75 | T18: =1+P18 -> 2 | U18: =INDEX(Routes!$L$6:$L$9,$C18)*T18*F18 -> 10 | V18: =INDEX(Routes!$M$6:$M$9,$C18)*T18*F18 -> 7 | W18: =INDEX(Routes!$H$6:$H$9,$C18)*2 -> 0 | X18: =(U18+V18+W18)*ConsPort -> 102 | Y18: =R18*D18*VLSFO_Mult+(S18+X18)*D18*MGO_Mult -> 652340.34 | Z18: =(INDEX(Routes!$N$6:$N$9,$C18)+AN18+MIN(AC18*INDEX(Routes!$T$6:$T$9,$C18),INDEX(Routes!$V$6:$V$9,$C18))+INDEX(Routes!$O$6:$O$9,$C18)+AO18+MIN(AC18*INDEX(Routes!$U$6:$U$9,$C18),INDEX(Routes!$W$6:$W$9,$C18))+IF(P18=1,INDEX(Routes!$N$6:$N$9,$C18)+AN18+MIN(AD18*INDEX(Routes!$T$6:$T$9,$C18),INDEX(Routes!$V$6:$V$9,$C18))+INDEX(Routes!$O$6:$O$9,$C18)+AO18+MIN(AD18*INDEX(Routes!$U$6:$U$9,$C18),INDEX(Routes!$W$6:$W$9,$C18)),0))*J18 -> 258206.19 | AA18: =INDEX(Routes!$R$6:$R$9,$C18)+IF(P18=1,INDEX(Routes!$R$6:$R$9,$C18),INDEX(Routes!$S$6:$S$9,$C18)) -> 0 | AB18: =((R18*CO2_VLSFO+S18*CO2_MGO)*INDEX(Routes!$I$6:$I$9,$C18)+(U18*INDEX(Routes!$P$6:$P$9,$C18)+V18*INDEX(Routes!$Q$6:$Q$9,$C18))*ConsPort*CO2_MGO)*PhaseIn*K18*FX -> 123936.41 | AC18: =Capacity*G18 -> 30600 | AD18: =Capacity*H18 -> 27000 | AE18: =INDEX(Routes!$J$6:$J$9,$C18)*E18 -> 52 | AF18: =INDEX(Routes!$K$6:$K$9,$C18)*E18 -> 38 | AG18: =AC18*AE18+AD18*AF18 -> 2617200 | AH18: =AG18*Commission -> 65430 | AI18: =Y18+Z18+AA18+AB18+MiscVoy -> 1059482.9 | AJ18: =N18+U18+V18+W18 -> 49.407407 | AK18: =(AG18-AH18-AI18)/AJ18 -> 30203.711 | AL18: =AG18-AH18-AI18-Benchmark*AJ18 -> 602953.72 | AM18: =IF(AC18>0,((Benchmark*AJ18+AI18)/(1-Commission)-AD18*AF18)/AC18,0) -> 31.79039 | AN18: =LOA_ft*Port_Tariffs!$C$9*IF((INDEX(Routes!$L$6:$L$9,$C18)*INDEX(Routes!$X$6:$X$9,$C18)*F18)<=2,(INDEX(Routes!$L$6:$L$9,$C18)*INDEX(Routes!$X$6:$X$9,$C18)*F18),IF((INDEX(Routes!$L$6:$L$9,$C18)*INDEX(Routes!$X$6:$X$9,$C18)*F18)<=3,2+0.9*((INDEX(Routes!$L$6:$L$9,$C18)*INDEX(Routes!$X$6:$X$9,$C18)*F18)-2),IF((INDEX(Routes!$L$6:$L$9,$C18)*INDEX(Routes!$X$6:$X$9,$C18)*F18)<=4,2.9+0.75*((INDEX(Routes!$L$6:$L$9,$C18)*INDEX(Routes!$X$6:$X$9,$C18)*F18)-3),IF((INDEX(Routes!$L$6:$L$9,$C18)*INDEX(Routes!$X$6:$X$9,$C18)*F18)<=5,3.65+0.6*((INDEX(Routes!$L$6:$L$9,$C18)*INDEX(Routes!$X$6:$X$9,$C18)*F18)-4),4.25+0.5*((INDEX(Routes!$L$6:$L$9,$C18)*INDEX(Routes!$X$6:$X$9,$C18)*F18)-5))))) -> 19557.6 | AO18: =LOA_ft*Port_Tariffs!$C$9*IF((INDEX(Routes!$M$6:$M$9,$C18)*INDEX(Routes!$Y$6:$Y$9,$C18)*F18)<=2,(INDEX(Routes!$M$6:$M$9,$C18)*INDEX(Routes!$Y$6:$Y$9,$C18)*F18),IF((INDEX(Routes!$M$6:$M$9,$C18)*INDEX(Routes!$Y$6:$Y$9,$C18)*F18)<=3,2+0.9*((INDEX(Routes!$M$6:$M$9,$C18)*INDEX(Routes!$Y$6:$Y$9,$C18)*F18)-2),IF((INDEX(Routes!$M$6:$M$9,$C18)*INDEX(Routes!$Y$6:$Y$9,$C18)*F18)<=4,2.9+0.75*((INDEX(Routes!$M$6:$M$9,$C18)*INDEX(Routes!$Y$6:$Y$9,$C18)*F18)-3),IF((INDEX(Routes!$M$6:$M$9,$C18)*INDEX(Routes!$Y$6:$Y$9,$C18)*F18)<=5,3.65+0.6*((INDEX(Routes!$M$6:$M$9,$C18)*INDEX(Routes!$Y$6:$Y$9,$C18)*F18)-4),4.25+0.5*((INDEX(Routes!$M$6:$M$9,$C18)*INDEX(Routes!$Y$6:$Y$9,$C18)*F18)-5))))) -> 0
A19: Service speed — low | B19: tornado | C19: =Sw_Route -> 1 | D19: =Brent -> 82.01 | E19: =FreightMult -> 1 | F19: =PortMult -> 1 | G19: =UtilFH -> 0.85 | H19: =UtilBH -> 0.5 | I19: 12 | J19: =PortCostMult -> 1 | K19: =EUA -> 75 | L19: =INDEX(Routes!$E$6:$E$9,$C19) -> 5000 | M19: =INDEX(Routes!$F$6:$F$9,$C19)/L19 -> 0.13 | N19: =2*L19*(1+SeaMargin)/(I19*24) -> 36.458333 | O19: =(I19/RefSpeed)^SpeedExp -> 0.70233196 | P19: =IF(H19>0,1,0) -> 1 | Q19: =N19/2*O19*(ConsLaden+IF(P19=1,ConsLaden,ConsBallast)) -> 691.35802 | R19: =Q19*(1-M19) -> 601.48148 | S19: =Q19*M19 -> 89.876543 | T19: =1+P19 -> 2 | U19: =INDEX(Routes!$L$6:$L$9,$C19)*T19*F19 -> 10 | V19: =INDEX(Routes!$M$6:$M$9,$C19)*T19*F19 -> 7 | W19: =INDEX(Routes!$H$6:$H$9,$C19)*2 -> 0 | X19: =(U19+V19+W19)*ConsPort -> 102 | Y19: =R19*D19*VLSFO_Mult+(S19+X19)*D19*MGO_Mult -> 532458.94 | Z19: =(INDEX(Routes!$N$6:$N$9,$C19)+AN19+MIN(AC19*INDEX(Routes!$T$6:$T$9,$C19),INDEX(Routes!$V$6:$V$9,$C19))+INDEX(Routes!$O$6:$O$9,$C19)+AO19+MIN(AC19*INDEX(Routes!$U$6:$U$9,$C19),INDEX(Routes!$W$6:$W$9,$C19))+IF(P19=1,INDEX(Routes!$N$6:$N$9,$C19)+AN19+MIN(AD19*INDEX(Routes!$T$6:$T$9,$C19),INDEX(Routes!$V$6:$V$9,$C19))+INDEX(Routes!$O$6:$O$9,$C19)+AO19+MIN(AD19*INDEX(Routes!$U$6:$U$9,$C19),INDEX(Routes!$W$6:$W$9,$C19)),0))*J19 -> 252304.21 | AA19: =INDEX(Routes!$R$6:$R$9,$C19)+IF(P19=1,INDEX(Routes!$R$6:$R$9,$C19),INDEX(Routes!$S$6:$S$9,$C19)) -> 0 | AB19: =((R19*CO2_VLSFO+S19*CO2_MGO)*INDEX(Routes!$I$6:$I$9,$C19)+(U19*INDEX(Routes!$P$6:$P$9,$C19)+V19*INDEX(Routes!$Q$6:$Q$9,$C19))*ConsPort*CO2_MGO)*PhaseIn*K19*FX -> 100256.54 | AC19: =Capacity*G19 -> 30600 | AD19: =Capacity*H19 -> 18000 | AE19: =INDEX(Routes!$J$6:$J$9,$C19)*E19 -> 52 | AF19: =INDEX(Routes!$K$6:$K$9,$C19)*E19 -> 38 | AG19: =AC19*AE19+AD19*AF19 -> 2275200 | AH19: =AG19*Commission -> 56880 | AI19: =Y19+Z19+AA19+AB19+MiscVoy -> 910019.68 | AJ19: =N19+U19+V19+W19 -> 53.458333 | AK19: =(AG19-AH19-AI19)/AJ19 -> 24473.272 | AL19: =AG19-AH19-AI19-Benchmark*AJ19 -> 346050.32 | AM19: =IF(AC19>0,((Benchmark*AJ19+AI19)/(1-Commission)-AD19*AF19)/AC19,0) -> 40.401196 | AN19: =LOA_ft*Port_Tariffs!$C$9*IF((INDEX(Routes!$L$6:$L$9,$C19)*INDEX(Routes!$X$6:$X$9,$C19)*F19)<=2,(INDEX(Routes!$L$6:$L$9,$C19)*INDEX(Routes!$X$6:$X$9,$C19)*F19),IF((INDEX(Routes!$L$6:$L$9,$C19)*INDEX(Routes!$X$6:$X$9,$C19)*F19)<=3,2+0.9*((INDEX(Routes!$L$6:$L$9,$C19)*INDEX(Routes!$X$6:$X$9,$C19)*F19)-2),IF((INDEX(Routes!$L$6:$L$9,$C19)*INDEX(Routes!$X$6:$X$9,$C19)*F19)<=4,2.9+0.75*((INDEX(Routes!$L$6:$L$9,$C19)*INDEX(Routes!$X$6:$X$9,$C19)*F19)-3),IF((INDEX(Routes!$L$6:$L$9,$C19)*INDEX(Routes!$X$6:$X$9,$C19)*F19)<=5,3.65+0.6*((INDEX(Routes!$L$6:$L$9,$C19)*INDEX(Routes!$X$6:$X$9,$C19)*F19)-4),4.25+0.5*((INDEX(Routes!$L$6:$L$9,$C19)*INDEX(Routes!$X$6:$X$9,$C19)*F19)-5))))) -> 19557.6 | AO19: =LOA_ft*Port_Tariffs!$C$9*IF((INDEX(Routes!$M$6:$M$9,$C19)*INDEX(Routes!$Y$6:$Y$9,$C19)*F19)<=2,(INDEX(Routes!$M$6:$M$9,$C19)*INDEX(Routes!$Y$6:$Y$9,$C19)*F19),IF((INDEX(Routes!$M$6:$M$9,$C19)*INDEX(Routes!$Y$6:$Y$9,$C19)*F19)<=3,2+0.9*((INDEX(Routes!$M$6:$M$9,$C19)*INDEX(Routes!$Y$6:$Y$9,$C19)*F19)-2),IF((INDEX(Routes!$M$6:$M$9,$C19)*INDEX(Routes!$Y$6:$Y$9,$C19)*F19)<=4,2.9+0.75*((INDEX(Routes!$M$6:$M$9,$C19)*INDEX(Routes!$Y$6:$Y$9,$C19)*F19)-3),IF((INDEX(Routes!$M$6:$M$9,$C19)*INDEX(Routes!$Y$6:$Y$9,$C19)*F19)<=5,3.65+0.6*((INDEX(Routes!$M$6:$M$9,$C19)*INDEX(Routes!$Y$6:$Y$9,$C19)*F19)-4),4.25+0.5*((INDEX(Routes!$M$6:$M$9,$C19)*INDEX(Routes!$Y$6:$Y$9,$C19)*F19)-5))))) -> 0
A20: Service speed — high | B20: tornado | C20: =Sw_Route -> 1 | D20: =Brent -> 82.01 | E20: =FreightMult -> 1 | F20: =PortMult -> 1 | G20: =UtilFH -> 0.85 | H20: =UtilBH -> 0.5 | I20: 14.5 | J20: =PortCostMult -> 1 | K20: =EUA -> 75 | L20: =INDEX(Routes!$E$6:$E$9,$C20) -> 5000 | M20: =INDEX(Routes!$F$6:$F$9,$C20)/L20 -> 0.13 | N20: =2*L20*(1+SeaMargin)/(I20*24) -> 30.172414 | O20: =(I20/RefSpeed)^SpeedExp -> 1.2390896 | P20: =IF(H20>0,1,0) -> 1 | Q20: =N20/2*O20*(ConsLaden+IF(P20=1,ConsLaden,ConsBallast)) -> 1009.4307 | R20: =Q20*(1-M20) -> 878.20473 | S20: =Q20*M20 -> 131.22599 | T20: =1+P20 -> 2 | U20: =INDEX(Routes!$L$6:$L$9,$C20)*T20*F20 -> 10 | V20: =INDEX(Routes!$M$6:$M$9,$C20)*T20*F20 -> 7 | W20: =INDEX(Routes!$H$6:$H$9,$C20)*2 -> 0 | X20: =(U20+V20+W20)*ConsPort -> 102 | Y20: =R20*D20*VLSFO_Mult+(S20+X20)*D20*MGO_Mult -> 740096.67 | Z20: =(INDEX(Routes!$N$6:$N$9,$C20)+AN20+MIN(AC20*INDEX(Routes!$T$6:$T$9,$C20),INDEX(Routes!$V$6:$V$9,$C20))+INDEX(Routes!$O$6:$O$9,$C20)+AO20+MIN(AC20*INDEX(Routes!$U$6:$U$9,$C20),INDEX(Routes!$W$6:$W$9,$C20))+IF(P20=1,INDEX(Routes!$N$6:$N$9,$C20)+AN20+MIN(AD20*INDEX(Routes!$T$6:$T$9,$C20),INDEX(Routes!$V$6:$V$9,$C20))+INDEX(Routes!$O$6:$O$9,$C20)+AO20+MIN(AD20*INDEX(Routes!$U$6:$U$9,$C20),INDEX(Routes!$W$6:$W$9,$C20)),0))*J20 -> 252304.21 | AA20: =INDEX(Routes!$R$6:$R$9,$C20)+IF(P20=1,INDEX(Routes!$R$6:$R$9,$C20),INDEX(Routes!$S$6:$S$9,$C20)) -> 0 | AB20: =((R20*CO2_VLSFO+S20*CO2_MGO)*INDEX(Routes!$I$6:$I$9,$C20)+(U20*INDEX(Routes!$P$6:$P$9,$C20)+V20*INDEX(Routes!$Q$6:$Q$9,$C20))*ConsPort*CO2_MGO)*PhaseIn*K20*FX -> 141270.69 | AC20: =Capacity*G20 -> 30600 | AD20: =Capacity*H20 -> 18000 | AE20: =INDEX(Routes!$J$6:$J$9,$C20)*E20 -> 52 | AF20: =INDEX(Routes!$K$6:$K$9,$C20)*E20 -> 38 | AG20: =AC20*AE20+AD20*AF20 -> 2275200 | AH20: =AG20*Commission -> 56880 | AI20: =Y20+Z20+AA20+AB20+MiscVoy -> 1158671.6 | AJ20: =N20+U20+V20+W20 -> 47.172414 | AK20: =(AG20-AH20-AI20)/AJ20 -> 22463.307 | AL20: =AG20-AH20-AI20-Benchmark*AJ20 -> 210544.98 | AM20: =IF(AC20>0,((Benchmark*AJ20+AI20)/(1-Commission)-AD20*AF20)/AC20,0) -> 44.943021 | AN20: =LOA_ft*Port_Tariffs!$C$9*IF((INDEX(Routes!$L$6:$L$9,$C20)*INDEX(Routes!$X$6:$X$9,$C20)*F20)<=2,(INDEX(Routes!$L$6:$L$9,$C20)*INDEX(Routes!$X$6:$X$9,$C20)*F20),IF((INDEX(Routes!$L$6:$L$9,$C20)*INDEX(Routes!$X$6:$X$9,$C20)*F20)<=3,2+0.9*((INDEX(Routes!$L$6:$L$9,$C20)*INDEX(Routes!$X$6:$X$9,$C20)*F20)-2),IF((INDEX(Routes!$L$6:$L$9,$C20)*INDEX(Routes!$X$6:$X$9,$C20)*F20)<=4,2.9+0.75*((INDEX(Routes!$L$6:$L$9,$C20)*INDEX(Routes!$X$6:$X$9,$C20)*F20)-3),IF((INDEX(Routes!$L$6:$L$9,$C20)*INDEX(Routes!$X$6:$X$9,$C20)*F20)<=5,3.65+0.6*((INDEX(Routes!$L$6:$L$9,$C20)*INDEX(Routes!$X$6:$X$9,$C20)*F20)-4),4.25+0.5*((INDEX(Routes!$L$6:$L$9,$C20)*INDEX(Routes!$X$6:$X$9,$C20)*F20)-5))))) -> 19557.6 | AO20: =LOA_ft*Port_Tariffs!$C$9*IF((INDEX(Routes!$M$6:$M$9,$C20)*INDEX(Routes!$Y$6:$Y$9,$C20)*F20)<=2,(INDEX(Routes!$M$6:$M$9,$C20)*INDEX(Routes!$Y$6:$Y$9,$C20)*F20),IF((INDEX(Routes!$M$6:$M$9,$C20)*INDEX(Routes!$Y$6:$Y$9,$C20)*F20)<=3,2+0.9*((INDEX(Routes!$M$6:$M$9,$C20)*INDEX(Routes!$Y$6:$Y$9,$C20)*F20)-2),IF((INDEX(Routes!$M$6:$M$9,$C20)*INDEX(Routes!$Y$6:$Y$9,$C20)*F20)<=4,2.9+0.75*((INDEX(Routes!$M$6:$M$9,$C20)*INDEX(Routes!$Y$6:$Y$9,$C20)*F20)-3),IF((INDEX(Routes!$M$6:$M$9,$C20)*INDEX(Routes!$Y$6:$Y$9,$C20)*F20)<=5,3.65+0.6*((INDEX(Routes!$M$6:$M$9,$C20)*INDEX(Routes!$Y$6:$Y$9,$C20)*F20)-4),4.25+0.5*((INDEX(Routes!$M$6:$M$9,$C20)*INDEX(Routes!$Y$6:$Y$9,$C20)*F20)-5))))) -> 0
A21: Port disbursements — low | B21: tornado | C21: =Sw_Route -> 1 | D21: =Brent -> 82.01 | E21: =FreightMult -> 1 | F21: =PortMult -> 1 | G21: =UtilFH -> 0.85 | H21: =UtilBH -> 0.5 | I21: =Speed -> 13.5 | J21: 0.75 | K21: =EUA -> 75 | L21: =INDEX(Routes!$E$6:$E$9,$C21) -> 5000 | M21: =INDEX(Routes!$F$6:$F$9,$C21)/L21 -> 0.13 | N21: =2*L21*(1+SeaMargin)/(I21*24) -> 32.407407 | O21: =(I21/RefSpeed)^SpeedExp -> 1 | P21: =IF(H21>0,1,0) -> 1 | Q21: =N21/2*O21*(ConsLaden+IF(P21=1,ConsLaden,ConsBallast)) -> 875 | R21: =Q21*(1-M21) -> 761.25 | S21: =Q21*M21 -> 113.75 | T21: =1+P21 -> 2 | U21: =INDEX(Routes!$L$6:$L$9,$C21)*T21*F21 -> 10 | V21: =INDEX(Routes!$M$6:$M$9,$C21)*T21*F21 -> 7 | W21: =INDEX(Routes!$H$6:$H$9,$C21)*2 -> 0 | X21: =(U21+V21+W21)*ConsPort -> 102 | Y21: =R21*D21*VLSFO_Mult+(S21+X21)*D21*MGO_Mult -> 652340.34 | Z21: =(INDEX(Routes!$N$6:$N$9,$C21)+AN21+MIN(AC21*INDEX(Routes!$T$6:$T$9,$C21),INDEX(Routes!$V$6:$V$9,$C21))+INDEX(Routes!$O$6:$O$9,$C21)+AO21+MIN(AC21*INDEX(Routes!$U$6:$U$9,$C21),INDEX(Routes!$W$6:$W$9,$C21))+IF(P21=1,INDEX(Routes!$N$6:$N$9,$C21)+AN21+MIN(AD21*INDEX(Routes!$T$6:$T$9,$C21),INDEX(Routes!$V$6:$V$9,$C21))+INDEX(Routes!$O$6:$O$9,$C21)+AO21+MIN(AD21*INDEX(Routes!$U$6:$U$9,$C21),INDEX(Routes!$W$6:$W$9,$C21)),0))*J21 -> 189228.16 | AA21: =INDEX(Routes!$R$6:$R$9,$C21)+IF(P21=1,INDEX(Routes!$R$6:$R$9,$C21),INDEX(Routes!$S$6:$S$9,$C21)) -> 0 | AB21: =((R21*CO2_VLSFO+S21*CO2_MGO)*INDEX(Routes!$I$6:$I$9,$C21)+(U21*INDEX(Routes!$P$6:$P$9,$C21)+V21*INDEX(Routes!$Q$6:$Q$9,$C21))*ConsPort*CO2_MGO)*PhaseIn*K21*FX -> 123936.41 | AC21: =Capacity*G21 -> 30600 | AD21: =Capacity*H21 -> 18000 | AE21: =INDEX(Routes!$J$6:$J$9,$C21)*E21 -> 52 | AF21: =INDEX(Routes!$K$6:$K$9,$C21)*E21 -> 38 | AG21: =AC21*AE21+AD21*AF21 -> 2275200 | AH21: =AG21*Commission -> 56880 | AI21: =Y21+Z21+AA21+AB21+MiscVoy -> 990504.91 | AJ21: =N21+U21+V21+W21 -> 49.407407 | AK21: =(AG21-AH21-AI21)/AJ21 -> 24850.83 | AL21: =AG21-AH21-AI21-Benchmark*AJ21 -> 338481.76 | AM21: =IF(AC21>0,((Benchmark*AJ21+AI21)/(1-Commission)-AD21*AF21)/AC21,0) -> 40.654877 | AN21: =LOA_ft*Port_Tariffs!$C$9*IF((INDEX(Routes!$L$6:$L$9,$C21)*INDEX(Routes!$X$6:$X$9,$C21)*F21)<=2,(INDEX(Routes!$L$6:$L$9,$C21)*INDEX(Routes!$X$6:$X$9,$C21)*F21),IF((INDEX(Routes!$L$6:$L$9,$C21)*INDEX(Routes!$X$6:$X$9,$C21)*F21)<=3,2+0.9*((INDEX(Routes!$L$6:$L$9,$C21)*INDEX(Routes!$X$6:$X$9,$C21)*F21)-2),IF((INDEX(Routes!$L$6:$L$9,$C21)*INDEX(Routes!$X$6:$X$9,$C21)*F21)<=4,2.9+0.75*((INDEX(Routes!$L$6:$L$9,$C21)*INDEX(Routes!$X$6:$X$9,$C21)*F21)-3),IF((INDEX(Routes!$L$6:$L$9,$C21)*INDEX(Routes!$X$6:$X$9,$C21)*F21)<=5,3.65+0.6*((INDEX(Routes!$L$6:$L$9,$C21)*INDEX(Routes!$X$6:$X$9,$C21)*F21)-4),4.25+0.5*((INDEX(Routes!$L$6:$L$9,$C21)*INDEX(Routes!$X$6:$X$9,$C21)*F21)-5))))) -> 19557.6 | AO21: =LOA_ft*Port_Tariffs!$C$9*IF((INDEX(Routes!$M$6:$M$9,$C21)*INDEX(Routes!$Y$6:$Y$9,$C21)*F21)<=2,(INDEX(Routes!$M$6:$M$9,$C21)*INDEX(Routes!$Y$6:$Y$9,$C21)*F21),IF((INDEX(Routes!$M$6:$M$9,$C21)*INDEX(Routes!$Y$6:$Y$9,$C21)*F21)<=3,2+0.9*((INDEX(Routes!$M$6:$M$9,$C21)*INDEX(Routes!$Y$6:$Y$9,$C21)*F21)-2),IF((INDEX(Routes!$M$6:$M$9,$C21)*INDEX(Routes!$Y$6:$Y$9,$C21)*F21)<=4,2.9+0.75*((INDEX(Routes!$M$6:$M$9,$C21)*INDEX(Routes!$Y$6:$Y$9,$C21)*F21)-3),IF((INDEX(Routes!$M$6:$M$9,$C21)*INDEX(Routes!$Y$6:$Y$9,$C21)*F21)<=5,3.65+0.6*((INDEX(Routes!$M$6:$M$9,$C21)*INDEX(Routes!$Y$6:$Y$9,$C21)*F21)-4),4.25+0.5*((INDEX(Routes!$M$6:$M$9,$C21)*INDEX(Routes!$Y$6:$Y$9,$C21)*F21)-5))))) -> 0
A22: Port disbursements — high | B22: tornado | C22: =Sw_Route -> 1 | D22: =Brent -> 82.01 | E22: =FreightMult -> 1 | F22: =PortMult -> 1 | G22: =UtilFH -> 0.85 | H22: =UtilBH -> 0.5 | I22: =Speed -> 13.5 | J22: 1.25 | K22: =EUA -> 75 | L22: =INDEX(Routes!$E$6:$E$9,$C22) -> 5000 | M22: =INDEX(Routes!$F$6:$F$9,$C22)/L22 -> 0.13 | N22: =2*L22*(1+SeaMargin)/(I22*24) -> 32.407407 | O22: =(I22/RefSpeed)^SpeedExp -> 1 | P22: =IF(H22>0,1,0) -> 1 | Q22: =N22/2*O22*(ConsLaden+IF(P22=1,ConsLaden,ConsBallast)) -> 875 | R22: =Q22*(1-M22) -> 761.25 | S22: =Q22*M22 -> 113.75 | T22: =1+P22 -> 2 | U22: =INDEX(Routes!$L$6:$L$9,$C22)*T22*F22 -> 10 | V22: =INDEX(Routes!$M$6:$M$9,$C22)*T22*F22 -> 7 | W22: =INDEX(Routes!$H$6:$H$9,$C22)*2 -> 0 | X22: =(U22+V22+W22)*ConsPort -> 102 | Y22: =R22*D22*VLSFO_Mult+(S22+X22)*D22*MGO_Mult -> 652340.34 | Z22: =(INDEX(Routes!$N$6:$N$9,$C22)+AN22+MIN(AC22*INDEX(Routes!$T$6:$T$9,$C22),INDEX(Routes!$V$6:$V$9,$C22))+INDEX(Routes!$O$6:$O$9,$C22)+AO22+MIN(AC22*INDEX(Routes!$U$6:$U$9,$C22),INDEX(Routes!$W$6:$W$9,$C22))+IF(P22=1,INDEX(Routes!$N$6:$N$9,$C22)+AN22+MIN(AD22*INDEX(Routes!$T$6:$T$9,$C22),INDEX(Routes!$V$6:$V$9,$C22))+INDEX(Routes!$O$6:$O$9,$C22)+AO22+MIN(AD22*INDEX(Routes!$U$6:$U$9,$C22),INDEX(Routes!$W$6:$W$9,$C22)),0))*J22 -> 315380.26 | AA22: =INDEX(Routes!$R$6:$R$9,$C22)+IF(P22=1,INDEX(Routes!$R$6:$R$9,$C22),INDEX(Routes!$S$6:$S$9,$C22)) -> 0 | AB22: =((R22*CO2_VLSFO+S22*CO2_MGO)*INDEX(Routes!$I$6:$I$9,$C22)+(U22*INDEX(Routes!$P$6:$P$9,$C22)+V22*INDEX(Routes!$Q$6:$Q$9,$C22))*ConsPort*CO2_MGO)*PhaseIn*K22*FX -> 123936.41 | AC22: =Capacity*G22 -> 30600 | AD22: =Capacity*H22 -> 18000 | AE22: =INDEX(Routes!$J$6:$J$9,$C22)*E22 -> 52 | AF22: =INDEX(Routes!$K$6:$K$9,$C22)*E22 -> 38 | AG22: =AC22*AE22+AD22*AF22 -> 2275200 | AH22: =AG22*Commission -> 56880 | AI22: =Y22+Z22+AA22+AB22+MiscVoy -> 1116657 | AJ22: =N22+U22+V22+W22 -> 49.407407 | AK22: =(AG22-AH22-AI22)/AJ22 -> 22297.527 | AL22: =AG22-AH22-AI22-Benchmark*AJ22 -> 212329.65 | AM22: =IF(AC22>0,((Benchmark*AJ22+AI22)/(1-Commission)-AD22*AF22)/AC22,0) -> 44.883203 | AN22: =LOA_ft*Port_Tariffs!$C$9*IF((INDEX(Routes!$L$6:$L$9,$C22)*INDEX(Routes!$X$6:$X$9,$C22)*F22)<=2,(INDEX(Routes!$L$6:$L$9,$C22)*INDEX(Routes!$X$6:$X$9,$C22)*F22),IF((INDEX(Routes!$L$6:$L$9,$C22)*INDEX(Routes!$X$6:$X$9,$C22)*F22)<=3,2+0.9*((INDEX(Routes!$L$6:$L$9,$C22)*INDEX(Routes!$X$6:$X$9,$C22)*F22)-2),IF((INDEX(Routes!$L$6:$L$9,$C22)*INDEX(Routes!$X$6:$X$9,$C22)*F22)<=4,2.9+0.75*((INDEX(Routes!$L$6:$L$9,$C22)*INDEX(Routes!$X$6:$X$9,$C22)*F22)-3),IF((INDEX(Routes!$L$6:$L$9,$C22)*INDEX(Routes!$X$6:$X$9,$C22)*F22)<=5,3.65+0.6*((INDEX(Routes!$L$6:$L$9,$C22)*INDEX(Routes!$X$6:$X$9,$C22)*F22)-4),4.25+0.5*((INDEX(Routes!$L$6:$L$9,$C22)*INDEX(Routes!$X$6:$X$9,$C22)*F22)-5))))) -> 19557.6 | AO22: =LOA_ft*Port_Tariffs!$C$9*IF((INDEX(Routes!$M$6:$M$9,$C22)*INDEX(Routes!$Y$6:$Y$9,$C22)*F22)<=2,(INDEX(Routes!$M$6:$M$9,$C22)*INDEX(Routes!$Y$6:$Y$9,$C22)*F22),IF((INDEX(Routes!$M$6:$M$9,$C22)*INDEX(Routes!$Y$6:$Y$9,$C22)*F22)<=3,2+0.9*((INDEX(Routes!$M$6:$M$9,$C22)*INDEX(Routes!$Y$6:$Y$9,$C22)*F22)-2),IF((INDEX(Routes!$M$6:$M$9,$C22)*INDEX(Routes!$Y$6:$Y$9,$C22)*F22)<=4,2.9+0.75*((INDEX(Routes!$M$6:$M$9,$C22)*INDEX(Routes!$Y$6:$Y$9,$C22)*F22)-3),IF((INDEX(Routes!$M$6:$M$9,$C22)*INDEX(Routes!$Y$6:$Y$9,$C22)*F22)<=5,3.65+0.6*((INDEX(Routes!$M$6:$M$9,$C22)*INDEX(Routes!$Y$6:$Y$9,$C22)*F22)-4),4.25+0.5*((INDEX(Routes!$M$6:$M$9,$C22)*INDEX(Routes!$Y$6:$Y$9,$C22)*F22)-5))))) -> 0
A23: EU carbon price (EUA) — low | B23: tornado | C23: =Sw_Route -> 1 | D23: =Brent -> 82.01 | E23: =FreightMult -> 1 | F23: =PortMult -> 1 | G23: =UtilFH -> 0.85 | H23: =UtilBH -> 0.5 | I23: =Speed -> 13.5 | J23: =PortCostMult -> 1 | K23: 50 | L23: =INDEX(Routes!$E$6:$E$9,$C23) -> 5000 | M23: =INDEX(Routes!$F$6:$F$9,$C23)/L23 -> 0.13 | N23: =2*L23*(1+SeaMargin)/(I23*24) -> 32.407407 | O23: =(I23/RefSpeed)^SpeedExp -> 1 | P23: =IF(H23>0,1,0) -> 1 | Q23: =N23/2*O23*(ConsLaden+IF(P23=1,ConsLaden,ConsBallast)) -> 875 | R23: =Q23*(1-M23) -> 761.25 | S23: =Q23*M23 -> 113.75 | T23: =1+P23 -> 2 | U23: =INDEX(Routes!$L$6:$L$9,$C23)*T23*F23 -> 10 | V23: =INDEX(Routes!$M$6:$M$9,$C23)*T23*F23 -> 7 | W23: =INDEX(Routes!$H$6:$H$9,$C23)*2 -> 0 | X23: =(U23+V23+W23)*ConsPort -> 102 | Y23: =R23*D23*VLSFO_Mult+(S23+X23)*D23*MGO_Mult -> 652340.34 | Z23: =(INDEX(Routes!$N$6:$N$9,$C23)+AN23+MIN(AC23*INDEX(Routes!$T$6:$T$9,$C23),INDEX(Routes!$V$6:$V$9,$C23))+INDEX(Routes!$O$6:$O$9,$C23)+AO23+MIN(AC23*INDEX(Routes!$U$6:$U$9,$C23),INDEX(Routes!$W$6:$W$9,$C23))+IF(P23=1,INDEX(Routes!$N$6:$N$9,$C23)+AN23+MIN(AD23*INDEX(Routes!$T$6:$T$9,$C23),INDEX(Routes!$V$6:$V$9,$C23))+INDEX(Routes!$O$6:$O$9,$C23)+AO23+MIN(AD23*INDEX(Routes!$U$6:$U$9,$C23),INDEX(Routes!$W$6:$W$9,$C23)),0))*J23 -> 252304.21 | AA23: =INDEX(Routes!$R$6:$R$9,$C23)+IF(P23=1,INDEX(Routes!$R$6:$R$9,$C23),INDEX(Routes!$S$6:$S$9,$C23)) -> 0 | AB23: =((R23*CO2_VLSFO+S23*CO2_MGO)*INDEX(Routes!$I$6:$I$9,$C23)+(U23*INDEX(Routes!$P$6:$P$9,$C23)+V23*INDEX(Routes!$Q$6:$Q$9,$C23))*ConsPort*CO2_MGO)*PhaseIn*K23*FX -> 82624.273 | AC23: =Capacity*G23 -> 30600 | AD23: =Capacity*H23 -> 18000 | AE23: =INDEX(Routes!$J$6:$J$9,$C23)*E23 -> 52 | AF23: =INDEX(Routes!$K$6:$K$9,$C23)*E23 -> 38 | AG23: =AC23*AE23+AD23*AF23 -> 2275200 | AH23: =AG23*Commission -> 56880 | AI23: =Y23+Z23+AA23+AB23+MiscVoy -> 1012268.8 | AJ23: =N23+U23+V23+W23 -> 49.407407 | AK23: =(AG23-AH23-AI23)/AJ23 -> 24410.331 | AL23: =AG23-AH23-AI23-Benchmark*AJ23 -> 316717.84 | AM23: =IF(AC23>0,((Benchmark*AJ23+AI23)/(1-Commission)-AD23*AF23)/AC23,0) -> 41.384353 | AN23: =LOA_ft*Port_Tariffs!$C$9*IF((INDEX(Routes!$L$6:$L$9,$C23)*INDEX(Routes!$X$6:$X$9,$C23)*F23)<=2,(INDEX(Routes!$L$6:$L$9,$C23)*INDEX(Routes!$X$6:$X$9,$C23)*F23),IF((INDEX(Routes!$L$6:$L$9,$C23)*INDEX(Routes!$X$6:$X$9,$C23)*F23)<=3,2+0.9*((INDEX(Routes!$L$6:$L$9,$C23)*INDEX(Routes!$X$6:$X$9,$C23)*F23)-2),IF((INDEX(Routes!$L$6:$L$9,$C23)*INDEX(Routes!$X$6:$X$9,$C23)*F23)<=4,2.9+0.75*((INDEX(Routes!$L$6:$L$9,$C23)*INDEX(Routes!$X$6:$X$9,$C23)*F23)-3),IF((INDEX(Routes!$L$6:$L$9,$C23)*INDEX(Routes!$X$6:$X$9,$C23)*F23)<=5,3.65+0.6*((INDEX(Routes!$L$6:$L$9,$C23)*INDEX(Routes!$X$6:$X$9,$C23)*F23)-4),4.25+0.5*((INDEX(Routes!$L$6:$L$9,$C23)*INDEX(Routes!$X$6:$X$9,$C23)*F23)-5))))) -> 19557.6 | AO23: =LOA_ft*Port_Tariffs!$C$9*IF((INDEX(Routes!$M$6:$M$9,$C23)*INDEX(Routes!$Y$6:$Y$9,$C23)*F23)<=2,(INDEX(Routes!$M$6:$M$9,$C23)*INDEX(Routes!$Y$6:$Y$9,$C23)*F23),IF((INDEX(Routes!$M$6:$M$9,$C23)*INDEX(Routes!$Y$6:$Y$9,$C23)*F23)<=3,2+0.9*((INDEX(Routes!$M$6:$M$9,$C23)*INDEX(Routes!$Y$6:$Y$9,$C23)*F23)-2),IF((INDEX(Routes!$M$6:$M$9,$C23)*INDEX(Routes!$Y$6:$Y$9,$C23)*F23)<=4,2.9+0.75*((INDEX(Routes!$M$6:$M$9,$C23)*INDEX(Routes!$Y$6:$Y$9,$C23)*F23)-3),IF((INDEX(Routes!$M$6:$M$9,$C23)*INDEX(Routes!$Y$6:$Y$9,$C23)*F23)<=5,3.65+0.6*((INDEX(Routes!$M$6:$M$9,$C23)*INDEX(Routes!$Y$6:$Y$9,$C23)*F23)-4),4.25+0.5*((INDEX(Routes!$M$6:$M$9,$C23)*INDEX(Routes!$Y$6:$Y$9,$C23)*F23)-5))))) -> 0
A24: EU carbon price (EUA) — high | B24: tornado | C24: =Sw_Route -> 1 | D24: =Brent -> 82.01 | E24: =FreightMult -> 1 | F24: =PortMult -> 1 | G24: =UtilFH -> 0.85 | H24: =UtilBH -> 0.5 | I24: =Speed -> 13.5 | J24: =PortCostMult -> 1 | K24: 110 | L24: =INDEX(Routes!$E$6:$E$9,$C24) -> 5000 | M24: =INDEX(Routes!$F$6:$F$9,$C24)/L24 -> 0.13 | N24: =2*L24*(1+SeaMargin)/(I24*24) -> 32.407407 | O24: =(I24/RefSpeed)^SpeedExp -> 1 | P24: =IF(H24>0,1,0) -> 1 | Q24: =N24/2*O24*(ConsLaden+IF(P24=1,ConsLaden,ConsBallast)) -> 875 | R24: =Q24*(1-M24) -> 761.25 | S24: =Q24*M24 -> 113.75 | T24: =1+P24 -> 2 | U24: =INDEX(Routes!$L$6:$L$9,$C24)*T24*F24 -> 10 | V24: =INDEX(Routes!$M$6:$M$9,$C24)*T24*F24 -> 7 | W24: =INDEX(Routes!$H$6:$H$9,$C24)*2 -> 0 | X24: =(U24+V24+W24)*ConsPort -> 102 | Y24: =R24*D24*VLSFO_Mult+(S24+X24)*D24*MGO_Mult -> 652340.34 | Z24: =(INDEX(Routes!$N$6:$N$9,$C24)+AN24+MIN(AC24*INDEX(Routes!$T$6:$T$9,$C24),INDEX(Routes!$V$6:$V$9,$C24))+INDEX(Routes!$O$6:$O$9,$C24)+AO24+MIN(AC24*INDEX(Routes!$U$6:$U$9,$C24),INDEX(Routes!$W$6:$W$9,$C24))+IF(P24=1,INDEX(Routes!$N$6:$N$9,$C24)+AN24+MIN(AD24*INDEX(Routes!$T$6:$T$9,$C24),INDEX(Routes!$V$6:$V$9,$C24))+INDEX(Routes!$O$6:$O$9,$C24)+AO24+MIN(AD24*INDEX(Routes!$U$6:$U$9,$C24),INDEX(Routes!$W$6:$W$9,$C24)),0))*J24 -> 252304.21 | AA24: =INDEX(Routes!$R$6:$R$9,$C24)+IF(P24=1,INDEX(Routes!$R$6:$R$9,$C24),INDEX(Routes!$S$6:$S$9,$C24)) -> 0 | AB24: =((R24*CO2_VLSFO+S24*CO2_MGO)*INDEX(Routes!$I$6:$I$9,$C24)+(U24*INDEX(Routes!$P$6:$P$9,$C24)+V24*INDEX(Routes!$Q$6:$Q$9,$C24))*ConsPort*CO2_MGO)*PhaseIn*K24*FX -> 181773.4 | AC24: =Capacity*G24 -> 30600 | AD24: =Capacity*H24 -> 18000 | AE24: =INDEX(Routes!$J$6:$J$9,$C24)*E24 -> 52 | AF24: =INDEX(Routes!$K$6:$K$9,$C24)*E24 -> 38 | AG24: =AC24*AE24+AD24*AF24 -> 2275200 | AH24: =AG24*Commission -> 56880 | AI24: =Y24+Z24+AA24+AB24+MiscVoy -> 1111418 | AJ24: =N24+U24+V24+W24 -> 49.407407 | AK24: =(AG24-AH24-AI24)/AJ24 -> 22403.565 | AL24: =AG24-AH24-AI24-Benchmark*AJ24 -> 217568.71 | AM24: =IF(AC24>0,((Benchmark*AJ24+AI24)/(1-Commission)-AD24*AF24)/AC24,0) -> 44.707601 | AN24: =LOA_ft*Port_Tariffs!$C$9*IF((INDEX(Routes!$L$6:$L$9,$C24)*INDEX(Routes!$X$6:$X$9,$C24)*F24)<=2,(INDEX(Routes!$L$6:$L$9,$C24)*INDEX(Routes!$X$6:$X$9,$C24)*F24),IF((INDEX(Routes!$L$6:$L$9,$C24)*INDEX(Routes!$X$6:$X$9,$C24)*F24)<=3,2+0.9*((INDEX(Routes!$L$6:$L$9,$C24)*INDEX(Routes!$X$6:$X$9,$C24)*F24)-2),IF((INDEX(Routes!$L$6:$L$9,$C24)*INDEX(Routes!$X$6:$X$9,$C24)*F24)<=4,2.9+0.75*((INDEX(Routes!$L$6:$L$9,$C24)*INDEX(Routes!$X$6:$X$9,$C24)*F24)-3),IF((INDEX(Routes!$L$6:$L$9,$C24)*INDEX(Routes!$X$6:$X$9,$C24)*F24)<=5,3.65+0.6*((INDEX(Routes!$L$6:$L$9,$C24)*INDEX(Routes!$X$6:$X$9,$C24)*F24)-4),4.25+0.5*((INDEX(Routes!$L$6:$L$9,$C24)*INDEX(Routes!$X$6:$X$9,$C24)*F24)-5))))) -> 19557.6 | AO24: =LOA_ft*Port_Tariffs!$C$9*IF((INDEX(Routes!$M$6:$M$9,$C24)*INDEX(Routes!$Y$6:$Y$9,$C24)*F24)<=2,(INDEX(Routes!$M$6:$M$9,$C24)*INDEX(Routes!$Y$6:$Y$9,$C24)*F24),IF((INDEX(Routes!$M$6:$M$9,$C24)*INDEX(Routes!$Y$6:$Y$9,$C24)*F24)<=3,2+0.9*((INDEX(Routes!$M$6:$M$9,$C24)*INDEX(Routes!$Y$6:$Y$9,$C24)*F24)-2),IF((INDEX(Routes!$M$6:$M$9,$C24)*INDEX(Routes!$Y$6:$Y$9,$C24)*F24)<=4,2.9+0.75*((INDEX(Routes!$M$6:$M$9,$C24)*INDEX(Routes!$Y$6:$Y$9,$C24)*F24)-3),IF((INDEX(Routes!$M$6:$M$9,$C24)*INDEX(Routes!$Y$6:$Y$9,$C24)*F24)<=5,3.65+0.6*((INDEX(Routes!$M$6:$M$9,$C24)*INDEX(Routes!$Y$6:$Y$9,$C24)*F24)-4),4.25+0.5*((INDEX(Routes!$M$6:$M$9,$C24)*INDEX(Routes!$Y$6:$Y$9,$C24)*F24)-5))))) -> 0
A26: ELASTICITY CASES (+10% on one lever)
A27: Freight rate +10% | B27: elasticity | C27: =Sw_Route -> 1 | D27: =Brent -> 82.01 | E27: =FreightMult*1.1 -> 1.1 | F27: =PortMult -> 1 | G27: =UtilFH -> 0.85 | H27: =UtilBH -> 0.5 | I27: =Speed -> 13.5 | J27: =PortCostMult -> 1 | K27: =EUA -> 75 | L27: =INDEX(Routes!$E$6:$E$9,$C27) -> 5000 | M27: =INDEX(Routes!$F$6:$F$9,$C27)/L27 -> 0.13 | N27: =2*L27*(1+SeaMargin)/(I27*24) -> 32.407407 | O27: =(I27/RefSpeed)^SpeedExp -> 1 | P27: =IF(H27>0,1,0) -> 1 | Q27: =N27/2*O27*(ConsLaden+IF(P27=1,ConsLaden,ConsBallast)) -> 875 | R27: =Q27*(1-M27) -> 761.25 | S27: =Q27*M27 -> 113.75 | T27: =1+P27 -> 2 | U27: =INDEX(Routes!$L$6:$L$9,$C27)*T27*F27 -> 10 | V27: =INDEX(Routes!$M$6:$M$9,$C27)*T27*F27 -> 7 | W27: =INDEX(Routes!$H$6:$H$9,$C27)*2 -> 0 | X27: =(U27+V27+W27)*ConsPort -> 102 | Y27: =R27*D27*VLSFO_Mult+(S27+X27)*D27*MGO_Mult -> 652340.34 | Z27: =(INDEX(Routes!$N$6:$N$9,$C27)+AN27+MIN(AC27*INDEX(Routes!$T$6:$T$9,$C27),INDEX(Routes!$V$6:$V$9,$C27))+INDEX(Routes!$O$6:$O$9,$C27)+AO27+MIN(AC27*INDEX(Routes!$U$6:$U$9,$C27),INDEX(Routes!$W$6:$W$9,$C27))+IF(P27=1,INDEX(Routes!$N$6:$N$9,$C27)+AN27+MIN(AD27*INDEX(Routes!$T$6:$T$9,$C27),INDEX(Routes!$V$6:$V$9,$C27))+INDEX(Routes!$O$6:$O$9,$C27)+AO27+MIN(AD27*INDEX(Routes!$U$6:$U$9,$C27),INDEX(Routes!$W$6:$W$9,$C27)),0))*J27 -> 252304.21 | AA27: =INDEX(Routes!$R$6:$R$9,$C27)+IF(P27=1,INDEX(Routes!$R$6:$R$9,$C27),INDEX(Routes!$S$6:$S$9,$C27)) -> 0 | AB27: =((R27*CO2_VLSFO+S27*CO2_MGO)*INDEX(Routes!$I$6:$I$9,$C27)+(U27*INDEX(Routes!$P$6:$P$9,$C27)+V27*INDEX(Routes!$Q$6:$Q$9,$C27))*ConsPort*CO2_MGO)*PhaseIn*K27*FX -> 123936.41 | AC27: =Capacity*G27 -> 30600 | AD27: =Capacity*H27 -> 18000 | AE27: =INDEX(Routes!$J$6:$J$9,$C27)*E27 -> 57.2 | AF27: =INDEX(Routes!$K$6:$K$9,$C27)*E27 -> 41.8 | AG27: =AC27*AE27+AD27*AF27 -> 2502720 | AH27: =AG27*Commission -> 62568 | AI27: =Y27+Z27+AA27+AB27+MiscVoy -> 1053581 | AJ27: =N27+U27+V27+W27 -> 49.407407 | AK27: =(AG27-AH27-AI27)/AJ27 -> 28064.031 | AL27: =AG27-AH27-AI27-Benchmark*AJ27 -> 497237.7 | AM27: =IF(AC27>0,((Benchmark*AJ27+AI27)/(1-Commission)-AD27*AF27)/AC27,0) -> 40.533745 | AN27: =LOA_ft*Port_Tariffs!$C$9*IF((INDEX(Routes!$L$6:$L$9,$C27)*INDEX(Routes!$X$6:$X$9,$C27)*F27)<=2,(INDEX(Routes!$L$6:$L$9,$C27)*INDEX(Routes!$X$6:$X$9,$C27)*F27),IF((INDEX(Routes!$L$6:$L$9,$C27)*INDEX(Routes!$X$6:$X$9,$C27)*F27)<=3,2+0.9*((INDEX(Routes!$L$6:$L$9,$C27)*INDEX(Routes!$X$6:$X$9,$C27)*F27)-2),IF((INDEX(Routes!$L$6:$L$9,$C27)*INDEX(Routes!$X$6:$X$9,$C27)*F27)<=4,2.9+0.75*((INDEX(Routes!$L$6:$L$9,$C27)*INDEX(Routes!$X$6:$X$9,$C27)*F27)-3),IF((INDEX(Routes!$L$6:$L$9,$C27)*INDEX(Routes!$X$6:$X$9,$C27)*F27)<=5,3.65+0.6*((INDEX(Routes!$L$6:$L$9,$C27)*INDEX(Routes!$X$6:$X$9,$C27)*F27)-4),4.25+0.5*((INDEX(Routes!$L$6:$L$9,$C27)*INDEX(Routes!$X$6:$X$9,$C27)*F27)-5))))) -> 19557.6 | AO27: =LOA_ft*Port_Tariffs!$C$9*IF((INDEX(Routes!$M$6:$M$9,$C27)*INDEX(Routes!$Y$6:$Y$9,$C27)*F27)<=2,(INDEX(Routes!$M$6:$M$9,$C27)*INDEX(Routes!$Y$6:$Y$9,$C27)*F27),IF((INDEX(Routes!$M$6:$M$9,$C27)*INDEX(Routes!$Y$6:$Y$9,$C27)*F27)<=3,2+0.9*((INDEX(Routes!$M$6:$M$9,$C27)*INDEX(Routes!$Y$6:$Y$9,$C27)*F27)-2),IF((INDEX(Routes!$M$6:$M$9,$C27)*INDEX(Routes!$Y$6:$Y$9,$C27)*F27)<=4,2.9+0.75*((INDEX(Routes!$M$6:$M$9,$C27)*INDEX(Routes!$Y$6:$Y$9,$C27)*F27)-3),IF((INDEX(Routes!$M$6:$M$9,$C27)*INDEX(Routes!$Y$6:$Y$9,$C27)*F27)<=5,3.65+0.6*((INDEX(Routes!$M$6:$M$9,$C27)*INDEX(Routes!$Y$6:$Y$9,$C27)*F27)-4),4.25+0.5*((INDEX(Routes!$M$6:$M$9,$C27)*INDEX(Routes!$Y$6:$Y$9,$C27)*F27)-5))))) -> 0
A28: Bunker price +10% | B28: elasticity | C28: =Sw_Route -> 1 | D28: =Brent*1.1 -> 90.211 | E28: =FreightMult -> 1 | F28: =PortMult -> 1 | G28: =UtilFH -> 0.85 | H28: =UtilBH -> 0.5 | I28: =Speed -> 13.5 | J28: =PortCostMult -> 1 | K28: =EUA -> 75 | L28: =INDEX(Routes!$E$6:$E$9,$C28) -> 5000 | M28: =INDEX(Routes!$F$6:$F$9,$C28)/L28 -> 0.13 | N28: =2*L28*(1+SeaMargin)/(I28*24) -> 32.407407 | O28: =(I28/RefSpeed)^SpeedExp -> 1 | P28: =IF(H28>0,1,0) -> 1 | Q28: =N28/2*O28*(ConsLaden+IF(P28=1,ConsLaden,ConsBallast)) -> 875 | R28: =Q28*(1-M28) -> 761.25 | S28: =Q28*M28 -> 113.75 | T28: =1+P28 -> 2 | U28: =INDEX(Routes!$L$6:$L$9,$C28)*T28*F28 -> 10 | V28: =INDEX(Routes!$M$6:$M$9,$C28)*T28*F28 -> 7 | W28: =INDEX(Routes!$H$6:$H$9,$C28)*2 -> 0 | X28: =(U28+V28+W28)*ConsPort -> 102 | Y28: =R28*D28*VLSFO_Mult+(S28+X28)*D28*MGO_Mult -> 717574.38 | Z28: =(INDEX(Routes!$N$6:$N$9,$C28)+AN28+MIN(AC28*INDEX(Routes!$T$6:$T$9,$C28),INDEX(Routes!$V$6:$V$9,$C28))+INDEX(Routes!$O$6:$O$9,$C28)+AO28+MIN(AC28*INDEX(Routes!$U$6:$U$9,$C28),INDEX(Routes!$W$6:$W$9,$C28))+IF(P28=1,INDEX(Routes!$N$6:$N$9,$C28)+AN28+MIN(AD28*INDEX(Routes!$T$6:$T$9,$C28),INDEX(Routes!$V$6:$V$9,$C28))+INDEX(Routes!$O$6:$O$9,$C28)+AO28+MIN(AD28*INDEX(Routes!$U$6:$U$9,$C28),INDEX(Routes!$W$6:$W$9,$C28)),0))*J28 -> 252304.21 | AA28: =INDEX(Routes!$R$6:$R$9,$C28)+IF(P28=1,INDEX(Routes!$R$6:$R$9,$C28),INDEX(Routes!$S$6:$S$9,$C28)) -> 0 | AB28: =((R28*CO2_VLSFO+S28*CO2_MGO)*INDEX(Routes!$I$6:$I$9,$C28)+(U28*INDEX(Routes!$P$6:$P$9,$C28)+V28*INDEX(Routes!$Q$6:$Q$9,$C28))*ConsPort*CO2_MGO)*PhaseIn*K28*FX -> 123936.41 | AC28: =Capacity*G28 -> 30600 | AD28: =Capacity*H28 -> 18000 | AE28: =INDEX(Routes!$J$6:$J$9,$C28)*E28 -> 52 | AF28: =INDEX(Routes!$K$6:$K$9,$C28)*E28 -> 38 | AG28: =AC28*AE28+AD28*AF28 -> 2275200 | AH28: =AG28*Commission -> 56880 | AI28: =Y28+Z28+AA28+AB28+MiscVoy -> 1118815 | AJ28: =N28+U28+V28+W28 -> 49.407407 | AK28: =(AG28-AH28-AI28)/AJ28 -> 22253.849 | AL28: =AG28-AH28-AI28-Benchmark*AJ28 -> 210171.67 | AM28: =IF(AC28>0,((Benchmark*AJ28+AI28)/(1-Commission)-AD28*AF28)/AC28,0) -> 44.955533 | AN28: =LOA_ft*Port_Tariffs!$C$9*IF((INDEX(Routes!$L$6:$L$9,$C28)*INDEX(Routes!$X$6:$X$9,$C28)*F28)<=2,(INDEX(Routes!$L$6:$L$9,$C28)*INDEX(Routes!$X$6:$X$9,$C28)*F28),IF((INDEX(Routes!$L$6:$L$9,$C28)*INDEX(Routes!$X$6:$X$9,$C28)*F28)<=3,2+0.9*((INDEX(Routes!$L$6:$L$9,$C28)*INDEX(Routes!$X$6:$X$9,$C28)*F28)-2),IF((INDEX(Routes!$L$6:$L$9,$C28)*INDEX(Routes!$X$6:$X$9,$C28)*F28)<=4,2.9+0.75*((INDEX(Routes!$L$6:$L$9,$C28)*INDEX(Routes!$X$6:$X$9,$C28)*F28)-3),IF((INDEX(Routes!$L$6:$L$9,$C28)*INDEX(Routes!$X$6:$X$9,$C28)*F28)<=5,3.65+0.6*((INDEX(Routes!$L$6:$L$9,$C28)*INDEX(Routes!$X$6:$X$9,$C28)*F28)-4),4.25+0.5*((INDEX(Routes!$L$6:$L$9,$C28)*INDEX(Routes!$X$6:$X$9,$C28)*F28)-5))))) -> 19557.6 | AO28: =LOA_ft*Port_Tariffs!$C$9*IF((INDEX(Routes!$M$6:$M$9,$C28)*INDEX(Routes!$Y$6:$Y$9,$C28)*F28)<=2,(INDEX(Routes!$M$6:$M$9,$C28)*INDEX(Routes!$Y$6:$Y$9,$C28)*F28),IF((INDEX(Routes!$M$6:$M$9,$C28)*INDEX(Routes!$Y$6:$Y$9,$C28)*F28)<=3,2+0.9*((INDEX(Routes!$M$6:$M$9,$C28)*INDEX(Routes!$Y$6:$Y$9,$C28)*F28)-2),IF((INDEX(Routes!$M$6:$M$9,$C28)*INDEX(Routes!$Y$6:$Y$9,$C28)*F28)<=4,2.9+0.75*((INDEX(Routes!$M$6:$M$9,$C28)*INDEX(Routes!$Y$6:$Y$9,$C28)*F28)-3),IF((INDEX(Routes!$M$6:$M$9,$C28)*INDEX(Routes!$Y$6:$Y$9,$C28)*F28)<=5,3.65+0.6*((INDEX(Routes!$M$6:$M$9,$C28)*INDEX(Routes!$Y$6:$Y$9,$C28)*F28)-4),4.25+0.5*((INDEX(Routes!$M$6:$M$9,$C28)*INDEX(Routes!$Y$6:$Y$9,$C28)*F28)-5))))) -> 0
A29: Port time +10% | B29: elasticity | C29: =Sw_Route -> 1 | D29: =Brent -> 82.01 | E29: =FreightMult -> 1 | F29: =PortMult*1.1 -> 1.1 | G29: =UtilFH -> 0.85 | H29: =UtilBH -> 0.5 | I29: =Speed -> 13.5 | J29: =PortCostMult -> 1 | K29: =EUA -> 75 | L29: =INDEX(Routes!$E$6:$E$9,$C29) -> 5000 | M29: =INDEX(Routes!$F$6:$F$9,$C29)/L29 -> 0.13 | N29: =2*L29*(1+SeaMargin)/(I29*24) -> 32.407407 | O29: =(I29/RefSpeed)^SpeedExp -> 1 | P29: =IF(H29>0,1,0) -> 1 | Q29: =N29/2*O29*(ConsLaden+IF(P29=1,ConsLaden,ConsBallast)) -> 875 | R29: =Q29*(1-M29) -> 761.25 | S29: =Q29*M29 -> 113.75 | T29: =1+P29 -> 2 | U29: =INDEX(Routes!$L$6:$L$9,$C29)*T29*F29 -> 11 | V29: =INDEX(Routes!$M$6:$M$9,$C29)*T29*F29 -> 7.7 | W29: =INDEX(Routes!$H$6:$H$9,$C29)*2 -> 0 | X29: =(U29+V29+W29)*ConsPort -> 112.2 | Y29: =R29*D29*VLSFO_Mult+(S29+X29)*D29*MGO_Mult -> 660454.41 | Z29: =(INDEX(Routes!$N$6:$N$9,$C29)+AN29+MIN(AC29*INDEX(Routes!$T$6:$T$9,$C29),INDEX(Routes!$V$6:$V$9,$C29))+INDEX(Routes!$O$6:$O$9,$C29)+AO29+MIN(AC29*INDEX(Routes!$U$6:$U$9,$C29),INDEX(Routes!$W$6:$W$9,$C29))+IF(P29=1,INDEX(Routes!$N$6:$N$9,$C29)+AN29+MIN(AD29*INDEX(Routes!$T$6:$T$9,$C29),INDEX(Routes!$V$6:$V$9,$C29))+INDEX(Routes!$O$6:$O$9,$C29)+AO29+MIN(AD29*INDEX(Routes!$U$6:$U$9,$C29),INDEX(Routes!$W$6:$W$9,$C29)),0))*J29 -> 255339.01 | AA29: =INDEX(Routes!$R$6:$R$9,$C29)+IF(P29=1,INDEX(Routes!$R$6:$R$9,$C29),INDEX(Routes!$S$6:$S$9,$C29)) -> 0 | AB29: =((R29*CO2_VLSFO+S29*CO2_MGO)*INDEX(Routes!$I$6:$I$9,$C29)+(U29*INDEX(Routes!$P$6:$P$9,$C29)+V29*INDEX(Routes!$Q$6:$Q$9,$C29))*ConsPort*CO2_MGO)*PhaseIn*K29*FX -> 125047.29 | AC29: =Capacity*G29 -> 30600 | AD29: =Capacity*H29 -> 18000 | AE29: =INDEX(Routes!$J$6:$J$9,$C29)*E29 -> 52 | AF29: =INDEX(Routes!$K$6:$K$9,$C29)*E29 -> 38 | AG29: =AC29*AE29+AD29*AF29 -> 2275200 | AH29: =AG29*Commission -> 56880 | AI29: =Y29+Z29+AA29+AB29+MiscVoy -> 1065840.7 | AJ29: =N29+U29+V29+W29 -> 51.107407 | AK29: =(AG29-AH29-AI29)/AJ29 -> 22550.142 | AL29: =AG29-AH29-AI29-Benchmark*AJ29 -> 232545.96 | AM29: =IF(AC29>0,((Benchmark*AJ29+AI29)/(1-Commission)-AD29*AF29)/AC29,0) -> 44.205599 | AN29: =LOA_ft*Port_Tariffs!$C$9*IF((INDEX(Routes!$L$6:$L$9,$C29)*INDEX(Routes!$X$6:$X$9,$C29)*F29)<=2,(INDEX(Routes!$L$6:$L$9,$C29)*INDEX(Routes!$X$6:$X$9,$C29)*F29),IF((INDEX(Routes!$L$6:$L$9,$C29)*INDEX(Routes!$X$6:$X$9,$C29)*F29)<=3,2+0.9*((INDEX(Routes!$L$6:$L$9,$C29)*INDEX(Routes!$X$6:$X$9,$C29)*F29)-2),IF((INDEX(Routes!$L$6:$L$9,$C29)*INDEX(Routes!$X$6:$X$9,$C29)*F29)<=4,2.9+0.75*((INDEX(Routes!$L$6:$L$9,$C29)*INDEX(Routes!$X$6:$X$9,$C29)*F29)-3),IF((INDEX(Routes!$L$6:$L$9,$C29)*INDEX(Routes!$X$6:$X$9,$C29)*F29)<=5,3.65+0.6*((INDEX(Routes!$L$6:$L$9,$C29)*INDEX(Routes!$X$6:$X$9,$C29)*F29)-4),4.25+0.5*((INDEX(Routes!$L$6:$L$9,$C29)*INDEX(Routes!$X$6:$X$9,$C29)*F29)-5))))) -> 21075 | AO29: =LOA_ft*Port_Tariffs!$C$9*IF((INDEX(Routes!$M$6:$M$9,$C29)*INDEX(Routes!$Y$6:$Y$9,$C29)*F29)<=2,(INDEX(Routes!$M$6:$M$9,$C29)*INDEX(Routes!$Y$6:$Y$9,$C29)*F29),IF((INDEX(Routes!$M$6:$M$9,$C29)*INDEX(Routes!$Y$6:$Y$9,$C29)*F29)<=3,2+0.9*((INDEX(Routes!$M$6:$M$9,$C29)*INDEX(Routes!$Y$6:$Y$9,$C29)*F29)-2),IF((INDEX(Routes!$M$6:$M$9,$C29)*INDEX(Routes!$Y$6:$Y$9,$C29)*F29)<=4,2.9+0.75*((INDEX(Routes!$M$6:$M$9,$C29)*INDEX(Routes!$Y$6:$Y$9,$C29)*F29)-3),IF((INDEX(Routes!$M$6:$M$9,$C29)*INDEX(Routes!$Y$6:$Y$9,$C29)*F29)<=5,3.65+0.6*((INDEX(Routes!$M$6:$M$9,$C29)*INDEX(Routes!$Y$6:$Y$9,$C29)*F29)-4),4.25+0.5*((INDEX(Routes!$M$6:$M$9,$C29)*INDEX(Routes!$Y$6:$Y$9,$C29)*F29)-5))))) -> 0
A30: Fronthaul utilization +10% | B30: elasticity | C30: =Sw_Route -> 1 | D30: =Brent -> 82.01 | E30: =FreightMult -> 1 | F30: =PortMult -> 1 | G30: =UtilFH*1.1 -> 0.935 | H30: =UtilBH -> 0.5 | I30: =Speed -> 13.5 | J30: =PortCostMult -> 1 | K30: =EUA -> 75 | L30: =INDEX(Routes!$E$6:$E$9,$C30) -> 5000 | M30: =INDEX(Routes!$F$6:$F$9,$C30)/L30 -> 0.13 | N30: =2*L30*(1+SeaMargin)/(I30*24) -> 32.407407 | O30: =(I30/RefSpeed)^SpeedExp -> 1 | P30: =IF(H30>0,1,0) -> 1 | Q30: =N30/2*O30*(ConsLaden+IF(P30=1,ConsLaden,ConsBallast)) -> 875 | R30: =Q30*(1-M30) -> 761.25 | S30: =Q30*M30 -> 113.75 | T30: =1+P30 -> 2 | U30: =INDEX(Routes!$L$6:$L$9,$C30)*T30*F30 -> 10 | V30: =INDEX(Routes!$M$6:$M$9,$C30)*T30*F30 -> 7 | W30: =INDEX(Routes!$H$6:$H$9,$C30)*2 -> 0 | X30: =(U30+V30+W30)*ConsPort -> 102 | Y30: =R30*D30*VLSFO_Mult+(S30+X30)*D30*MGO_Mult -> 652340.34 | Z30: =(INDEX(Routes!$N$6:$N$9,$C30)+AN30+MIN(AC30*INDEX(Routes!$T$6:$T$9,$C30),INDEX(Routes!$V$6:$V$9,$C30))+INDEX(Routes!$O$6:$O$9,$C30)+AO30+MIN(AC30*INDEX(Routes!$U$6:$U$9,$C30),INDEX(Routes!$W$6:$W$9,$C30))+IF(P30=1,INDEX(Routes!$N$6:$N$9,$C30)+AN30+MIN(AD30*INDEX(Routes!$T$6:$T$9,$C30),INDEX(Routes!$V$6:$V$9,$C30))+INDEX(Routes!$O$6:$O$9,$C30)+AO30+MIN(AD30*INDEX(Routes!$U$6:$U$9,$C30),INDEX(Routes!$W$6:$W$9,$C30)),0))*J30 -> 252779.98 | AA30: =INDEX(Routes!$R$6:$R$9,$C30)+IF(P30=1,INDEX(Routes!$R$6:$R$9,$C30),INDEX(Routes!$S$6:$S$9,$C30)) -> 0 | AB30: =((R30*CO2_VLSFO+S30*CO2_MGO)*INDEX(Routes!$I$6:$I$9,$C30)+(U30*INDEX(Routes!$P$6:$P$9,$C30)+V30*INDEX(Routes!$Q$6:$Q$9,$C30))*ConsPort*CO2_MGO)*PhaseIn*K30*FX -> 123936.41 | AC30: =Capacity*G30 -> 33660 | AD30: =Capacity*H30 -> 18000 | AE30: =INDEX(Routes!$J$6:$J$9,$C30)*E30 -> 52 | AF30: =INDEX(Routes!$K$6:$K$9,$C30)*E30 -> 38 | AG30: =AC30*AE30+AD30*AF30 -> 2434320 | AH30: =AG30*Commission -> 60858 | AI30: =Y30+Z30+AA30+AB30+MiscVoy -> 1054056.7 | AJ30: =N30+U30+V30+W30 -> 49.407407 | AK30: =(AG30-AH30-AI30)/AJ30 -> 26704.604 | AL30: =AG30-AH30-AI30-Benchmark*AJ30 -> 430071.94 | AM30: =IF(AC30>0,((Benchmark*AJ30+AI30)/(1-Commission)-AD30*AF30)/AC30,0) -> 38.895442 | AN30: =LOA_ft*Port_Tariffs!$C$9*IF((INDEX(Routes!$L$6:$L$9,$C30)*INDEX(Routes!$X$6:$X$9,$C30)*F30)<=2,(INDEX(Routes!$L$6:$L$9,$C30)*INDEX(Routes!$X$6:$X$9,$C30)*F30),IF((INDEX(Routes!$L$6:$L$9,$C30)*INDEX(Routes!$X$6:$X$9,$C30)*F30)<=3,2+0.9*((INDEX(Routes!$L$6:$L$9,$C30)*INDEX(Routes!$X$6:$X$9,$C30)*F30)-2),IF((INDEX(Routes!$L$6:$L$9,$C30)*INDEX(Routes!$X$6:$X$9,$C30)*F30)<=4,2.9+0.75*((INDEX(Routes!$L$6:$L$9,$C30)*INDEX(Routes!$X$6:$X$9,$C30)*F30)-3),IF((INDEX(Routes!$L$6:$L$9,$C30)*INDEX(Routes!$X$6:$X$9,$C30)*F30)<=5,3.65+0.6*((INDEX(Routes!$L$6:$L$9,$C30)*INDEX(Routes!$X$6:$X$9,$C30)*F30)-4),4.25+0.5*((INDEX(Routes!$L$6:$L$9,$C30)*INDEX(Routes!$X$6:$X$9,$C30)*F30)-5))))) -> 19557.6 | AO30: =LOA_ft*Port_Tariffs!$C$9*IF((INDEX(Routes!$M$6:$M$9,$C30)*INDEX(Routes!$Y$6:$Y$9,$C30)*F30)<=2,(INDEX(Routes!$M$6:$M$9,$C30)*INDEX(Routes!$Y$6:$Y$9,$C30)*F30),IF((INDEX(Routes!$M$6:$M$9,$C30)*INDEX(Routes!$Y$6:$Y$9,$C30)*F30)<=3,2+0.9*((INDEX(Routes!$M$6:$M$9,$C30)*INDEX(Routes!$Y$6:$Y$9,$C30)*F30)-2),IF((INDEX(Routes!$M$6:$M$9,$C30)*INDEX(Routes!$Y$6:$Y$9,$C30)*F30)<=4,2.9+0.75*((INDEX(Routes!$M$6:$M$9,$C30)*INDEX(Routes!$Y$6:$Y$9,$C30)*F30)-3),IF((INDEX(Routes!$M$6:$M$9,$C30)*INDEX(Routes!$Y$6:$Y$9,$C30)*F30)<=5,3.65+0.6*((INDEX(Routes!$M$6:$M$9,$C30)*INDEX(Routes!$Y$6:$Y$9,$C30)*F30)-4),4.25+0.5*((INDEX(Routes!$M$6:$M$9,$C30)*INDEX(Routes!$Y$6:$Y$9,$C30)*F30)-5))))) -> 0
A31: Backhaul utilization +10% | B31: elasticity | C31: =Sw_Route -> 1 | D31: =Brent -> 82.01 | E31: =FreightMult -> 1 | F31: =PortMult -> 1 | G31: =UtilFH -> 0.85 | H31: =UtilBH*1.1 -> 0.55 | I31: =Speed -> 13.5 | J31: =PortCostMult -> 1 | K31: =EUA -> 75 | L31: =INDEX(Routes!$E$6:$E$9,$C31) -> 5000 | M31: =INDEX(Routes!$F$6:$F$9,$C31)/L31 -> 0.13 | N31: =2*L31*(1+SeaMargin)/(I31*24) -> 32.407407 | O31: =(I31/RefSpeed)^SpeedExp -> 1 | P31: =IF(H31>0,1,0) -> 1 | Q31: =N31/2*O31*(ConsLaden+IF(P31=1,ConsLaden,ConsBallast)) -> 875 | R31: =Q31*(1-M31) -> 761.25 | S31: =Q31*M31 -> 113.75 | T31: =1+P31 -> 2 | U31: =INDEX(Routes!$L$6:$L$9,$C31)*T31*F31 -> 10 | V31: =INDEX(Routes!$M$6:$M$9,$C31)*T31*F31 -> 7 | W31: =INDEX(Routes!$H$6:$H$9,$C31)*2 -> 0 | X31: =(U31+V31+W31)*ConsPort -> 102 | Y31: =R31*D31*VLSFO_Mult+(S31+X31)*D31*MGO_Mult -> 652340.34 | Z31: =(INDEX(Routes!$N$6:$N$9,$C31)+AN31+MIN(AC31*INDEX(Routes!$T$6:$T$9,$C31),INDEX(Routes!$V$6:$V$9,$C31))+INDEX(Routes!$O$6:$O$9,$C31)+AO31+MIN(AC31*INDEX(Routes!$U$6:$U$9,$C31),INDEX(Routes!$W$6:$W$9,$C31))+IF(P31=1,INDEX(Routes!$N$6:$N$9,$C31)+AN31+MIN(AD31*INDEX(Routes!$T$6:$T$9,$C31),INDEX(Routes!$V$6:$V$9,$C31))+INDEX(Routes!$O$6:$O$9,$C31)+AO31+MIN(AD31*INDEX(Routes!$U$6:$U$9,$C31),INDEX(Routes!$W$6:$W$9,$C31)),0))*J31 -> 253484.61 | AA31: =INDEX(Routes!$R$6:$R$9,$C31)+IF(P31=1,INDEX(Routes!$R$6:$R$9,$C31),INDEX(Routes!$S$6:$S$9,$C31)) -> 0 | AB31: =((R31*CO2_VLSFO+S31*CO2_MGO)*INDEX(Routes!$I$6:$I$9,$C31)+(U31*INDEX(Routes!$P$6:$P$9,$C31)+V31*INDEX(Routes!$Q$6:$Q$9,$C31))*ConsPort*CO2_MGO)*PhaseIn*K31*FX -> 123936.41 | AC31: =Capacity*G31 -> 30600 | AD31: =Capacity*H31 -> 19800 | AE31: =INDEX(Routes!$J$6:$J$9,$C31)*E31 -> 52 | AF31: =INDEX(Routes!$K$6:$K$9,$C31)*E31 -> 38 | AG31: =AC31*AE31+AD31*AF31 -> 2343600 | AH31: =AG31*Commission -> 58590 | AI31: =Y31+Z31+AA31+AB31+MiscVoy -> 1054761.4 | AJ31: =N31+U31+V31+W31 -> 49.407407 | AK31: =(AG31-AH31-AI31)/AJ31 -> 24900.085 | AL31: =AG31-AH31-AI31-Benchmark*AJ31 -> 340915.31 | AM31: =IF(AC31>0,((Benchmark*AJ31+AI31)/(1-Commission)-AD31*AF31)/AC31,0) -> 40.57331 | AN31: =LOA_ft*Port_Tariffs!$C$9*IF((INDEX(Routes!$L$6:$L$9,$C31)*INDEX(Routes!$X$6:$X$9,$C31)*F31)<=2,(INDEX(Routes!$L$6:$L$9,$C31)*INDEX(Routes!$X$6:$X$9,$C31)*F31),IF((INDEX(Routes!$L$6:$L$9,$C31)*INDEX(Routes!$X$6:$X$9,$C31)*F31)<=3,2+0.9*((INDEX(Routes!$L$6:$L$9,$C31)*INDEX(Routes!$X$6:$X$9,$C31)*F31)-2),IF((INDEX(Routes!$L$6:$L$9,$C31)*INDEX(Routes!$X$6:$X$9,$C31)*F31)<=4,2.9+0.75*((INDEX(Routes!$L$6:$L$9,$C31)*INDEX(Routes!$X$6:$X$9,$C31)*F31)-3),IF((INDEX(Routes!$L$6:$L$9,$C31)*INDEX(Routes!$X$6:$X$9,$C31)*F31)<=5,3.65+0.6*((INDEX(Routes!$L$6:$L$9,$C31)*INDEX(Routes!$X$6:$X$9,$C31)*F31)-4),4.25+0.5*((INDEX(Routes!$L$6:$L$9,$C31)*INDEX(Routes!$X$6:$X$9,$C31)*F31)-5))))) -> 19557.6 | AO31: =LOA_ft*Port_Tariffs!$C$9*IF((INDEX(Routes!$M$6:$M$9,$C31)*INDEX(Routes!$Y$6:$Y$9,$C31)*F31)<=2,(INDEX(Routes!$M$6:$M$9,$C31)*INDEX(Routes!$Y$6:$Y$9,$C31)*F31),IF((INDEX(Routes!$M$6:$M$9,$C31)*INDEX(Routes!$Y$6:$Y$9,$C31)*F31)<=3,2+0.9*((INDEX(Routes!$M$6:$M$9,$C31)*INDEX(Routes!$Y$6:$Y$9,$C31)*F31)-2),IF((INDEX(Routes!$M$6:$M$9,$C31)*INDEX(Routes!$Y$6:$Y$9,$C31)*F31)<=4,2.9+0.75*((INDEX(Routes!$M$6:$M$9,$C31)*INDEX(Routes!$Y$6:$Y$9,$C31)*F31)-3),IF((INDEX(Routes!$M$6:$M$9,$C31)*INDEX(Routes!$Y$6:$Y$9,$C31)*F31)<=5,3.65+0.6*((INDEX(Routes!$M$6:$M$9,$C31)*INDEX(Routes!$Y$6:$Y$9,$C31)*F31)-4),4.25+0.5*((INDEX(Routes!$M$6:$M$9,$C31)*INDEX(Routes!$Y$6:$Y$9,$C31)*F31)-5))))) -> 0
A32: Service speed +10% | B32: elasticity | C32: =Sw_Route -> 1 | D32: =Brent -> 82.01 | E32: =FreightMult -> 1 | F32: =PortMult -> 1 | G32: =UtilFH -> 0.85 | H32: =UtilBH -> 0.5 | I32: =Speed*1.1 -> 14.85 | J32: =PortCostMult -> 1 | K32: =EUA -> 75 | L32: =INDEX(Routes!$E$6:$E$9,$C32) -> 5000 | M32: =INDEX(Routes!$F$6:$F$9,$C32)/L32 -> 0.13 | N32: =2*L32*(1+SeaMargin)/(I32*24) -> 29.461279 | O32: =(I32/RefSpeed)^SpeedExp -> 1.331 | P32: =IF(H32>0,1,0) -> 1 | Q32: =N32/2*O32*(ConsLaden+IF(P32=1,ConsLaden,ConsBallast)) -> 1058.75 | R32: =Q32*(1-M32) -> 921.1125 | S32: =Q32*M32 -> 137.6375 | T32: =1+P32 -> 2 | U32: =INDEX(Routes!$L$6:$L$9,$C32)*T32*F32 -> 10 | V32: =INDEX(Routes!$M$6:$M$9,$C32)*T32*F32 -> 7 | W32: =INDEX(Routes!$H$6:$H$9,$C32)*2 -> 0 | X32: =(U32+V32+W32)*ConsPort -> 102 | Y32: =R32*D32*VLSFO_Mult+(S32+X32)*D32*MGO_Mult -> 772292.27 | Z32: =(INDEX(Routes!$N$6:$N$9,$C32)+AN32+MIN(AC32*INDEX(Routes!$T$6:$T$9,$C32),INDEX(Routes!$V$6:$V$9,$C32))+INDEX(Routes!$O$6:$O$9,$C32)+AO32+MIN(AC32*INDEX(Routes!$U$6:$U$9,$C32),INDEX(Routes!$W$6:$W$9,$C32))+IF(P32=1,INDEX(Routes!$N$6:$N$9,$C32)+AN32+MIN(AD32*INDEX(Routes!$T$6:$T$9,$C32),INDEX(Routes!$V$6:$V$9,$C32))+INDEX(Routes!$O$6:$O$9,$C32)+AO32+MIN(AD32*INDEX(Routes!$U$6:$U$9,$C32),INDEX(Routes!$W$6:$W$9,$C32)),0))*J32 -> 252304.21 | AA32: =INDEX(Routes!$R$6:$R$9,$C32)+IF(P32=1,INDEX(Routes!$R$6:$R$9,$C32),INDEX(Routes!$S$6:$S$9,$C32)) -> 0 | AB32: =((R32*CO2_VLSFO+S32*CO2_MGO)*INDEX(Routes!$I$6:$I$9,$C32)+(U32*INDEX(Routes!$P$6:$P$9,$C32)+V32*INDEX(Routes!$Q$6:$Q$9,$C32))*ConsPort*CO2_MGO)*PhaseIn*K32*FX -> 147630.21 | AC32: =Capacity*G32 -> 30600 | AD32: =Capacity*H32 -> 18000 | AE32: =INDEX(Routes!$J$6:$J$9,$C32)*E32 -> 52 | AF32: =INDEX(Routes!$K$6:$K$9,$C32)*E32 -> 38 | AG32: =AC32*AE32+AD32*AF32 -> 2275200 | AH32: =AG32*Commission -> 56880 | AI32: =Y32+Z32+AA32+AB32+MiscVoy -> 1197226.7 | AJ32: =N32+U32+V32+W32 -> 46.461279 | AK32: =(AG32-AH32-AI32)/AJ32 -> 21977.296 | AL32: =AG32-AH32-AI32-Benchmark*AJ32 -> 184790.28 | AM32: =IF(AC32>0,((Benchmark*AJ32+AI32)/(1-Commission)-AD32*AF32)/AC32,0) -> 45.806258 | AN32: =LOA_ft*Port_Tariffs!$C$9*IF((INDEX(Routes!$L$6:$L$9,$C32)*INDEX(Routes!$X$6:$X$9,$C32)*F32)<=2,(INDEX(Routes!$L$6:$L$9,$C32)*INDEX(Routes!$X$6:$X$9,$C32)*F32),IF((INDEX(Routes!$L$6:$L$9,$C32)*INDEX(Routes!$X$6:$X$9,$C32)*F32)<=3,2+0.9*((INDEX(Routes!$L$6:$L$9,$C32)*INDEX(Routes!$X$6:$X$9,$C32)*F32)-2),IF((INDEX(Routes!$L$6:$L$9,$C32)*INDEX(Routes!$X$6:$X$9,$C32)*F32)<=4,2.9+0.75*((INDEX(Routes!$L$6:$L$9,$C32)*INDEX(Routes!$X$6:$X$9,$C32)*F32)-3),IF((INDEX(Routes!$L$6:$L$9,$C32)*INDEX(Routes!$X$6:$X$9,$C32)*F32)<=5,3.65+0.6*((INDEX(Routes!$L$6:$L$9,$C32)*INDEX(Routes!$X$6:$X$9,$C32)*F32)-4),4.25+0.5*((INDEX(Routes!$L$6:$L$9,$C32)*INDEX(Routes!$X$6:$X$9,$C32)*F32)-5))))) -> 19557.6 | AO32: =LOA_ft*Port_Tariffs!$C$9*IF((INDEX(Routes!$M$6:$M$9,$C32)*INDEX(Routes!$Y$6:$Y$9,$C32)*F32)<=2,(INDEX(Routes!$M$6:$M$9,$C32)*INDEX(Routes!$Y$6:$Y$9,$C32)*F32),IF((INDEX(Routes!$M$6:$M$9,$C32)*INDEX(Routes!$Y$6:$Y$9,$C32)*F32)<=3,2+0.9*((INDEX(Routes!$M$6:$M$9,$C32)*INDEX(Routes!$Y$6:$Y$9,$C32)*F32)-2),IF((INDEX(Routes!$M$6:$M$9,$C32)*INDEX(Routes!$Y$6:$Y$9,$C32)*F32)<=4,2.9+0.75*((INDEX(Routes!$M$6:$M$9,$C32)*INDEX(Routes!$Y$6:$Y$9,$C32)*F32)-3),IF((INDEX(Routes!$M$6:$M$9,$C32)*INDEX(Routes!$Y$6:$Y$9,$C32)*F32)<=5,3.65+0.6*((INDEX(Routes!$M$6:$M$9,$C32)*INDEX(Routes!$Y$6:$Y$9,$C32)*F32)-4),4.25+0.5*((INDEX(Routes!$M$6:$M$9,$C32)*INDEX(Routes!$Y$6:$Y$9,$C32)*F32)-5))))) -> 0
A33: Port disbursements +10% | B33: elasticity | C33: =Sw_Route -> 1 | D33: =Brent -> 82.01 | E33: =FreightMult -> 1 | F33: =PortMult -> 1 | G33: =UtilFH -> 0.85 | H33: =UtilBH -> 0.5 | I33: =Speed -> 13.5 | J33: =PortCostMult*1.1 -> 1.1 | K33: =EUA -> 75 | L33: =INDEX(Routes!$E$6:$E$9,$C33) -> 5000 | M33: =INDEX(Routes!$F$6:$F$9,$C33)/L33 -> 0.13 | N33: =2*L33*(1+SeaMargin)/(I33*24) -> 32.407407 | O33: =(I33/RefSpeed)^SpeedExp -> 1 | P33: =IF(H33>0,1,0) -> 1 | Q33: =N33/2*O33*(ConsLaden+IF(P33=1,ConsLaden,ConsBallast)) -> 875 | R33: =Q33*(1-M33) -> 761.25 | S33: =Q33*M33 -> 113.75 | T33: =1+P33 -> 2 | U33: =INDEX(Routes!$L$6:$L$9,$C33)*T33*F33 -> 10 | V33: =INDEX(Routes!$M$6:$M$9,$C33)*T33*F33 -> 7 | W33: =INDEX(Routes!$H$6:$H$9,$C33)*2 -> 0 | X33: =(U33+V33+W33)*ConsPort -> 102 | Y33: =R33*D33*VLSFO_Mult+(S33+X33)*D33*MGO_Mult -> 652340.34 | Z33: =(INDEX(Routes!$N$6:$N$9,$C33)+AN33+MIN(AC33*INDEX(Routes!$T$6:$T$9,$C33),INDEX(Routes!$V$6:$V$9,$C33))+INDEX(Routes!$O$6:$O$9,$C33)+AO33+MIN(AC33*INDEX(Routes!$U$6:$U$9,$C33),INDEX(Routes!$W$6:$W$9,$C33))+IF(P33=1,INDEX(Routes!$N$6:$N$9,$C33)+AN33+MIN(AD33*INDEX(Routes!$T$6:$T$9,$C33),INDEX(Routes!$V$6:$V$9,$C33))+INDEX(Routes!$O$6:$O$9,$C33)+AO33+MIN(AD33*INDEX(Routes!$U$6:$U$9,$C33),INDEX(Routes!$W$6:$W$9,$C33)),0))*J33 -> 277534.63 | AA33: =INDEX(Routes!$R$6:$R$9,$C33)+IF(P33=1,INDEX(Routes!$R$6:$R$9,$C33),INDEX(Routes!$S$6:$S$9,$C33)) -> 0 | AB33: =((R33*CO2_VLSFO+S33*CO2_MGO)*INDEX(Routes!$I$6:$I$9,$C33)+(U33*INDEX(Routes!$P$6:$P$9,$C33)+V33*INDEX(Routes!$Q$6:$Q$9,$C33))*ConsPort*CO2_MGO)*PhaseIn*K33*FX -> 123936.41 | AC33: =Capacity*G33 -> 30600 | AD33: =Capacity*H33 -> 18000 | AE33: =INDEX(Routes!$J$6:$J$9,$C33)*E33 -> 52 | AF33: =INDEX(Routes!$K$6:$K$9,$C33)*E33 -> 38 | AG33: =AC33*AE33+AD33*AF33 -> 2275200 | AH33: =AG33*Commission -> 56880 | AI33: =Y33+Z33+AA33+AB33+MiscVoy -> 1078811.4 | AJ33: =N33+U33+V33+W33 -> 49.407407 | AK33: =(AG33-AH33-AI33)/AJ33 -> 23063.518 | AL33: =AG33-AH33-AI33-Benchmark*AJ33 -> 250175.28 | AM33: =IF(AC33>0,((Benchmark*AJ33+AI33)/(1-Commission)-AD33*AF33)/AC33,0) -> 43.614705 | AN33: =LOA_ft*Port_Tariffs!$C$9*IF((INDEX(Routes!$L$6:$L$9,$C33)*INDEX(Routes!$X$6:$X$9,$C33)*F33)<=2,(INDEX(Routes!$L$6:$L$9,$C33)*INDEX(Routes!$X$6:$X$9,$C33)*F33),IF((INDEX(Routes!$L$6:$L$9,$C33)*INDEX(Routes!$X$6:$X$9,$C33)*F33)<=3,2+0.9*((INDEX(Routes!$L$6:$L$9,$C33)*INDEX(Routes!$X$6:$X$9,$C33)*F33)-2),IF((INDEX(Routes!$L$6:$L$9,$C33)*INDEX(Routes!$X$6:$X$9,$C33)*F33)<=4,2.9+0.75*((INDEX(Routes!$L$6:$L$9,$C33)*INDEX(Routes!$X$6:$X$9,$C33)*F33)-3),IF((INDEX(Routes!$L$6:$L$9,$C33)*INDEX(Routes!$X$6:$X$9,$C33)*F33)<=5,3.65+0.6*((INDEX(Routes!$L$6:$L$9,$C33)*INDEX(Routes!$X$6:$X$9,$C33)*F33)-4),4.25+0.5*((INDEX(Routes!$L$6:$L$9,$C33)*INDEX(Routes!$X$6:$X$9,$C33)*F33)-5))))) -> 19557.6 | AO33: =LOA_ft*Port_Tariffs!$C$9*IF((INDEX(Routes!$M$6:$M$9,$C33)*INDEX(Routes!$Y$6:$Y$9,$C33)*F33)<=2,(INDEX(Routes!$M$6:$M$9,$C33)*INDEX(Routes!$Y$6:$Y$9,$C33)*F33),IF((INDEX(Routes!$M$6:$M$9,$C33)*INDEX(Routes!$Y$6:$Y$9,$C33)*F33)<=3,2+0.9*((INDEX(Routes!$M$6:$M$9,$C33)*INDEX(Routes!$Y$6:$Y$9,$C33)*F33)-2),IF((INDEX(Routes!$M$6:$M$9,$C33)*INDEX(Routes!$Y$6:$Y$9,$C33)*F33)<=4,2.9+0.75*((INDEX(Routes!$M$6:$M$9,$C33)*INDEX(Routes!$Y$6:$Y$9,$C33)*F33)-3),IF((INDEX(Routes!$M$6:$M$9,$C33)*INDEX(Routes!$Y$6:$Y$9,$C33)*F33)<=5,3.65+0.6*((INDEX(Routes!$M$6:$M$9,$C33)*INDEX(Routes!$Y$6:$Y$9,$C33)*F33)-4),4.25+0.5*((INDEX(Routes!$M$6:$M$9,$C33)*INDEX(Routes!$Y$6:$Y$9,$C33)*F33)-5))))) -> 0
A35: ROUTE COMPARISON (active levers, each route)
A36: Route 1 | B36: routes | C36: 1 | D36: =Brent -> 82.01 | E36: =FreightMult -> 1 | F36: =PortMult -> 1 | G36: =UtilFH -> 0.85 | H36: =UtilBH -> 0.5 | I36: =Speed -> 13.5 | J36: =PortCostMult -> 1 | K36: =EUA -> 75 | L36: =INDEX(Routes!$E$6:$E$9,$C36) -> 5000 | M36: =INDEX(Routes!$F$6:$F$9,$C36)/L36 -> 0.13 | N36: =2*L36*(1+SeaMargin)/(I36*24) -> 32.407407 | O36: =(I36/RefSpeed)^SpeedExp -> 1 | P36: =IF(H36>0,1,0) -> 1 | Q36: =N36/2*O36*(ConsLaden+IF(P36=1,ConsLaden,ConsBallast)) -> 875 | R36: =Q36*(1-M36) -> 761.25 | S36: =Q36*M36 -> 113.75 | T36: =1+P36 -> 2 | U36: =INDEX(Routes!$L$6:$L$9,$C36)*T36*F36 -> 10 | V36: =INDEX(Routes!$M$6:$M$9,$C36)*T36*F36 -> 7 | W36: =INDEX(Routes!$H$6:$H$9,$C36)*2 -> 0 | X36: =(U36+V36+W36)*ConsPort -> 102 | Y36: =R36*D36*VLSFO_Mult+(S36+X36)*D36*MGO_Mult -> 652340.34 | Z36: =(INDEX(Routes!$N$6:$N$9,$C36)+AN36+MIN(AC36*INDEX(Routes!$T$6:$T$9,$C36),INDEX(Routes!$V$6:$V$9,$C36))+INDEX(Routes!$O$6:$O$9,$C36)+AO36+MIN(AC36*INDEX(Routes!$U$6:$U$9,$C36),INDEX(Routes!$W$6:$W$9,$C36))+IF(P36=1,INDEX(Routes!$N$6:$N$9,$C36)+AN36+MIN(AD36*INDEX(Routes!$T$6:$T$9,$C36),INDEX(Routes!$V$6:$V$9,$C36))+INDEX(Routes!$O$6:$O$9,$C36)+AO36+MIN(AD36*INDEX(Routes!$U$6:$U$9,$C36),INDEX(Routes!$W$6:$W$9,$C36)),0))*J36 -> 252304.21 | AA36: =INDEX(Routes!$R$6:$R$9,$C36)+IF(P36=1,INDEX(Routes!$R$6:$R$9,$C36),INDEX(Routes!$S$6:$S$9,$C36)) -> 0 | AB36: =((R36*CO2_VLSFO+S36*CO2_MGO)*INDEX(Routes!$I$6:$I$9,$C36)+(U36*INDEX(Routes!$P$6:$P$9,$C36)+V36*INDEX(Routes!$Q$6:$Q$9,$C36))*ConsPort*CO2_MGO)*PhaseIn*K36*FX -> 123936.41 | AC36: =Capacity*G36 -> 30600 | AD36: =Capacity*H36 -> 18000 | AE36: =INDEX(Routes!$J$6:$J$9,$C36)*E36 -> 52 | AF36: =INDEX(Routes!$K$6:$K$9,$C36)*E36 -> 38 | AG36: =AC36*AE36+AD36*AF36 -> 2275200 | AH36: =AG36*Commission -> 56880 | AI36: =Y36+Z36+AA36+AB36+MiscVoy -> 1053581 | AJ36: =N36+U36+V36+W36 -> 49.407407 | AK36: =(AG36-AH36-AI36)/AJ36 -> 23574.178 | AL36: =AG36-AH36-AI36-Benchmark*AJ36 -> 275405.7 | AM36: =IF(AC36>0,((Benchmark*AJ36+AI36)/(1-Commission)-AD36*AF36)/AC36,0) -> 42.76904 | AN36: =LOA_ft*Port_Tariffs!$C$9*IF((INDEX(Routes!$L$6:$L$9,$C36)*INDEX(Routes!$X$6:$X$9,$C36)*F36)<=2,(INDEX(Routes!$L$6:$L$9,$C36)*INDEX(Routes!$X$6:$X$9,$C36)*F36),IF((INDEX(Routes!$L$6:$L$9,$C36)*INDEX(Routes!$X$6:$X$9,$C36)*F36)<=3,2+0.9*((INDEX(Routes!$L$6:$L$9,$C36)*INDEX(Routes!$X$6:$X$9,$C36)*F36)-2),IF((INDEX(Routes!$L$6:$L$9,$C36)*INDEX(Routes!$X$6:$X$9,$C36)*F36)<=4,2.9+0.75*((INDEX(Routes!$L$6:$L$9,$C36)*INDEX(Routes!$X$6:$X$9,$C36)*F36)-3),IF((INDEX(Routes!$L$6:$L$9,$C36)*INDEX(Routes!$X$6:$X$9,$C36)*F36)<=5,3.65+0.6*((INDEX(Routes!$L$6:$L$9,$C36)*INDEX(Routes!$X$6:$X$9,$C36)*F36)-4),4.25+0.5*((INDEX(Routes!$L$6:$L$9,$C36)*INDEX(Routes!$X$6:$X$9,$C36)*F36)-5))))) -> 19557.6 | AO36: =LOA_ft*Port_Tariffs!$C$9*IF((INDEX(Routes!$M$6:$M$9,$C36)*INDEX(Routes!$Y$6:$Y$9,$C36)*F36)<=2,(INDEX(Routes!$M$6:$M$9,$C36)*INDEX(Routes!$Y$6:$Y$9,$C36)*F36),IF((INDEX(Routes!$M$6:$M$9,$C36)*INDEX(Routes!$Y$6:$Y$9,$C36)*F36)<=3,2+0.9*((INDEX(Routes!$M$6:$M$9,$C36)*INDEX(Routes!$Y$6:$Y$9,$C36)*F36)-2),IF((INDEX(Routes!$M$6:$M$9,$C36)*INDEX(Routes!$Y$6:$Y$9,$C36)*F36)<=4,2.9+0.75*((INDEX(Routes!$M$6:$M$9,$C36)*INDEX(Routes!$Y$6:$Y$9,$C36)*F36)-3),IF((INDEX(Routes!$M$6:$M$9,$C36)*INDEX(Routes!$Y$6:$Y$9,$C36)*F36)<=5,3.65+0.6*((INDEX(Routes!$M$6:$M$9,$C36)*INDEX(Routes!$Y$6:$Y$9,$C36)*F36)-4),4.25+0.5*((INDEX(Routes!$M$6:$M$9,$C36)*INDEX(Routes!$Y$6:$Y$9,$C36)*F36)-5))))) -> 0
A37: Route 2 | B37: routes | C37: 2 | D37: =Brent -> 82.01 | E37: =FreightMult -> 1 | F37: =PortMult -> 1 | G37: =UtilFH -> 0.85 | H37: =UtilBH -> 0.5 | I37: =Speed -> 13.5 | J37: =PortCostMult -> 1 | K37: =EUA -> 75 | L37: =INDEX(Routes!$E$6:$E$9,$C37) -> 9650 | M37: =INDEX(Routes!$F$6:$F$9,$C37)/L37 -> 0.020725389 | N37: =2*L37*(1+SeaMargin)/(I37*24) -> 62.546296 | O37: =(I37/RefSpeed)^SpeedExp -> 1 | P37: =IF(H37>0,1,0) -> 1 | Q37: =N37/2*O37*(ConsLaden+IF(P37=1,ConsLaden,ConsBallast)) -> 1688.75 | R37: =Q37*(1-M37) -> 1653.75 | S37: =Q37*M37 -> 35 | T37: =1+P37 -> 2 | U37: =INDEX(Routes!$L$6:$L$9,$C37)*T37*F37 -> 10 | V37: =INDEX(Routes!$M$6:$M$9,$C37)*T37*F37 -> 7 | W37: =INDEX(Routes!$H$6:$H$9,$C37)*2 -> 3 | X37: =(U37+V37+W37)*ConsPort -> 120 | Y37: =R37*D37*VLSFO_Mult+(S37+X37)*D37*MGO_Mult -> 1167607.1 | Z37: =(INDEX(Routes!$N$6:$N$9,$C37)+AN37+MIN(AC37*INDEX(Routes!$T$6:$T$9,$C37),INDEX(Routes!$V$6:$V$9,$C37))+INDEX(Routes!$O$6:$O$9,$C37)+AO37+MIN(AC37*INDEX(Routes!$U$6:$U$9,$C37),INDEX(Routes!$W$6:$W$9,$C37))+IF(P37=1,INDEX(Routes!$N$6:$N$9,$C37)+AN37+MIN(AD37*INDEX(Routes!$T$6:$T$9,$C37),INDEX(Routes!$V$6:$V$9,$C37))+INDEX(Routes!$O$6:$O$9,$C37)+AO37+MIN(AD37*INDEX(Routes!$U$6:$U$9,$C37),INDEX(Routes!$W$6:$W$9,$C37)),0))*J37 -> 260742 | AA37: =INDEX(Routes!$R$6:$R$9,$C37)+IF(P37=1,INDEX(Routes!$R$6:$R$9,$C37),INDEX(Routes!$S$6:$S$9,$C37)) -> 426920 | AB37: =((R37*CO2_VLSFO+S37*CO2_MGO)*INDEX(Routes!$I$6:$I$9,$C37)+(U37*INDEX(Routes!$P$6:$P$9,$C37)+V37*INDEX(Routes!$Q$6:$Q$9,$C37))*ConsPort*CO2_MGO)*PhaseIn*K37*FX -> 0 | AC37: =Capacity*G37 -> 30600 | AD37: =Capacity*H37 -> 18000 | AE37: =INDEX(Routes!$J$6:$J$9,$C37)*E37 -> 92 | AF37: =INDEX(Routes!$K$6:$K$9,$C37)*E37 -> 52 | AG37: =AC37*AE37+AD37*AF37 -> 3751200 | AH37: =AG37*Commission -> 93780 | AI37: =Y37+Z37+AA37+AB37+MiscVoy -> 1880269.1 | AJ37: =N37+U37+V37+W37 -> 82.546296 | AK37: =(AG37-AH37-AI37)/AJ37 -> 21529.141 | AL37: =AG37-AH37-AI37-Benchmark*AJ37 -> 291317.54 | AM37: =IF(AC37>0,((Benchmark*AJ37+AI37)/(1-Commission)-AD37*AF37)/AC37,0) -> 82.235712 | AN37: =LOA_ft*Port_Tariffs!$C$9*IF((INDEX(Routes!$L$6:$L$9,$C37)*INDEX(Routes!$X$6:$X$9,$C37)*F37)<=2,(INDEX(Routes!$L$6:$L$9,$C37)*INDEX(Routes!$X$6:$X$9,$C37)*F37),IF((INDEX(Routes!$L$6:$L$9,$C37)*INDEX(Routes!$X$6:$X$9,$C37)*F37)<=3,2+0.9*((INDEX(Routes!$L$6:$L$9,$C37)*INDEX(Routes!$X$6:$X$9,$C37)*F37)-2),IF((INDEX(Routes!$L$6:$L$9,$C37)*INDEX(Routes!$X$6:$X$9,$C37)*F37)<=4,2.9+0.75*((INDEX(Routes!$L$6:$L$9,$C37)*INDEX(Routes!$X$6:$X$9,$C37)*F37)-3),IF((INDEX(Routes!$L$6:$L$9,$C37)*INDEX(Routes!$X$6:$X$9,$C37)*F37)<=5,3.65+0.6*((INDEX(Routes!$L$6:$L$9,$C37)*INDEX(Routes!$X$6:$X$9,$C37)*F37)-4),4.25+0.5*((INDEX(Routes!$L$6:$L$9,$C37)*INDEX(Routes!$X$6:$X$9,$C37)*F37)-5))))) -> 19557.6 | AO37: =LOA_ft*Port_Tariffs!$C$9*IF((INDEX(Routes!$M$6:$M$9,$C37)*INDEX(Routes!$Y$6:$Y$9,$C37)*F37)<=2,(INDEX(Routes!$M$6:$M$9,$C37)*INDEX(Routes!$Y$6:$Y$9,$C37)*F37),IF((INDEX(Routes!$M$6:$M$9,$C37)*INDEX(Routes!$Y$6:$Y$9,$C37)*F37)<=3,2+0.9*((INDEX(Routes!$M$6:$M$9,$C37)*INDEX(Routes!$Y$6:$Y$9,$C37)*F37)-2),IF((INDEX(Routes!$M$6:$M$9,$C37)*INDEX(Routes!$Y$6:$Y$9,$C37)*F37)<=4,2.9+0.75*((INDEX(Routes!$M$6:$M$9,$C37)*INDEX(Routes!$Y$6:$Y$9,$C37)*F37)-3),IF((INDEX(Routes!$M$6:$M$9,$C37)*INDEX(Routes!$Y$6:$Y$9,$C37)*F37)<=5,3.65+0.6*((INDEX(Routes!$M$6:$M$9,$C37)*INDEX(Routes!$Y$6:$Y$9,$C37)*F37)-4),4.25+0.5*((INDEX(Routes!$M$6:$M$9,$C37)*INDEX(Routes!$Y$6:$Y$9,$C37)*F37)-5))))) -> 0
A38: Route 3 | B38: routes | C38: 3 | D38: =Brent -> 82.01 | E38: =FreightMult -> 1 | F38: =PortMult -> 1 | G38: =UtilFH -> 0.85 | H38: =UtilBH -> 0.5 | I38: =Speed -> 13.5 | J38: =PortCostMult -> 1 | K38: =EUA -> 75 | L38: =INDEX(Routes!$E$6:$E$9,$C38) -> 6350 | M38: =INDEX(Routes!$F$6:$F$9,$C38)/L38 -> 0.070866142 | N38: =2*L38*(1+SeaMargin)/(I38*24) -> 41.157407 | O38: =(I38/RefSpeed)^SpeedExp -> 1 | P38: =IF(H38>0,1,0) -> 1 | Q38: =N38/2*O38*(ConsLaden+IF(P38=1,ConsLaden,ConsBallast)) -> 1111.25 | R38: =Q38*(1-M38) -> 1032.5 | S38: =Q38*M38 -> 78.75 | T38: =1+P38 -> 2 | U38: =INDEX(Routes!$L$6:$L$9,$C38)*T38*F38 -> 7 | V38: =INDEX(Routes!$M$6:$M$9,$C38)*T38*F38 -> 8 | W38: =INDEX(Routes!$H$6:$H$9,$C38)*2 -> 2 | X38: =(U38+V38+W38)*ConsPort -> 102 | Y38: =R38*D38*VLSFO_Mult+(S38+X38)*D38*MGO_Mult -> 795786.09 | Z38: =(INDEX(Routes!$N$6:$N$9,$C38)+AN38+MIN(AC38*INDEX(Routes!$T$6:$T$9,$C38),INDEX(Routes!$V$6:$V$9,$C38))+INDEX(Routes!$O$6:$O$9,$C38)+AO38+MIN(AC38*INDEX(Routes!$U$6:$U$9,$C38),INDEX(Routes!$W$6:$W$9,$C38))+IF(P38=1,INDEX(Routes!$N$6:$N$9,$C38)+AN38+MIN(AD38*INDEX(Routes!$T$6:$T$9,$C38),INDEX(Routes!$V$6:$V$9,$C38))+INDEX(Routes!$O$6:$O$9,$C38)+AO38+MIN(AD38*INDEX(Routes!$U$6:$U$9,$C38),INDEX(Routes!$W$6:$W$9,$C38)),0))*J38 -> 231562.21 | AA38: =INDEX(Routes!$R$6:$R$9,$C38)+IF(P38=1,INDEX(Routes!$R$6:$R$9,$C38),INDEX(Routes!$S$6:$S$9,$C38)) -> 752016 | AB38: =((R38*CO2_VLSFO+S38*CO2_MGO)*INDEX(Routes!$I$6:$I$9,$C38)+(U38*INDEX(Routes!$P$6:$P$9,$C38)+V38*INDEX(Routes!$Q$6:$Q$9,$C38))*ConsPort*CO2_MGO)*PhaseIn*K38*FX -> 154150.49 | AC38: =Capacity*G38 -> 30600 | AD38: =Capacity*H38 -> 18000 | AE38: =INDEX(Routes!$J$6:$J$9,$C38)*E38 -> 75 | AF38: =INDEX(Routes!$K$6:$K$9,$C38)*E38 -> 55 | AG38: =AC38*AE38+AD38*AF38 -> 3285000 | AH38: =AG38*Commission -> 82125 | AI38: =Y38+Z38+AA38+AB38+MiscVoy -> 1958514.8 | AJ38: =N38+U38+V38+W38 -> 58.157407 | AK38: =(AG38-AH38-AI38)/AJ38 -> 21396.418 | AL38: =AG38-AH38-AI38-Benchmark*AJ38 -> 197526.88 | AM38: =IF(AC38>0,((Benchmark*AJ38+AI38)/(1-Commission)-AD38*AF38)/AC38,0) -> 68.379357 | AN38: =LOA_ft*Port_Tariffs!$C$9*IF((INDEX(Routes!$L$6:$L$9,$C38)*INDEX(Routes!$X$6:$X$9,$C38)*F38)<=2,(INDEX(Routes!$L$6:$L$9,$C38)*INDEX(Routes!$X$6:$X$9,$C38)*F38),IF((INDEX(Routes!$L$6:$L$9,$C38)*INDEX(Routes!$X$6:$X$9,$C38)*F38)<=3,2+0.9*((INDEX(Routes!$L$6:$L$9,$C38)*INDEX(Routes!$X$6:$X$9,$C38)*F38)-2),IF((INDEX(Routes!$L$6:$L$9,$C38)*INDEX(Routes!$X$6:$X$9,$C38)*F38)<=4,2.9+0.75*((INDEX(Routes!$L$6:$L$9,$C38)*INDEX(Routes!$X$6:$X$9,$C38)*F38)-3),IF((INDEX(Routes!$L$6:$L$9,$C38)*INDEX(Routes!$X$6:$X$9,$C38)*F38)<=5,3.65+0.6*((INDEX(Routes!$L$6:$L$9,$C38)*INDEX(Routes!$X$6:$X$9,$C38)*F38)-4),4.25+0.5*((INDEX(Routes!$L$6:$L$9,$C38)*INDEX(Routes!$X$6:$X$9,$C38)*F38)-5))))) -> 0 | AO38: =LOA_ft*Port_Tariffs!$C$9*IF((INDEX(Routes!$M$6:$M$9,$C38)*INDEX(Routes!$Y$6:$Y$9,$C38)*F38)<=2,(INDEX(Routes!$M$6:$M$9,$C38)*INDEX(Routes!$Y$6:$Y$9,$C38)*F38),IF((INDEX(Routes!$M$6:$M$9,$C38)*INDEX(Routes!$Y$6:$Y$9,$C38)*F38)<=3,2+0.9*((INDEX(Routes!$M$6:$M$9,$C38)*INDEX(Routes!$Y$6:$Y$9,$C38)*F38)-2),IF((INDEX(Routes!$M$6:$M$9,$C38)*INDEX(Routes!$Y$6:$Y$9,$C38)*F38)<=4,2.9+0.75*((INDEX(Routes!$M$6:$M$9,$C38)*INDEX(Routes!$Y$6:$Y$9,$C38)*F38)-3),IF((INDEX(Routes!$M$6:$M$9,$C38)*INDEX(Routes!$Y$6:$Y$9,$C38)*F38)<=5,3.65+0.6*((INDEX(Routes!$M$6:$M$9,$C38)*INDEX(Routes!$Y$6:$Y$9,$C38)*F38)-4),4.25+0.5*((INDEX(Routes!$M$6:$M$9,$C38)*INDEX(Routes!$Y$6:$Y$9,$C38)*F38)-5))))) -> 0
A39: Route 4 | B39: routes | C39: 4 | D39: =Brent -> 82.01 | E39: =FreightMult -> 1 | F39: =PortMult -> 1 | G39: =UtilFH -> 0.85 | H39: =UtilBH -> 0.5 | I39: =Speed -> 13.5 | J39: =PortCostMult -> 1 | K39: =EUA -> 75 | L39: =INDEX(Routes!$E$6:$E$9,$C39) -> 10850 | M39: =INDEX(Routes!$F$6:$F$9,$C39)/L39 -> 0.041474654 | N39: =2*L39*(1+SeaMargin)/(I39*24) -> 70.324074 | O39: =(I39/RefSpeed)^SpeedExp -> 1 | P39: =IF(H39>0,1,0) -> 1 | Q39: =N39/2*O39*(ConsLaden+IF(P39=1,ConsLaden,ConsBallast)) -> 1898.75 | R39: =Q39*(1-M39) -> 1820 | S39: =Q39*M39 -> 78.75 | T39: =1+P39 -> 2 | U39: =INDEX(Routes!$L$6:$L$9,$C39)*T39*F39 -> 7 | V39: =INDEX(Routes!$M$6:$M$9,$C39)*T39*F39 -> 8 | W39: =INDEX(Routes!$H$6:$H$9,$C39)*2 -> 0 | X39: =(U39+V39+W39)*ConsPort -> 90 | Y39: =R39*D39*VLSFO_Mult+(S39+X39)*D39*MGO_Mult -> 1283528.3 | Z39: =(INDEX(Routes!$N$6:$N$9,$C39)+AN39+MIN(AC39*INDEX(Routes!$T$6:$T$9,$C39),INDEX(Routes!$V$6:$V$9,$C39))+INDEX(Routes!$O$6:$O$9,$C39)+AO39+MIN(AC39*INDEX(Routes!$U$6:$U$9,$C39),INDEX(Routes!$W$6:$W$9,$C39))+IF(P39=1,INDEX(Routes!$N$6:$N$9,$C39)+AN39+MIN(AD39*INDEX(Routes!$T$6:$T$9,$C39),INDEX(Routes!$V$6:$V$9,$C39))+INDEX(Routes!$O$6:$O$9,$C39)+AO39+MIN(AD39*INDEX(Routes!$U$6:$U$9,$C39),INDEX(Routes!$W$6:$W$9,$C39)),0))*J39 -> 231562.21 | AA39: =INDEX(Routes!$R$6:$R$9,$C39)+IF(P39=1,INDEX(Routes!$R$6:$R$9,$C39),INDEX(Routes!$S$6:$S$9,$C39)) -> 0 | AB39: =((R39*CO2_VLSFO+S39*CO2_MGO)*INDEX(Routes!$I$6:$I$9,$C39)+(U39*INDEX(Routes!$P$6:$P$9,$C39)+V39*INDEX(Routes!$Q$6:$Q$9,$C39))*ConsPort*CO2_MGO)*PhaseIn*K39*FX -> 255306.83 | AC39: =Capacity*G39 -> 30600 | AD39: =Capacity*H39 -> 18000 | AE39: =INDEX(Routes!$J$6:$J$9,$C39)*E39 -> 75 | AF39: =INDEX(Routes!$K$6:$K$9,$C39)*E39 -> 55 | AG39: =AC39*AE39+AD39*AF39 -> 3285000 | AH39: =AG39*Commission -> 82125 | AI39: =Y39+Z39+AA39+AB39+MiscVoy -> 1795397.3 | AJ39: =N39+U39+V39+W39 -> 85.324074 | AK39: =(AG39-AH39-AI39)/AJ39 -> 16495.669 | AL39: =AG39-AH39-AI39-Benchmark*AJ39 -> -128355.63 | AM39: =IF(AC39>0,((Benchmark*AJ39+AI39)/(1-Commission)-AD39*AF39)/AC39,0) -> 79.302183 | AN39: =LOA_ft*Port_Tariffs!$C$9*IF((INDEX(Routes!$L$6:$L$9,$C39)*INDEX(Routes!$X$6:$X$9,$C39)*F39)<=2,(INDEX(Routes!$L$6:$L$9,$C39)*INDEX(Routes!$X$6:$X$9,$C39)*F39),IF((INDEX(Routes!$L$6:$L$9,$C39)*INDEX(Routes!$X$6:$X$9,$C39)*F39)<=3,2+0.9*((INDEX(Routes!$L$6:$L$9,$C39)*INDEX(Routes!$X$6:$X$9,$C39)*F39)-2),IF((INDEX(Routes!$L$6:$L$9,$C39)*INDEX(Routes!$X$6:$X$9,$C39)*F39)<=4,2.9+0.75*((INDEX(Routes!$L$6:$L$9,$C39)*INDEX(Routes!$X$6:$X$9,$C39)*F39)-3),IF((INDEX(Routes!$L$6:$L$9,$C39)*INDEX(Routes!$X$6:$X$9,$C39)*F39)<=5,3.65+0.6*((INDEX(Routes!$L$6:$L$9,$C39)*INDEX(Routes!$X$6:$X$9,$C39)*F39)-4),4.25+0.5*((INDEX(Routes!$L$6:$L$9,$C39)*INDEX(Routes!$X$6:$X$9,$C39)*F39)-5))))) -> 0 | AO39: =LOA_ft*Port_Tariffs!$C$9*IF((INDEX(Routes!$M$6:$M$9,$C39)*INDEX(Routes!$Y$6:$Y$9,$C39)*F39)<=2,(INDEX(Routes!$M$6:$M$9,$C39)*INDEX(Routes!$Y$6:$Y$9,$C39)*F39),IF((INDEX(Routes!$M$6:$M$9,$C39)*INDEX(Routes!$Y$6:$Y$9,$C39)*F39)<=3,2+0.9*((INDEX(Routes!$M$6:$M$9,$C39)*INDEX(Routes!$Y$6:$Y$9,$C39)*F39)-2),IF((INDEX(Routes!$M$6:$M$9,$C39)*INDEX(Routes!$Y$6:$Y$9,$C39)*F39)<=4,2.9+0.75*((INDEX(Routes!$M$6:$M$9,$C39)*INDEX(Routes!$Y$6:$Y$9,$C39)*F39)-3),IF((INDEX(Routes!$M$6:$M$9,$C39)*INDEX(Routes!$Y$6:$Y$9,$C39)*F39)<=5,3.65+0.6*((INDEX(Routes!$M$6:$M$9,$C39)*INDEX(Routes!$Y$6:$Y$9,$C39)*F39)-4),4.25+0.5*((INDEX(Routes!$M$6:$M$9,$C39)*INDEX(Routes!$Y$6:$Y$9,$C39)*F39)-5))))) -> 0
A41: BREAK-EVEN CASES (Brent x port-time; Brent x fronthaul utilization)
A42: BE port 1.0x Brent 50 | B42: be_port | C42: =Sw_Route -> 1 | D42: 50 | E42: =FreightMult -> 1 | F42: 1 | G42: =UtilFH -> 0.85 | H42: =UtilBH -> 0.5 | I42: =Speed -> 13.5 | J42: =PortCostMult -> 1 | K42: =EUA -> 75 | L42: =INDEX(Routes!$E$6:$E$9,$C42) -> 5000 | M42: =INDEX(Routes!$F$6:$F$9,$C42)/L42 -> 0.13 | N42: =2*L42*(1+SeaMargin)/(I42*24) -> 32.407407 | O42: =(I42/RefSpeed)^SpeedExp -> 1 | P42: =IF(H42>0,1,0) -> 1 | Q42: =N42/2*O42*(ConsLaden+IF(P42=1,ConsLaden,ConsBallast)) -> 875 | R42: =Q42*(1-M42) -> 761.25 | S42: =Q42*M42 -> 113.75 | T42: =1+P42 -> 2 | U42: =INDEX(Routes!$L$6:$L$9,$C42)*T42*F42 -> 10 | V42: =INDEX(Routes!$M$6:$M$9,$C42)*T42*F42 -> 7 | W42: =INDEX(Routes!$H$6:$H$9,$C42)*2 -> 0 | X42: =(U42+V42+W42)*ConsPort -> 102 | Y42: =R42*D42*VLSFO_Mult+(S42+X42)*D42*MGO_Mult -> 397720 | Z42: =(INDEX(Routes!$N$6:$N$9,$C42)+AN42+MIN(AC42*INDEX(Routes!$T$6:$T$9,$C42),INDEX(Routes!$V$6:$V$9,$C42))+INDEX(Routes!$O$6:$O$9,$C42)+AO42+MIN(AC42*INDEX(Routes!$U$6:$U$9,$C42),INDEX(Routes!$W$6:$W$9,$C42))+IF(P42=1,INDEX(Routes!$N$6:$N$9,$C42)+AN42+MIN(AD42*INDEX(Routes!$T$6:$T$9,$C42),INDEX(Routes!$V$6:$V$9,$C42))+INDEX(Routes!$O$6:$O$9,$C42)+AO42+MIN(AD42*INDEX(Routes!$U$6:$U$9,$C42),INDEX(Routes!$W$6:$W$9,$C42)),0))*J42 -> 252304.21 | AA42: =INDEX(Routes!$R$6:$R$9,$C42)+IF(P42=1,INDEX(Routes!$R$6:$R$9,$C42),INDEX(Routes!$S$6:$S$9,$C42)) -> 0 | AB42: =((R42*CO2_VLSFO+S42*CO2_MGO)*INDEX(Routes!$I$6:$I$9,$C42)+(U42*INDEX(Routes!$P$6:$P$9,$C42)+V42*INDEX(Routes!$Q$6:$Q$9,$C42))*ConsPort*CO2_MGO)*PhaseIn*K42*FX -> 123936.41 | AC42: =Capacity*G42 -> 30600 | AD42: =Capacity*H42 -> 18000 | AE42: =INDEX(Routes!$J$6:$J$9,$C42)*E42 -> 52 | AF42: =INDEX(Routes!$K$6:$K$9,$C42)*E42 -> 38 | AG42: =AC42*AE42+AD42*AF42 -> 2275200 | AH42: =AG42*Commission -> 56880 | AI42: =Y42+Z42+AA42+AB42+MiscVoy -> 798960.62 | AJ42: =N42+U42+V42+W42 -> 49.407407 | AK42: =(AG42-AH42-AI42)/AJ42 -> 28727.664 | AL42: =AG42-AH42-AI42-Benchmark*AJ42 -> 530026.05 | AM42: =IF(AC42>0,((Benchmark*AJ42+AI42)/(1-Commission)-AD42*AF42)/AC42,0) -> 34.234756 | AN42: =LOA_ft*Port_Tariffs!$C$9*IF((INDEX(Routes!$L$6:$L$9,$C42)*INDEX(Routes!$X$6:$X$9,$C42)*F42)<=2,(INDEX(Routes!$L$6:$L$9,$C42)*INDEX(Routes!$X$6:$X$9,$C42)*F42),IF((INDEX(Routes!$L$6:$L$9,$C42)*INDEX(Routes!$X$6:$X$9,$C42)*F42)<=3,2+0.9*((INDEX(Routes!$L$6:$L$9,$C42)*INDEX(Routes!$X$6:$X$9,$C42)*F42)-2),IF((INDEX(Routes!$L$6:$L$9,$C42)*INDEX(Routes!$X$6:$X$9,$C42)*F42)<=4,2.9+0.75*((INDEX(Routes!$L$6:$L$9,$C42)*INDEX(Routes!$X$6:$X$9,$C42)*F42)-3),IF((INDEX(Routes!$L$6:$L$9,$C42)*INDEX(Routes!$X$6:$X$9,$C42)*F42)<=5,3.65+0.6*((INDEX(Routes!$L$6:$L$9,$C42)*INDEX(Routes!$X$6:$X$9,$C42)*F42)-4),4.25+0.5*((INDEX(Routes!$L$6:$L$9,$C42)*INDEX(Routes!$X$6:$X$9,$C42)*F42)-5))))) -> 19557.6 | AO42: =LOA_ft*Port_Tariffs!$C$9*IF((INDEX(Routes!$M$6:$M$9,$C42)*INDEX(Routes!$Y$6:$Y$9,$C42)*F42)<=2,(INDEX(Routes!$M$6:$M$9,$C42)*INDEX(Routes!$Y$6:$Y$9,$C42)*F42),IF((INDEX(Routes!$M$6:$M$9,$C42)*INDEX(Routes!$Y$6:$Y$9,$C42)*F42)<=3,2+0.9*((INDEX(Routes!$M$6:$M$9,$C42)*INDEX(Routes!$Y$6:$Y$9,$C42)*F42)-2),IF((INDEX(Routes!$M$6:$M$9,$C42)*INDEX(Routes!$Y$6:$Y$9,$C42)*F42)<=4,2.9+0.75*((INDEX(Routes!$M$6:$M$9,$C42)*INDEX(Routes!$Y$6:$Y$9,$C42)*F42)-3),IF((INDEX(Routes!$M$6:$M$9,$C42)*INDEX(Routes!$Y$6:$Y$9,$C42)*F42)<=5,3.65+0.6*((INDEX(Routes!$M$6:$M$9,$C42)*INDEX(Routes!$Y$6:$Y$9,$C42)*F42)-4),4.25+0.5*((INDEX(Routes!$M$6:$M$9,$C42)*INDEX(Routes!$Y$6:$Y$9,$C42)*F42)-5))))) -> 0
A43: BE port 1.0x Brent 60 | B43: be_port | C43: =Sw_Route -> 1 | D43: 60 | E43: =FreightMult -> 1 | F43: 1 | G43: =UtilFH -> 0.85 | H43: =UtilBH -> 0.5 | I43: =Speed -> 13.5 | J43: =PortCostMult -> 1 | K43: =EUA -> 75 | L43: =INDEX(Routes!$E$6:$E$9,$C43) -> 5000 | M43: =INDEX(Routes!$F$6:$F$9,$C43)/L43 -> 0.13 | N43: =2*L43*(1+SeaMargin)/(I43*24) -> 32.407407 | O43: =(I43/RefSpeed)^SpeedExp -> 1 | P43: =IF(H43>0,1,0) -> 1 | Q43: =N43/2*O43*(ConsLaden+IF(P43=1,ConsLaden,ConsBallast)) -> 875 | R43: =Q43*(1-M43) -> 761.25 | S43: =Q43*M43 -> 113.75 | T43: =1+P43 -> 2 | U43: =INDEX(Routes!$L$6:$L$9,$C43)*T43*F43 -> 10 | V43: =INDEX(Routes!$M$6:$M$9,$C43)*T43*F43 -> 7 | W43: =INDEX(Routes!$H$6:$H$9,$C43)*2 -> 0 | X43: =(U43+V43+W43)*ConsPort -> 102 | Y43: =R43*D43*VLSFO_Mult+(S43+X43)*D43*MGO_Mult -> 477264 | Z43: =(INDEX(Routes!$N$6:$N$9,$C43)+AN43+MIN(AC43*INDEX(Routes!$T$6:$T$9,$C43),INDEX(Routes!$V$6:$V$9,$C43))+INDEX(Routes!$O$6:$O$9,$C43)+AO43+MIN(AC43*INDEX(Routes!$U$6:$U$9,$C43),INDEX(Routes!$W$6:$W$9,$C43))+IF(P43=1,INDEX(Routes!$N$6:$N$9,$C43)+AN43+MIN(AD43*INDEX(Routes!$T$6:$T$9,$C43),INDEX(Routes!$V$6:$V$9,$C43))+INDEX(Routes!$O$6:$O$9,$C43)+AO43+MIN(AD43*INDEX(Routes!$U$6:$U$9,$C43),INDEX(Routes!$W$6:$W$9,$C43)),0))*J43 -> 252304.21 | AA43: =INDEX(Routes!$R$6:$R$9,$C43)+IF(P43=1,INDEX(Routes!$R$6:$R$9,$C43),INDEX(Routes!$S$6:$S$9,$C43)) -> 0 | AB43: =((R43*CO2_VLSFO+S43*CO2_MGO)*INDEX(Routes!$I$6:$I$9,$C43)+(U43*INDEX(Routes!$P$6:$P$9,$C43)+V43*INDEX(Routes!$Q$6:$Q$9,$C43))*ConsPort*CO2_MGO)*PhaseIn*K43*FX -> 123936.41 | AC43: =Capacity*G43 -> 30600 | AD43: =Capacity*H43 -> 18000 | AE43: =INDEX(Routes!$J$6:$J$9,$C43)*E43 -> 52 | AF43: =INDEX(Routes!$K$6:$K$9,$C43)*E43 -> 38 | AG43: =AC43*AE43+AD43*AF43 -> 2275200 | AH43: =AG43*Commission -> 56880 | AI43: =Y43+Z43+AA43+AB43+MiscVoy -> 878504.62 | AJ43: =N43+U43+V43+W43 -> 49.407407 | AK43: =(AG43-AH43-AI43)/AJ43 -> 27117.703 | AL43: =AG43-AH43-AI43-Benchmark*AJ43 -> 450482.05 | AM43: =IF(AC43>0,((Benchmark*AJ43+AI43)/(1-Commission)-AD43*AF43)/AC43,0) -> 36.900887 | AN43: =LOA_ft*Port_Tariffs!$C$9*IF((INDEX(Routes!$L$6:$L$9,$C43)*INDEX(Routes!$X$6:$X$9,$C43)*F43)<=2,(INDEX(Routes!$L$6:$L$9,$C43)*INDEX(Routes!$X$6:$X$9,$C43)*F43),IF((INDEX(Routes!$L$6:$L$9,$C43)*INDEX(Routes!$X$6:$X$9,$C43)*F43)<=3,2+0.9*((INDEX(Routes!$L$6:$L$9,$C43)*INDEX(Routes!$X$6:$X$9,$C43)*F43)-2),IF((INDEX(Routes!$L$6:$L$9,$C43)*INDEX(Routes!$X$6:$X$9,$C43)*F43)<=4,2.9+0.75*((INDEX(Routes!$L$6:$L$9,$C43)*INDEX(Routes!$X$6:$X$9,$C43)*F43)-3),IF((INDEX(Routes!$L$6:$L$9,$C43)*INDEX(Routes!$X$6:$X$9,$C43)*F43)<=5,3.65+0.6*((INDEX(Routes!$L$6:$L$9,$C43)*INDEX(Routes!$X$6:$X$9,$C43)*F43)-4),4.25+0.5*((INDEX(Routes!$L$6:$L$9,$C43)*INDEX(Routes!$X$6:$X$9,$C43)*F43)-5))))) -> 19557.6 | AO43: =LOA_ft*Port_Tariffs!$C$9*IF((INDEX(Routes!$M$6:$M$9,$C43)*INDEX(Routes!$Y$6:$Y$9,$C43)*F43)<=2,(INDEX(Routes!$M$6:$M$9,$C43)*INDEX(Routes!$Y$6:$Y$9,$C43)*F43),IF((INDEX(Routes!$M$6:$M$9,$C43)*INDEX(Routes!$Y$6:$Y$9,$C43)*F43)<=3,2+0.9*((INDEX(Routes!$M$6:$M$9,$C43)*INDEX(Routes!$Y$6:$Y$9,$C43)*F43)-2),IF((INDEX(Routes!$M$6:$M$9,$C43)*INDEX(Routes!$Y$6:$Y$9,$C43)*F43)<=4,2.9+0.75*((INDEX(Routes!$M$6:$M$9,$C43)*INDEX(Routes!$Y$6:$Y$9,$C43)*F43)-3),IF((INDEX(Routes!$M$6:$M$9,$C43)*INDEX(Routes!$Y$6:$Y$9,$C43)*F43)<=5,3.65+0.6*((INDEX(Routes!$M$6:$M$9,$C43)*INDEX(Routes!$Y$6:$Y$9,$C43)*F43)-4),4.25+0.5*((INDEX(Routes!$M$6:$M$9,$C43)*INDEX(Routes!$Y$6:$Y$9,$C43)*F43)-5))))) -> 0
A44: BE port 1.0x Brent 70 | B44: be_port | C44: =Sw_Route -> 1 | D44: 70 | E44: =FreightMult -> 1 | F44: 1 | G44: =UtilFH -> 0.85 | H44: =UtilBH -> 0.5 | I44: =Speed -> 13.5 | J44: =PortCostMult -> 1 | K44: =EUA -> 75 | L44: =INDEX(Routes!$E$6:$E$9,$C44) -> 5000 | M44: =INDEX(Routes!$F$6:$F$9,$C44)/L44 -> 0.13 | N44: =2*L44*(1+SeaMargin)/(I44*24) -> 32.407407 | O44: =(I44/RefSpeed)^SpeedExp -> 1 | P44: =IF(H44>0,1,0) -> 1 | Q44: =N44/2*O44*(ConsLaden+IF(P44=1,ConsLaden,ConsBallast)) -> 875 | R44: =Q44*(1-M44) -> 761.25 | S44: =Q44*M44 -> 113.75 | T44: =1+P44 -> 2 | U44: =INDEX(Routes!$L$6:$L$9,$C44)*T44*F44 -> 10 | V44: =INDEX(Routes!$M$6:$M$9,$C44)*T44*F44 -> 7 | W44: =INDEX(Routes!$H$6:$H$9,$C44)*2 -> 0 | X44: =(U44+V44+W44)*ConsPort -> 102 | Y44: =R44*D44*VLSFO_Mult+(S44+X44)*D44*MGO_Mult -> 556808 | Z44: =(INDEX(Routes!$N$6:$N$9,$C44)+AN44+MIN(AC44*INDEX(Routes!$T$6:$T$9,$C44),INDEX(Routes!$V$6:$V$9,$C44))+INDEX(Routes!$O$6:$O$9,$C44)+AO44+MIN(AC44*INDEX(Routes!$U$6:$U$9,$C44),INDEX(Routes!$W$6:$W$9,$C44))+IF(P44=1,INDEX(Routes!$N$6:$N$9,$C44)+AN44+MIN(AD44*INDEX(Routes!$T$6:$T$9,$C44),INDEX(Routes!$V$6:$V$9,$C44))+INDEX(Routes!$O$6:$O$9,$C44)+AO44+MIN(AD44*INDEX(Routes!$U$6:$U$9,$C44),INDEX(Routes!$W$6:$W$9,$C44)),0))*J44 -> 252304.21 | AA44: =INDEX(Routes!$R$6:$R$9,$C44)+IF(P44=1,INDEX(Routes!$R$6:$R$9,$C44),INDEX(Routes!$S$6:$S$9,$C44)) -> 0 | AB44: =((R44*CO2_VLSFO+S44*CO2_MGO)*INDEX(Routes!$I$6:$I$9,$C44)+(U44*INDEX(Routes!$P$6:$P$9,$C44)+V44*INDEX(Routes!$Q$6:$Q$9,$C44))*ConsPort*CO2_MGO)*PhaseIn*K44*FX -> 123936.41 | AC44: =Capacity*G44 -> 30600 | AD44: =Capacity*H44 -> 18000 | AE44: =INDEX(Routes!$J$6:$J$9,$C44)*E44 -> 52 | AF44: =INDEX(Routes!$K$6:$K$9,$C44)*E44 -> 38 | AG44: =AC44*AE44+AD44*AF44 -> 2275200 | AH44: =AG44*Commission -> 56880 | AI44: =Y44+Z44+AA44+AB44+MiscVoy -> 958048.62 | AJ44: =N44+U44+V44+W44 -> 49.407407 | AK44: =(AG44-AH44-AI44)/AJ44 -> 25507.742 | AL44: =AG44-AH44-AI44-Benchmark*AJ44 -> 370938.05 | AM44: =IF(AC44>0,((Benchmark*AJ44+AI44)/(1-Commission)-AD44*AF44)/AC44,0) -> 39.567017 | AN44: =LOA_ft*Port_Tariffs!$C$9*IF((INDEX(Routes!$L$6:$L$9,$C44)*INDEX(Routes!$X$6:$X$9,$C44)*F44)<=2,(INDEX(Routes!$L$6:$L$9,$C44)*INDEX(Routes!$X$6:$X$9,$C44)*F44),IF((INDEX(Routes!$L$6:$L$9,$C44)*INDEX(Routes!$X$6:$X$9,$C44)*F44)<=3,2+0.9*((INDEX(Routes!$L$6:$L$9,$C44)*INDEX(Routes!$X$6:$X$9,$C44)*F44)-2),IF((INDEX(Routes!$L$6:$L$9,$C44)*INDEX(Routes!$X$6:$X$9,$C44)*F44)<=4,2.9+0.75*((INDEX(Routes!$L$6:$L$9,$C44)*INDEX(Routes!$X$6:$X$9,$C44)*F44)-3),IF((INDEX(Routes!$L$6:$L$9,$C44)*INDEX(Routes!$X$6:$X$9,$C44)*F44)<=5,3.65+0.6*((INDEX(Routes!$L$6:$L$9,$C44)*INDEX(Routes!$X$6:$X$9,$C44)*F44)-4),4.25+0.5*((INDEX(Routes!$L$6:$L$9,$C44)*INDEX(Routes!$X$6:$X$9,$C44)*F44)-5))))) -> 19557.6 | AO44: =LOA_ft*Port_Tariffs!$C$9*IF((INDEX(Routes!$M$6:$M$9,$C44)*INDEX(Routes!$Y$6:$Y$9,$C44)*F44)<=2,(INDEX(Routes!$M$6:$M$9,$C44)*INDEX(Routes!$Y$6:$Y$9,$C44)*F44),IF((INDEX(Routes!$M$6:$M$9,$C44)*INDEX(Routes!$Y$6:$Y$9,$C44)*F44)<=3,2+0.9*((INDEX(Routes!$M$6:$M$9,$C44)*INDEX(Routes!$Y$6:$Y$9,$C44)*F44)-2),IF((INDEX(Routes!$M$6:$M$9,$C44)*INDEX(Routes!$Y$6:$Y$9,$C44)*F44)<=4,2.9+0.75*((INDEX(Routes!$M$6:$M$9,$C44)*INDEX(Routes!$Y$6:$Y$9,$C44)*F44)-3),IF((INDEX(Routes!$M$6:$M$9,$C44)*INDEX(Routes!$Y$6:$Y$9,$C44)*F44)<=5,3.65+0.6*((INDEX(Routes!$M$6:$M$9,$C44)*INDEX(Routes!$Y$6:$Y$9,$C44)*F44)-4),4.25+0.5*((INDEX(Routes!$M$6:$M$9,$C44)*INDEX(Routes!$Y$6:$Y$9,$C44)*F44)-5))))) -> 0
A45: BE port 1.0x Brent 80 | B45: be_port | C45: =Sw_Route -> 1 | D45: 80 | E45: =FreightMult -> 1 | F45: 1 | G45: =UtilFH -> 0.85 | H45: =UtilBH -> 0.5 | I45: =Speed -> 13.5 | J45: =PortCostMult -> 1 | K45: =EUA -> 75 | L45: =INDEX(Routes!$E$6:$E$9,$C45) -> 5000 | M45: =INDEX(Routes!$F$6:$F$9,$C45)/L45 -> 0.13 | N45: =2*L45*(1+SeaMargin)/(I45*24) -> 32.407407 | O45: =(I45/RefSpeed)^SpeedExp -> 1 | P45: =IF(H45>0,1,0) -> 1 | Q45: =N45/2*O45*(ConsLaden+IF(P45=1,ConsLaden,ConsBallast)) -> 875 | R45: =Q45*(1-M45) -> 761.25 | S45: =Q45*M45 -> 113.75 | T45: =1+P45 -> 2 | U45: =INDEX(Routes!$L$6:$L$9,$C45)*T45*F45 -> 10 | V45: =INDEX(Routes!$M$6:$M$9,$C45)*T45*F45 -> 7 | W45: =INDEX(Routes!$H$6:$H$9,$C45)*2 -> 0 | X45: =(U45+V45+W45)*ConsPort -> 102 | Y45: =R45*D45*VLSFO_Mult+(S45+X45)*D45*MGO_Mult -> 636352 | Z45: =(INDEX(Routes!$N$6:$N$9,$C45)+AN45+MIN(AC45*INDEX(Routes!$T$6:$T$9,$C45),INDEX(Routes!$V$6:$V$9,$C45))+INDEX(Routes!$O$6:$O$9,$C45)+AO45+MIN(AC45*INDEX(Routes!$U$6:$U$9,$C45),INDEX(Routes!$W$6:$W$9,$C45))+IF(P45=1,INDEX(Routes!$N$6:$N$9,$C45)+AN45+MIN(AD45*INDEX(Routes!$T$6:$T$9,$C45),INDEX(Routes!$V$6:$V$9,$C45))+INDEX(Routes!$O$6:$O$9,$C45)+AO45+MIN(AD45*INDEX(Routes!$U$6:$U$9,$C45),INDEX(Routes!$W$6:$W$9,$C45)),0))*J45 -> 252304.21 | AA45: =INDEX(Routes!$R$6:$R$9,$C45)+IF(P45=1,INDEX(Routes!$R$6:$R$9,$C45),INDEX(Routes!$S$6:$S$9,$C45)) -> 0 | AB45: =((R45*CO2_VLSFO+S45*CO2_MGO)*INDEX(Routes!$I$6:$I$9,$C45)+(U45*INDEX(Routes!$P$6:$P$9,$C45)+V45*INDEX(Routes!$Q$6:$Q$9,$C45))*ConsPort*CO2_MGO)*PhaseIn*K45*FX -> 123936.41 | AC45: =Capacity*G45 -> 30600 | AD45: =Capacity*H45 -> 18000 | AE45: =INDEX(Routes!$J$6:$J$9,$C45)*E45 -> 52 | AF45: =INDEX(Routes!$K$6:$K$9,$C45)*E45 -> 38 | AG45: =AC45*AE45+AD45*AF45 -> 2275200 | AH45: =AG45*Commission -> 56880 | AI45: =Y45+Z45+AA45+AB45+MiscVoy -> 1037592.6 | AJ45: =N45+U45+V45+W45 -> 49.407407 | AK45: =(AG45-AH45-AI45)/AJ45 -> 23897.781 | AL45: =AG45-AH45-AI45-Benchmark*AJ45 -> 291394.05 | AM45: =IF(AC45>0,((Benchmark*AJ45+AI45)/(1-Commission)-AD45*AF45)/AC45,0) -> 42.233147 | AN45: =LOA_ft*Port_Tariffs!$C$9*IF((INDEX(Routes!$L$6:$L$9,$C45)*INDEX(Routes!$X$6:$X$9,$C45)*F45)<=2,(INDEX(Routes!$L$6:$L$9,$C45)*INDEX(Routes!$X$6:$X$9,$C45)*F45),IF((INDEX(Routes!$L$6:$L$9,$C45)*INDEX(Routes!$X$6:$X$9,$C45)*F45)<=3,2+0.9*((INDEX(Routes!$L$6:$L$9,$C45)*INDEX(Routes!$X$6:$X$9,$C45)*F45)-2),IF((INDEX(Routes!$L$6:$L$9,$C45)*INDEX(Routes!$X$6:$X$9,$C45)*F45)<=4,2.9+0.75*((INDEX(Routes!$L$6:$L$9,$C45)*INDEX(Routes!$X$6:$X$9,$C45)*F45)-3),IF((INDEX(Routes!$L$6:$L$9,$C45)*INDEX(Routes!$X$6:$X$9,$C45)*F45)<=5,3.65+0.6*((INDEX(Routes!$L$6:$L$9,$C45)*INDEX(Routes!$X$6:$X$9,$C45)*F45)-4),4.25+0.5*((INDEX(Routes!$L$6:$L$9,$C45)*INDEX(Routes!$X$6:$X$9,$C45)*F45)-5))))) -> 19557.6 | AO45: =LOA_ft*Port_Tariffs!$C$9*IF((INDEX(Routes!$M$6:$M$9,$C45)*INDEX(Routes!$Y$6:$Y$9,$C45)*F45)<=2,(INDEX(Routes!$M$6:$M$9,$C45)*INDEX(Routes!$Y$6:$Y$9,$C45)*F45),IF((INDEX(Routes!$M$6:$M$9,$C45)*INDEX(Routes!$Y$6:$Y$9,$C45)*F45)<=3,2+0.9*((INDEX(Routes!$M$6:$M$9,$C45)*INDEX(Routes!$Y$6:$Y$9,$C45)*F45)-2),IF((INDEX(Routes!$M$6:$M$9,$C45)*INDEX(Routes!$Y$6:$Y$9,$C45)*F45)<=4,2.9+0.75*((INDEX(Routes!$M$6:$M$9,$C45)*INDEX(Routes!$Y$6:$Y$9,$C45)*F45)-3),IF((INDEX(Routes!$M$6:$M$9,$C45)*INDEX(Routes!$Y$6:$Y$9,$C45)*F45)<=5,3.65+0.6*((INDEX(Routes!$M$6:$M$9,$C45)*INDEX(Routes!$Y$6:$Y$9,$C45)*F45)-4),4.25+0.5*((INDEX(Routes!$M$6:$M$9,$C45)*INDEX(Routes!$Y$6:$Y$9,$C45)*F45)-5))))) -> 0
A46: BE port 1.0x Brent 90 | B46: be_port | C46: =Sw_Route -> 1 | D46: 90 | E46: =FreightMult -> 1 | F46: 1 | G46: =UtilFH -> 0.85 | H46: =UtilBH -> 0.5 | I46: =Speed -> 13.5 | J46: =PortCostMult -> 1 | K46: =EUA -> 75 | L46: =INDEX(Routes!$E$6:$E$9,$C46) -> 5000 | M46: =INDEX(Routes!$F$6:$F$9,$C46)/L46 -> 0.13 | N46: =2*L46*(1+SeaMargin)/(I46*24) -> 32.407407 | O46: =(I46/RefSpeed)^SpeedExp -> 1 | P46: =IF(H46>0,1,0) -> 1 | Q46: =N46/2*O46*(ConsLaden+IF(P46=1,ConsLaden,ConsBallast)) -> 875 | R46: =Q46*(1-M46) -> 761.25 | S46: =Q46*M46 -> 113.75 | T46: =1+P46 -> 2 | U46: =INDEX(Routes!$L$6:$L$9,$C46)*T46*F46 -> 10 | V46: =INDEX(Routes!$M$6:$M$9,$C46)*T46*F46 -> 7 | W46: =INDEX(Routes!$H$6:$H$9,$C46)*2 -> 0 | X46: =(U46+V46+W46)*ConsPort -> 102 | Y46: =R46*D46*VLSFO_Mult+(S46+X46)*D46*MGO_Mult -> 715896 | Z46: =(INDEX(Routes!$N$6:$N$9,$C46)+AN46+MIN(AC46*INDEX(Routes!$T$6:$T$9,$C46),INDEX(Routes!$V$6:$V$9,$C46))+INDEX(Routes!$O$6:$O$9,$C46)+AO46+MIN(AC46*INDEX(Routes!$U$6:$U$9,$C46),INDEX(Routes!$W$6:$W$9,$C46))+IF(P46=1,INDEX(Routes!$N$6:$N$9,$C46)+AN46+MIN(AD46*INDEX(Routes!$T$6:$T$9,$C46),INDEX(Routes!$V$6:$V$9,$C46))+INDEX(Routes!$O$6:$O$9,$C46)+AO46+MIN(AD46*INDEX(Routes!$U$6:$U$9,$C46),INDEX(Routes!$W$6:$W$9,$C46)),0))*J46 -> 252304.21 | AA46: =INDEX(Routes!$R$6:$R$9,$C46)+IF(P46=1,INDEX(Routes!$R$6:$R$9,$C46),INDEX(Routes!$S$6:$S$9,$C46)) -> 0 | AB46: =((R46*CO2_VLSFO+S46*CO2_MGO)*INDEX(Routes!$I$6:$I$9,$C46)+(U46*INDEX(Routes!$P$6:$P$9,$C46)+V46*INDEX(Routes!$Q$6:$Q$9,$C46))*ConsPort*CO2_MGO)*PhaseIn*K46*FX -> 123936.41 | AC46: =Capacity*G46 -> 30600 | AD46: =Capacity*H46 -> 18000 | AE46: =INDEX(Routes!$J$6:$J$9,$C46)*E46 -> 52 | AF46: =INDEX(Routes!$K$6:$K$9,$C46)*E46 -> 38 | AG46: =AC46*AE46+AD46*AF46 -> 2275200 | AH46: =AG46*Commission -> 56880 | AI46: =Y46+Z46+AA46+AB46+MiscVoy -> 1117136.6 | AJ46: =N46+U46+V46+W46 -> 49.407407 | AK46: =(AG46-AH46-AI46)/AJ46 -> 22287.82 | AL46: =AG46-AH46-AI46-Benchmark*AJ46 -> 211850.05 | AM46: =IF(AC46>0,((Benchmark*AJ46+AI46)/(1-Commission)-AD46*AF46)/AC46,0) -> 44.899278 | AN46: =LOA_ft*Port_Tariffs!$C$9*IF((INDEX(Routes!$L$6:$L$9,$C46)*INDEX(Routes!$X$6:$X$9,$C46)*F46)<=2,(INDEX(Routes!$L$6:$L$9,$C46)*INDEX(Routes!$X$6:$X$9,$C46)*F46),IF((INDEX(Routes!$L$6:$L$9,$C46)*INDEX(Routes!$X$6:$X$9,$C46)*F46)<=3,2+0.9*((INDEX(Routes!$L$6:$L$9,$C46)*INDEX(Routes!$X$6:$X$9,$C46)*F46)-2),IF((INDEX(Routes!$L$6:$L$9,$C46)*INDEX(Routes!$X$6:$X$9,$C46)*F46)<=4,2.9+0.75*((INDEX(Routes!$L$6:$L$9,$C46)*INDEX(Routes!$X$6:$X$9,$C46)*F46)-3),IF((INDEX(Routes!$L$6:$L$9,$C46)*INDEX(Routes!$X$6:$X$9,$C46)*F46)<=5,3.65+0.6*((INDEX(Routes!$L$6:$L$9,$C46)*INDEX(Routes!$X$6:$X$9,$C46)*F46)-4),4.25+0.5*((INDEX(Routes!$L$6:$L$9,$C46)*INDEX(Routes!$X$6:$X$9,$C46)*F46)-5))))) -> 19557.6 | AO46: =LOA_ft*Port_Tariffs!$C$9*IF((INDEX(Routes!$M$6:$M$9,$C46)*INDEX(Routes!$Y$6:$Y$9,$C46)*F46)<=2,(INDEX(Routes!$M$6:$M$9,$C46)*INDEX(Routes!$Y$6:$Y$9,$C46)*F46),IF((INDEX(Routes!$M$6:$M$9,$C46)*INDEX(Routes!$Y$6:$Y$9,$C46)*F46)<=3,2+0.9*((INDEX(Routes!$M$6:$M$9,$C46)*INDEX(Routes!$Y$6:$Y$9,$C46)*F46)-2),IF((INDEX(Routes!$M$6:$M$9,$C46)*INDEX(Routes!$Y$6:$Y$9,$C46)*F46)<=4,2.9+0.75*((INDEX(Routes!$M$6:$M$9,$C46)*INDEX(Routes!$Y$6:$Y$9,$C46)*F46)-3),IF((INDEX(Routes!$M$6:$M$9,$C46)*INDEX(Routes!$Y$6:$Y$9,$C46)*F46)<=5,3.65+0.6*((INDEX(Routes!$M$6:$M$9,$C46)*INDEX(Routes!$Y$6:$Y$9,$C46)*F46)-4),4.25+0.5*((INDEX(Routes!$M$6:$M$9,$C46)*INDEX(Routes!$Y$6:$Y$9,$C46)*F46)-5))))) -> 0
A47: BE port 1.0x Brent 100 | B47: be_port | C47: =Sw_Route -> 1 | D47: 100 | E47: =FreightMult -> 1 | F47: 1 | G47: =UtilFH -> 0.85 | H47: =UtilBH -> 0.5 | I47: =Speed -> 13.5 | J47: =PortCostMult -> 1 | K47: =EUA -> 75 | L47: =INDEX(Routes!$E$6:$E$9,$C47) -> 5000 | M47: =INDEX(Routes!$F$6:$F$9,$C47)/L47 -> 0.13 | N47: =2*L47*(1+SeaMargin)/(I47*24) -> 32.407407 | O47: =(I47/RefSpeed)^SpeedExp -> 1 | P47: =IF(H47>0,1,0) -> 1 | Q47: =N47/2*O47*(ConsLaden+IF(P47=1,ConsLaden,ConsBallast)) -> 875 | R47: =Q47*(1-M47) -> 761.25 | S47: =Q47*M47 -> 113.75 | T47: =1+P47 -> 2 | U47: =INDEX(Routes!$L$6:$L$9,$C47)*T47*F47 -> 10 | V47: =INDEX(Routes!$M$6:$M$9,$C47)*T47*F47 -> 7 | W47: =INDEX(Routes!$H$6:$H$9,$C47)*2 -> 0 | X47: =(U47+V47+W47)*ConsPort -> 102 | Y47: =R47*D47*VLSFO_Mult+(S47+X47)*D47*MGO_Mult -> 795440 | Z47: =(INDEX(Routes!$N$6:$N$9,$C47)+AN47+MIN(AC47*INDEX(Routes!$T$6:$T$9,$C47),INDEX(Routes!$V$6:$V$9,$C47))+INDEX(Routes!$O$6:$O$9,$C47)+AO47+MIN(AC47*INDEX(Routes!$U$6:$U$9,$C47),INDEX(Routes!$W$6:$W$9,$C47))+IF(P47=1,INDEX(Routes!$N$6:$N$9,$C47)+AN47+MIN(AD47*INDEX(Routes!$T$6:$T$9,$C47),INDEX(Routes!$V$6:$V$9,$C47))+INDEX(Routes!$O$6:$O$9,$C47)+AO47+MIN(AD47*INDEX(Routes!$U$6:$U$9,$C47),INDEX(Routes!$W$6:$W$9,$C47)),0))*J47 -> 252304.21 | AA47: =INDEX(Routes!$R$6:$R$9,$C47)+IF(P47=1,INDEX(Routes!$R$6:$R$9,$C47),INDEX(Routes!$S$6:$S$9,$C47)) -> 0 | AB47: =((R47*CO2_VLSFO+S47*CO2_MGO)*INDEX(Routes!$I$6:$I$9,$C47)+(U47*INDEX(Routes!$P$6:$P$9,$C47)+V47*INDEX(Routes!$Q$6:$Q$9,$C47))*ConsPort*CO2_MGO)*PhaseIn*K47*FX -> 123936.41 | AC47: =Capacity*G47 -> 30600 | AD47: =Capacity*H47 -> 18000 | AE47: =INDEX(Routes!$J$6:$J$9,$C47)*E47 -> 52 | AF47: =INDEX(Routes!$K$6:$K$9,$C47)*E47 -> 38 | AG47: =AC47*AE47+AD47*AF47 -> 2275200 | AH47: =AG47*Commission -> 56880 | AI47: =Y47+Z47+AA47+AB47+MiscVoy -> 1196680.6 | AJ47: =N47+U47+V47+W47 -> 49.407407 | AK47: =(AG47-AH47-AI47)/AJ47 -> 20677.859 | AL47: =AG47-AH47-AI47-Benchmark*AJ47 -> 132306.05 | AM47: =IF(AC47>0,((Benchmark*AJ47+AI47)/(1-Commission)-AD47*AF47)/AC47,0) -> 47.565408 | AN47: =LOA_ft*Port_Tariffs!$C$9*IF((INDEX(Routes!$L$6:$L$9,$C47)*INDEX(Routes!$X$6:$X$9,$C47)*F47)<=2,(INDEX(Routes!$L$6:$L$9,$C47)*INDEX(Routes!$X$6:$X$9,$C47)*F47),IF((INDEX(Routes!$L$6:$L$9,$C47)*INDEX(Routes!$X$6:$X$9,$C47)*F47)<=3,2+0.9*((INDEX(Routes!$L$6:$L$9,$C47)*INDEX(Routes!$X$6:$X$9,$C47)*F47)-2),IF((INDEX(Routes!$L$6:$L$9,$C47)*INDEX(Routes!$X$6:$X$9,$C47)*F47)<=4,2.9+0.75*((INDEX(Routes!$L$6:$L$9,$C47)*INDEX(Routes!$X$6:$X$9,$C47)*F47)-3),IF((INDEX(Routes!$L$6:$L$9,$C47)*INDEX(Routes!$X$6:$X$9,$C47)*F47)<=5,3.65+0.6*((INDEX(Routes!$L$6:$L$9,$C47)*INDEX(Routes!$X$6:$X$9,$C47)*F47)-4),4.25+0.5*((INDEX(Routes!$L$6:$L$9,$C47)*INDEX(Routes!$X$6:$X$9,$C47)*F47)-5))))) -> 19557.6 | AO47: =LOA_ft*Port_Tariffs!$C$9*IF((INDEX(Routes!$M$6:$M$9,$C47)*INDEX(Routes!$Y$6:$Y$9,$C47)*F47)<=2,(INDEX(Routes!$M$6:$M$9,$C47)*INDEX(Routes!$Y$6:$Y$9,$C47)*F47),IF((INDEX(Routes!$M$6:$M$9,$C47)*INDEX(Routes!$Y$6:$Y$9,$C47)*F47)<=3,2+0.9*((INDEX(Routes!$M$6:$M$9,$C47)*INDEX(Routes!$Y$6:$Y$9,$C47)*F47)-2),IF((INDEX(Routes!$M$6:$M$9,$C47)*INDEX(Routes!$Y$6:$Y$9,$C47)*F47)<=4,2.9+0.75*((INDEX(Routes!$M$6:$M$9,$C47)*INDEX(Routes!$Y$6:$Y$9,$C47)*F47)-3),IF((INDEX(Routes!$M$6:$M$9,$C47)*INDEX(Routes!$Y$6:$Y$9,$C47)*F47)<=5,3.65+0.6*((INDEX(Routes!$M$6:$M$9,$C47)*INDEX(Routes!$Y$6:$Y$9,$C47)*F47)-4),4.25+0.5*((INDEX(Routes!$M$6:$M$9,$C47)*INDEX(Routes!$Y$6:$Y$9,$C47)*F47)-5))))) -> 0
A48: BE port 1.0x Brent 110 | B48: be_port | C48: =Sw_Route -> 1 | D48: 110 | E48: =FreightMult -> 1 | F48: 1 | G48: =UtilFH -> 0.85 | H48: =UtilBH -> 0.5 | I48: =Speed -> 13.5 | J48: =PortCostMult -> 1 | K48: =EUA -> 75 | L48: =INDEX(Routes!$E$6:$E$9,$C48) -> 5000 | M48: =INDEX(Routes!$F$6:$F$9,$C48)/L48 -> 0.13 | N48: =2*L48*(1+SeaMargin)/(I48*24) -> 32.407407 | O48: =(I48/RefSpeed)^SpeedExp -> 1 | P48: =IF(H48>0,1,0) -> 1 | Q48: =N48/2*O48*(ConsLaden+IF(P48=1,ConsLaden,ConsBallast)) -> 875 | R48: =Q48*(1-M48) -> 761.25 | S48: =Q48*M48 -> 113.75 | T48: =1+P48 -> 2 | U48: =INDEX(Routes!$L$6:$L$9,$C48)*T48*F48 -> 10 | V48: =INDEX(Routes!$M$6:$M$9,$C48)*T48*F48 -> 7 | W48: =INDEX(Routes!$H$6:$H$9,$C48)*2 -> 0 | X48: =(U48+V48+W48)*ConsPort -> 102 | Y48: =R48*D48*VLSFO_Mult+(S48+X48)*D48*MGO_Mult -> 874984 | Z48: =(INDEX(Routes!$N$6:$N$9,$C48)+AN48+MIN(AC48*INDEX(Routes!$T$6:$T$9,$C48),INDEX(Routes!$V$6:$V$9,$C48))+INDEX(Routes!$O$6:$O$9,$C48)+AO48+MIN(AC48*INDEX(Routes!$U$6:$U$9,$C48),INDEX(Routes!$W$6:$W$9,$C48))+IF(P48=1,INDEX(Routes!$N$6:$N$9,$C48)+AN48+MIN(AD48*INDEX(Routes!$T$6:$T$9,$C48),INDEX(Routes!$V$6:$V$9,$C48))+INDEX(Routes!$O$6:$O$9,$C48)+AO48+MIN(AD48*INDEX(Routes!$U$6:$U$9,$C48),INDEX(Routes!$W$6:$W$9,$C48)),0))*J48 -> 252304.21 | AA48: =INDEX(Routes!$R$6:$R$9,$C48)+IF(P48=1,INDEX(Routes!$R$6:$R$9,$C48),INDEX(Routes!$S$6:$S$9,$C48)) -> 0 | AB48: =((R48*CO2_VLSFO+S48*CO2_MGO)*INDEX(Routes!$I$6:$I$9,$C48)+(U48*INDEX(Routes!$P$6:$P$9,$C48)+V48*INDEX(Routes!$Q$6:$Q$9,$C48))*ConsPort*CO2_MGO)*PhaseIn*K48*FX -> 123936.41 | AC48: =Capacity*G48 -> 30600 | AD48: =Capacity*H48 -> 18000 | AE48: =INDEX(Routes!$J$6:$J$9,$C48)*E48 -> 52 | AF48: =INDEX(Routes!$K$6:$K$9,$C48)*E48 -> 38 | AG48: =AC48*AE48+AD48*AF48 -> 2275200 | AH48: =AG48*Commission -> 56880 | AI48: =Y48+Z48+AA48+AB48+MiscVoy -> 1276224.6 | AJ48: =N48+U48+V48+W48 -> 49.407407 | AK48: =(AG48-AH48-AI48)/AJ48 -> 19067.898 | AL48: =AG48-AH48-AI48-Benchmark*AJ48 -> 52762.048 | AM48: =IF(AC48>0,((Benchmark*AJ48+AI48)/(1-Commission)-AD48*AF48)/AC48,0) -> 50.231539 | AN48: =LOA_ft*Port_Tariffs!$C$9*IF((INDEX(Routes!$L$6:$L$9,$C48)*INDEX(Routes!$X$6:$X$9,$C48)*F48)<=2,(INDEX(Routes!$L$6:$L$9,$C48)*INDEX(Routes!$X$6:$X$9,$C48)*F48),IF((INDEX(Routes!$L$6:$L$9,$C48)*INDEX(Routes!$X$6:$X$9,$C48)*F48)<=3,2+0.9*((INDEX(Routes!$L$6:$L$9,$C48)*INDEX(Routes!$X$6:$X$9,$C48)*F48)-2),IF((INDEX(Routes!$L$6:$L$9,$C48)*INDEX(Routes!$X$6:$X$9,$C48)*F48)<=4,2.9+0.75*((INDEX(Routes!$L$6:$L$9,$C48)*INDEX(Routes!$X$6:$X$9,$C48)*F48)-3),IF((INDEX(Routes!$L$6:$L$9,$C48)*INDEX(Routes!$X$6:$X$9,$C48)*F48)<=5,3.65+0.6*((INDEX(Routes!$L$6:$L$9,$C48)*INDEX(Routes!$X$6:$X$9,$C48)*F48)-4),4.25+0.5*((INDEX(Routes!$L$6:$L$9,$C48)*INDEX(Routes!$X$6:$X$9,$C48)*F48)-5))))) -> 19557.6 | AO48: =LOA_ft*Port_Tariffs!$C$9*IF((INDEX(Routes!$M$6:$M$9,$C48)*INDEX(Routes!$Y$6:$Y$9,$C48)*F48)<=2,(INDEX(Routes!$M$6:$M$9,$C48)*INDEX(Routes!$Y$6:$Y$9,$C48)*F48),IF((INDEX(Routes!$M$6:$M$9,$C48)*INDEX(Routes!$Y$6:$Y$9,$C48)*F48)<=3,2+0.9*((INDEX(Routes!$M$6:$M$9,$C48)*INDEX(Routes!$Y$6:$Y$9,$C48)*F48)-2),IF((INDEX(Routes!$M$6:$M$9,$C48)*INDEX(Routes!$Y$6:$Y$9,$C48)*F48)<=4,2.9+0.75*((INDEX(Routes!$M$6:$M$9,$C48)*INDEX(Routes!$Y$6:$Y$9,$C48)*F48)-3),IF((INDEX(Routes!$M$6:$M$9,$C48)*INDEX(Routes!$Y$6:$Y$9,$C48)*F48)<=5,3.65+0.6*((INDEX(Routes!$M$6:$M$9,$C48)*INDEX(Routes!$Y$6:$Y$9,$C48)*F48)-4),4.25+0.5*((INDEX(Routes!$M$6:$M$9,$C48)*INDEX(Routes!$Y$6:$Y$9,$C48)*F48)-5))))) -> 0
A49: BE port 1.0x Brent 120 | B49: be_port | C49: =Sw_Route -> 1 | D49: 120 | E49: =FreightMult -> 1 | F49: 1 | G49: =UtilFH -> 0.85 | H49: =UtilBH -> 0.5 | I49: =Speed -> 13.5 | J49: =PortCostMult -> 1 | K49: =EUA -> 75 | L49: =INDEX(Routes!$E$6:$E$9,$C49) -> 5000 | M49: =INDEX(Routes!$F$6:$F$9,$C49)/L49 -> 0.13 | N49: =2*L49*(1+SeaMargin)/(I49*24) -> 32.407407 | O49: =(I49/RefSpeed)^SpeedExp -> 1 | P49: =IF(H49>0,1,0) -> 1 | Q49: =N49/2*O49*(ConsLaden+IF(P49=1,ConsLaden,ConsBallast)) -> 875 | R49: =Q49*(1-M49) -> 761.25 | S49: =Q49*M49 -> 113.75 | T49: =1+P49 -> 2 | U49: =INDEX(Routes!$L$6:$L$9,$C49)*T49*F49 -> 10 | V49: =INDEX(Routes!$M$6:$M$9,$C49)*T49*F49 -> 7 | W49: =INDEX(Routes!$H$6:$H$9,$C49)*2 -> 0 | X49: =(U49+V49+W49)*ConsPort -> 102 | Y49: =R49*D49*VLSFO_Mult+(S49+X49)*D49*MGO_Mult -> 954528 | Z49: =(INDEX(Routes!$N$6:$N$9,$C49)+AN49+MIN(AC49*INDEX(Routes!$T$6:$T$9,$C49),INDEX(Routes!$V$6:$V$9,$C49))+INDEX(Routes!$O$6:$O$9,$C49)+AO49+MIN(AC49*INDEX(Routes!$U$6:$U$9,$C49),INDEX(Routes!$W$6:$W$9,$C49))+IF(P49=1,INDEX(Routes!$N$6:$N$9,$C49)+AN49+MIN(AD49*INDEX(Routes!$T$6:$T$9,$C49),INDEX(Routes!$V$6:$V$9,$C49))+INDEX(Routes!$O$6:$O$9,$C49)+AO49+MIN(AD49*INDEX(Routes!$U$6:$U$9,$C49),INDEX(Routes!$W$6:$W$9,$C49)),0))*J49 -> 252304.21 | AA49: =INDEX(Routes!$R$6:$R$9,$C49)+IF(P49=1,INDEX(Routes!$R$6:$R$9,$C49),INDEX(Routes!$S$6:$S$9,$C49)) -> 0 | AB49: =((R49*CO2_VLSFO+S49*CO2_MGO)*INDEX(Routes!$I$6:$I$9,$C49)+(U49*INDEX(Routes!$P$6:$P$9,$C49)+V49*INDEX(Routes!$Q$6:$Q$9,$C49))*ConsPort*CO2_MGO)*PhaseIn*K49*FX -> 123936.41 | AC49: =Capacity*G49 -> 30600 | AD49: =Capacity*H49 -> 18000 | AE49: =INDEX(Routes!$J$6:$J$9,$C49)*E49 -> 52 | AF49: =INDEX(Routes!$K$6:$K$9,$C49)*E49 -> 38 | AG49: =AC49*AE49+AD49*AF49 -> 2275200 | AH49: =AG49*Commission -> 56880 | AI49: =Y49+Z49+AA49+AB49+MiscVoy -> 1355768.6 | AJ49: =N49+U49+V49+W49 -> 49.407407 | AK49: =(AG49-AH49-AI49)/AJ49 -> 17457.937 | AL49: =AG49-AH49-AI49-Benchmark*AJ49 -> -26781.952 | AM49: =IF(AC49>0,((Benchmark*AJ49+AI49)/(1-Commission)-AD49*AF49)/AC49,0) -> 52.897669 | AN49: =LOA_ft*Port_Tariffs!$C$9*IF((INDEX(Routes!$L$6:$L$9,$C49)*INDEX(Routes!$X$6:$X$9,$C49)*F49)<=2,(INDEX(Routes!$L$6:$L$9,$C49)*INDEX(Routes!$X$6:$X$9,$C49)*F49),IF((INDEX(Routes!$L$6:$L$9,$C49)*INDEX(Routes!$X$6:$X$9,$C49)*F49)<=3,2+0.9*((INDEX(Routes!$L$6:$L$9,$C49)*INDEX(Routes!$X$6:$X$9,$C49)*F49)-2),IF((INDEX(Routes!$L$6:$L$9,$C49)*INDEX(Routes!$X$6:$X$9,$C49)*F49)<=4,2.9+0.75*((INDEX(Routes!$L$6:$L$9,$C49)*INDEX(Routes!$X$6:$X$9,$C49)*F49)-3),IF((INDEX(Routes!$L$6:$L$9,$C49)*INDEX(Routes!$X$6:$X$9,$C49)*F49)<=5,3.65+0.6*((INDEX(Routes!$L$6:$L$9,$C49)*INDEX(Routes!$X$6:$X$9,$C49)*F49)-4),4.25+0.5*((INDEX(Routes!$L$6:$L$9,$C49)*INDEX(Routes!$X$6:$X$9,$C49)*F49)-5))))) -> 19557.6 | AO49: =LOA_ft*Port_Tariffs!$C$9*IF((INDEX(Routes!$M$6:$M$9,$C49)*INDEX(Routes!$Y$6:$Y$9,$C49)*F49)<=2,(INDEX(Routes!$M$6:$M$9,$C49)*INDEX(Routes!$Y$6:$Y$9,$C49)*F49),IF((INDEX(Routes!$M$6:$M$9,$C49)*INDEX(Routes!$Y$6:$Y$9,$C49)*F49)<=3,2+0.9*((INDEX(Routes!$M$6:$M$9,$C49)*INDEX(Routes!$Y$6:$Y$9,$C49)*F49)-2),IF((INDEX(Routes!$M$6:$M$9,$C49)*INDEX(Routes!$Y$6:$Y$9,$C49)*F49)<=4,2.9+0.75*((INDEX(Routes!$M$6:$M$9,$C49)*INDEX(Routes!$Y$6:$Y$9,$C49)*F49)-3),IF((INDEX(Routes!$M$6:$M$9,$C49)*INDEX(Routes!$Y$6:$Y$9,$C49)*F49)<=5,3.65+0.6*((INDEX(Routes!$M$6:$M$9,$C49)*INDEX(Routes!$Y$6:$Y$9,$C49)*F49)-4),4.25+0.5*((INDEX(Routes!$M$6:$M$9,$C49)*INDEX(Routes!$Y$6:$Y$9,$C49)*F49)-5))))) -> 0
A50: BE port 1.0x Brent 130 | B50: be_port | C50: =Sw_Route -> 1 | D50: 130 | E50: =FreightMult -> 1 | F50: 1 | G50: =UtilFH -> 0.85 | H50: =UtilBH -> 0.5 | I50: =Speed -> 13.5 | J50: =PortCostMult -> 1 | K50: =EUA -> 75 | L50: =INDEX(Routes!$E$6:$E$9,$C50) -> 5000 | M50: =INDEX(Routes!$F$6:$F$9,$C50)/L50 -> 0.13 | N50: =2*L50*(1+SeaMargin)/(I50*24) -> 32.407407 | O50: =(I50/RefSpeed)^SpeedExp -> 1 | P50: =IF(H50>0,1,0) -> 1 | Q50: =N50/2*O50*(ConsLaden+IF(P50=1,ConsLaden,ConsBallast)) -> 875 | R50: =Q50*(1-M50) -> 761.25 | S50: =Q50*M50 -> 113.75 | T50: =1+P50 -> 2 | U50: =INDEX(Routes!$L$6:$L$9,$C50)*T50*F50 -> 10 | V50: =INDEX(Routes!$M$6:$M$9,$C50)*T50*F50 -> 7 | W50: =INDEX(Routes!$H$6:$H$9,$C50)*2 -> 0 | X50: =(U50+V50+W50)*ConsPort -> 102 | Y50: =R50*D50*VLSFO_Mult+(S50+X50)*D50*MGO_Mult -> 1034072 | Z50: =(INDEX(Routes!$N$6:$N$9,$C50)+AN50+MIN(AC50*INDEX(Routes!$T$6:$T$9,$C50),INDEX(Routes!$V$6:$V$9,$C50))+INDEX(Routes!$O$6:$O$9,$C50)+AO50+MIN(AC50*INDEX(Routes!$U$6:$U$9,$C50),INDEX(Routes!$W$6:$W$9,$C50))+IF(P50=1,INDEX(Routes!$N$6:$N$9,$C50)+AN50+MIN(AD50*INDEX(Routes!$T$6:$T$9,$C50),INDEX(Routes!$V$6:$V$9,$C50))+INDEX(Routes!$O$6:$O$9,$C50)+AO50+MIN(AD50*INDEX(Routes!$U$6:$U$9,$C50),INDEX(Routes!$W$6:$W$9,$C50)),0))*J50 -> 252304.21 | AA50: =INDEX(Routes!$R$6:$R$9,$C50)+IF(P50=1,INDEX(Routes!$R$6:$R$9,$C50),INDEX(Routes!$S$6:$S$9,$C50)) -> 0 | AB50: =((R50*CO2_VLSFO+S50*CO2_MGO)*INDEX(Routes!$I$6:$I$9,$C50)+(U50*INDEX(Routes!$P$6:$P$9,$C50)+V50*INDEX(Routes!$Q$6:$Q$9,$C50))*ConsPort*CO2_MGO)*PhaseIn*K50*FX -> 123936.41 | AC50: =Capacity*G50 -> 30600 | AD50: =Capacity*H50 -> 18000 | AE50: =INDEX(Routes!$J$6:$J$9,$C50)*E50 -> 52 | AF50: =INDEX(Routes!$K$6:$K$9,$C50)*E50 -> 38 | AG50: =AC50*AE50+AD50*AF50 -> 2275200 | AH50: =AG50*Commission -> 56880 | AI50: =Y50+Z50+AA50+AB50+MiscVoy -> 1435312.6 | AJ50: =N50+U50+V50+W50 -> 49.407407 | AK50: =(AG50-AH50-AI50)/AJ50 -> 15847.975 | AL50: =AG50-AH50-AI50-Benchmark*AJ50 -> -106325.95 | AM50: =IF(AC50>0,((Benchmark*AJ50+AI50)/(1-Commission)-AD50*AF50)/AC50,0) -> 55.563799 | AN50: =LOA_ft*Port_Tariffs!$C$9*IF((INDEX(Routes!$L$6:$L$9,$C50)*INDEX(Routes!$X$6:$X$9,$C50)*F50)<=2,(INDEX(Routes!$L$6:$L$9,$C50)*INDEX(Routes!$X$6:$X$9,$C50)*F50),IF((INDEX(Routes!$L$6:$L$9,$C50)*INDEX(Routes!$X$6:$X$9,$C50)*F50)<=3,2+0.9*((INDEX(Routes!$L$6:$L$9,$C50)*INDEX(Routes!$X$6:$X$9,$C50)*F50)-2),IF((INDEX(Routes!$L$6:$L$9,$C50)*INDEX(Routes!$X$6:$X$9,$C50)*F50)<=4,2.9+0.75*((INDEX(Routes!$L$6:$L$9,$C50)*INDEX(Routes!$X$6:$X$9,$C50)*F50)-3),IF((INDEX(Routes!$L$6:$L$9,$C50)*INDEX(Routes!$X$6:$X$9,$C50)*F50)<=5,3.65+0.6*((INDEX(Routes!$L$6:$L$9,$C50)*INDEX(Routes!$X$6:$X$9,$C50)*F50)-4),4.25+0.5*((INDEX(Routes!$L$6:$L$9,$C50)*INDEX(Routes!$X$6:$X$9,$C50)*F50)-5))))) -> 19557.6 | AO50: =LOA_ft*Port_Tariffs!$C$9*IF((INDEX(Routes!$M$6:$M$9,$C50)*INDEX(Routes!$Y$6:$Y$9,$C50)*F50)<=2,(INDEX(Routes!$M$6:$M$9,$C50)*INDEX(Routes!$Y$6:$Y$9,$C50)*F50),IF((INDEX(Routes!$M$6:$M$9,$C50)*INDEX(Routes!$Y$6:$Y$9,$C50)*F50)<=3,2+0.9*((INDEX(Routes!$M$6:$M$9,$C50)*INDEX(Routes!$Y$6:$Y$9,$C50)*F50)-2),IF((INDEX(Routes!$M$6:$M$9,$C50)*INDEX(Routes!$Y$6:$Y$9,$C50)*F50)<=4,2.9+0.75*((INDEX(Routes!$M$6:$M$9,$C50)*INDEX(Routes!$Y$6:$Y$9,$C50)*F50)-3),IF((INDEX(Routes!$M$6:$M$9,$C50)*INDEX(Routes!$Y$6:$Y$9,$C50)*F50)<=5,3.65+0.6*((INDEX(Routes!$M$6:$M$9,$C50)*INDEX(Routes!$Y$6:$Y$9,$C50)*F50)-4),4.25+0.5*((INDEX(Routes!$M$6:$M$9,$C50)*INDEX(Routes!$Y$6:$Y$9,$C50)*F50)-5))))) -> 0
A51: BE port 1.5x Brent 50 | B51: be_port | C51: =Sw_Route -> 1 | D51: 50 | E51: =FreightMult -> 1 | F51: 1.5 | G51: =UtilFH -> 0.85 | H51: =UtilBH -> 0.5 | I51: =Speed -> 13.5 | J51: =PortCostMult -> 1 | K51: =EUA -> 75 | L51: =INDEX(Routes!$E$6:$E$9,$C51) -> 5000 | M51: =INDEX(Routes!$F$6:$F$9,$C51)/L51 -> 0.13 | N51: =2*L51*(1+SeaMargin)/(I51*24) -> 32.407407 | O51: =(I51/RefSpeed)^SpeedExp -> 1 | P51: =IF(H51>0,1,0) -> 1 | Q51: =N51/2*O51*(ConsLaden+IF(P51=1,ConsLaden,ConsBallast)) -> 875 | R51: =Q51*(1-M51) -> 761.25 | S51: =Q51*M51 -> 113.75 | T51: =1+P51 -> 2 | U51: =INDEX(Routes!$L$6:$L$9,$C51)*T51*F51 -> 15 | V51: =INDEX(Routes!$M$6:$M$9,$C51)*T51*F51 -> 10.5 | W51: =INDEX(Routes!$H$6:$H$9,$C51)*2 -> 0 | X51: =(U51+V51+W51)*ConsPort -> 153 | Y51: =R51*D51*VLSFO_Mult+(S51+X51)*D51*MGO_Mult -> 422455 | Z51: =(INDEX(Routes!$N$6:$N$9,$C51)+AN51+MIN(AC51*INDEX(Routes!$T$6:$T$9,$C51),INDEX(Routes!$V$6:$V$9,$C51))+INDEX(Routes!$O$6:$O$9,$C51)+AO51+MIN(AC51*INDEX(Routes!$U$6:$U$9,$C51),INDEX(Routes!$W$6:$W$9,$C51))+IF(P51=1,INDEX(Routes!$N$6:$N$9,$C51)+AN51+MIN(AD51*INDEX(Routes!$T$6:$T$9,$C51),INDEX(Routes!$V$6:$V$9,$C51))+INDEX(Routes!$O$6:$O$9,$C51)+AO51+MIN(AD51*INDEX(Routes!$U$6:$U$9,$C51),INDEX(Routes!$W$6:$W$9,$C51)),0))*J51 -> 266466.61 | AA51: =INDEX(Routes!$R$6:$R$9,$C51)+IF(P51=1,INDEX(Routes!$R$6:$R$9,$C51),INDEX(Routes!$S$6:$S$9,$C51)) -> 0 | AB51: =((R51*CO2_VLSFO+S51*CO2_MGO)*INDEX(Routes!$I$6:$I$9,$C51)+(U51*INDEX(Routes!$P$6:$P$9,$C51)+V51*INDEX(Routes!$Q$6:$Q$9,$C51))*ConsPort*CO2_MGO)*PhaseIn*K51*FX -> 129490.8 | AC51: =Capacity*G51 -> 30600 | AD51: =Capacity*H51 -> 18000 | AE51: =INDEX(Routes!$J$6:$J$9,$C51)*E51 -> 52 | AF51: =INDEX(Routes!$K$6:$K$9,$C51)*E51 -> 38 | AG51: =AC51*AE51+AD51*AF51 -> 2275200 | AH51: =AG51*Commission -> 56880 | AI51: =Y51+Z51+AA51+AB51+MiscVoy -> 843412.41 | AJ51: =N51+U51+V51+W51 -> 57.907407 | AK51: =(AG51-AH51-AI51)/AJ51 -> 23743.207 | AL51: =AG51-AH51-AI51-Benchmark*AJ51 -> 332574.25 | AM51: =IF(AC51>0,((Benchmark*AJ51+AI51)/(1-Commission)-AD51*AF51)/AC51,0) -> 40.852882 | AN51: =LOA_ft*Port_Tariffs!$C$9*IF((INDEX(Routes!$L$6:$L$9,$C51)*INDEX(Routes!$X$6:$X$9,$C51)*F51)<=2,(INDEX(Routes!$L$6:$L$9,$C51)*INDEX(Routes!$X$6:$X$9,$C51)*F51),IF((INDEX(Routes!$L$6:$L$9,$C51)*INDEX(Routes!$X$6:$X$9,$C51)*F51)<=3,2+0.9*((INDEX(Routes!$L$6:$L$9,$C51)*INDEX(Routes!$X$6:$X$9,$C51)*F51)-2),IF((INDEX(Routes!$L$6:$L$9,$C51)*INDEX(Routes!$X$6:$X$9,$C51)*F51)<=4,2.9+0.75*((INDEX(Routes!$L$6:$L$9,$C51)*INDEX(Routes!$X$6:$X$9,$C51)*F51)-3),IF((INDEX(Routes!$L$6:$L$9,$C51)*INDEX(Routes!$X$6:$X$9,$C51)*F51)<=5,3.65+0.6*((INDEX(Routes!$L$6:$L$9,$C51)*INDEX(Routes!$X$6:$X$9,$C51)*F51)-4),4.25+0.5*((INDEX(Routes!$L$6:$L$9,$C51)*INDEX(Routes!$X$6:$X$9,$C51)*F51)-5))))) -> 26638.8 | AO51: =LOA_ft*Port_Tariffs!$C$9*IF((INDEX(Routes!$M$6:$M$9,$C51)*INDEX(Routes!$Y$6:$Y$9,$C51)*F51)<=2,(INDEX(Routes!$M$6:$M$9,$C51)*INDEX(Routes!$Y$6:$Y$9,$C51)*F51),IF((INDEX(Routes!$M$6:$M$9,$C51)*INDEX(Routes!$Y$6:$Y$9,$C51)*F51)<=3,2+0.9*((INDEX(Routes!$M$6:$M$9,$C51)*INDEX(Routes!$Y$6:$Y$9,$C51)*F51)-2),IF((INDEX(Routes!$M$6:$M$9,$C51)*INDEX(Routes!$Y$6:$Y$9,$C51)*F51)<=4,2.9+0.75*((INDEX(Routes!$M$6:$M$9,$C51)*INDEX(Routes!$Y$6:$Y$9,$C51)*F51)-3),IF((INDEX(Routes!$M$6:$M$9,$C51)*INDEX(Routes!$Y$6:$Y$9,$C51)*F51)<=5,3.65+0.6*((INDEX(Routes!$M$6:$M$9,$C51)*INDEX(Routes!$Y$6:$Y$9,$C51)*F51)-4),4.25+0.5*((INDEX(Routes!$M$6:$M$9,$C51)*INDEX(Routes!$Y$6:$Y$9,$C51)*F51)-5))))) -> 0
A52: BE port 1.5x Brent 60 | B52: be_port | C52: =Sw_Route -> 1 | D52: 60 | E52: =FreightMult -> 1 | F52: 1.5 | G52: =UtilFH -> 0.85 | H52: =UtilBH -> 0.5 | I52: =Speed -> 13.5 | J52: =PortCostMult -> 1 | K52: =EUA -> 75 | L52: =INDEX(Routes!$E$6:$E$9,$C52) -> 5000 | M52: =INDEX(Routes!$F$6:$F$9,$C52)/L52 -> 0.13 | N52: =2*L52*(1+SeaMargin)/(I52*24) -> 32.407407 | O52: =(I52/RefSpeed)^SpeedExp -> 1 | P52: =IF(H52>0,1,0) -> 1 | Q52: =N52/2*O52*(ConsLaden+IF(P52=1,ConsLaden,ConsBallast)) -> 875 | R52: =Q52*(1-M52) -> 761.25 | S52: =Q52*M52 -> 113.75 | T52: =1+P52 -> 2 | U52: =INDEX(Routes!$L$6:$L$9,$C52)*T52*F52 -> 15 | V52: =INDEX(Routes!$M$6:$M$9,$C52)*T52*F52 -> 10.5 | W52: =INDEX(Routes!$H$6:$H$9,$C52)*2 -> 0 | X52: =(U52+V52+W52)*ConsPort -> 153 | Y52: =R52*D52*VLSFO_Mult+(S52+X52)*D52*MGO_Mult -> 506946 | Z52: =(INDEX(Routes!$N$6:$N$9,$C52)+AN52+MIN(AC52*INDEX(Routes!$T$6:$T$9,$C52),INDEX(Routes!$V$6:$V$9,$C52))+INDEX(Routes!$O$6:$O$9,$C52)+AO52+MIN(AC52*INDEX(Routes!$U$6:$U$9,$C52),INDEX(Routes!$W$6:$W$9,$C52))+IF(P52=1,INDEX(Routes!$N$6:$N$9,$C52)+AN52+MIN(AD52*INDEX(Routes!$T$6:$T$9,$C52),INDEX(Routes!$V$6:$V$9,$C52))+INDEX(Routes!$O$6:$O$9,$C52)+AO52+MIN(AD52*INDEX(Routes!$U$6:$U$9,$C52),INDEX(Routes!$W$6:$W$9,$C52)),0))*J52 -> 266466.61 | AA52: =INDEX(Routes!$R$6:$R$9,$C52)+IF(P52=1,INDEX(Routes!$R$6:$R$9,$C52),INDEX(Routes!$S$6:$S$9,$C52)) -> 0 | AB52: =((R52*CO2_VLSFO+S52*CO2_MGO)*INDEX(Routes!$I$6:$I$9,$C52)+(U52*INDEX(Routes!$P$6:$P$9,$C52)+V52*INDEX(Routes!$Q$6:$Q$9,$C52))*ConsPort*CO2_MGO)*PhaseIn*K52*FX -> 129490.8 | AC52: =Capacity*G52 -> 30600 | AD52: =Capacity*H52 -> 18000 | AE52: =INDEX(Routes!$J$6:$J$9,$C52)*E52 -> 52 | AF52: =INDEX(Routes!$K$6:$K$9,$C52)*E52 -> 38 | AG52: =AC52*AE52+AD52*AF52 -> 2275200 | AH52: =AG52*Commission -> 56880 | AI52: =Y52+Z52+AA52+AB52+MiscVoy -> 927903.41 | AJ52: =N52+U52+V52+W52 -> 57.907407 | AK52: =(AG52-AH52-AI52)/AJ52 -> 22284.137 | AL52: =AG52-AH52-AI52-Benchmark*AJ52 -> 248083.25 | AM52: =IF(AC52>0,((Benchmark*AJ52+AI52)/(1-Commission)-AD52*AF52)/AC52,0) -> 43.684825 | AN52: =LOA_ft*Port_Tariffs!$C$9*IF((INDEX(Routes!$L$6:$L$9,$C52)*INDEX(Routes!$X$6:$X$9,$C52)*F52)<=2,(INDEX(Routes!$L$6:$L$9,$C52)*INDEX(Routes!$X$6:$X$9,$C52)*F52),IF((INDEX(Routes!$L$6:$L$9,$C52)*INDEX(Routes!$X$6:$X$9,$C52)*F52)<=3,2+0.9*((INDEX(Routes!$L$6:$L$9,$C52)*INDEX(Routes!$X$6:$X$9,$C52)*F52)-2),IF((INDEX(Routes!$L$6:$L$9,$C52)*INDEX(Routes!$X$6:$X$9,$C52)*F52)<=4,2.9+0.75*((INDEX(Routes!$L$6:$L$9,$C52)*INDEX(Routes!$X$6:$X$9,$C52)*F52)-3),IF((INDEX(Routes!$L$6:$L$9,$C52)*INDEX(Routes!$X$6:$X$9,$C52)*F52)<=5,3.65+0.6*((INDEX(Routes!$L$6:$L$9,$C52)*INDEX(Routes!$X$6:$X$9,$C52)*F52)-4),4.25+0.5*((INDEX(Routes!$L$6:$L$9,$C52)*INDEX(Routes!$X$6:$X$9,$C52)*F52)-5))))) -> 26638.8 | AO52: =LOA_ft*Port_Tariffs!$C$9*IF((INDEX(Routes!$M$6:$M$9,$C52)*INDEX(Routes!$Y$6:$Y$9,$C52)*F52)<=2,(INDEX(Routes!$M$6:$M$9,$C52)*INDEX(Routes!$Y$6:$Y$9,$C52)*F52),IF((INDEX(Routes!$M$6:$M$9,$C52)*INDEX(Routes!$Y$6:$Y$9,$C52)*F52)<=3,2+0.9*((INDEX(Routes!$M$6:$M$9,$C52)*INDEX(Routes!$Y$6:$Y$9,$C52)*F52)-2),IF((INDEX(Routes!$M$6:$M$9,$C52)*INDEX(Routes!$Y$6:$Y$9,$C52)*F52)<=4,2.9+0.75*((INDEX(Routes!$M$6:$M$9,$C52)*INDEX(Routes!$Y$6:$Y$9,$C52)*F52)-3),IF((INDEX(Routes!$M$6:$M$9,$C52)*INDEX(Routes!$Y$6:$Y$9,$C52)*F52)<=5,3.65+0.6*((INDEX(Routes!$M$6:$M$9,$C52)*INDEX(Routes!$Y$6:$Y$9,$C52)*F52)-4),4.25+0.5*((INDEX(Routes!$M$6:$M$9,$C52)*INDEX(Routes!$Y$6:$Y$9,$C52)*F52)-5))))) -> 0
A53: BE port 1.5x Brent 70 | B53: be_port | C53: =Sw_Route -> 1 | D53: 70 | E53: =FreightMult -> 1 | F53: 1.5 | G53: =UtilFH -> 0.85 | H53: =UtilBH -> 0.5 | I53: =Speed -> 13.5 | J53: =PortCostMult -> 1 | K53: =EUA -> 75 | L53: =INDEX(Routes!$E$6:$E$9,$C53) -> 5000 | M53: =INDEX(Routes!$F$6:$F$9,$C53)/L53 -> 0.13 | N53: =2*L53*(1+SeaMargin)/(I53*24) -> 32.407407 | O53: =(I53/RefSpeed)^SpeedExp -> 1 | P53: =IF(H53>0,1,0) -> 1 | Q53: =N53/2*O53*(ConsLaden+IF(P53=1,ConsLaden,ConsBallast)) -> 875 | R53: =Q53*(1-M53) -> 761.25 | S53: =Q53*M53 -> 113.75 | T53: =1+P53 -> 2 | U53: =INDEX(Routes!$L$6:$L$9,$C53)*T53*F53 -> 15 | V53: =INDEX(Routes!$M$6:$M$9,$C53)*T53*F53 -> 10.5 | W53: =INDEX(Routes!$H$6:$H$9,$C53)*2 -> 0 | X53: =(U53+V53+W53)*ConsPort -> 153 | Y53: =R53*D53*VLSFO_Mult+(S53+X53)*D53*MGO_Mult -> 591437 | Z53: =(INDEX(Routes!$N$6:$N$9,$C53)+AN53+MIN(AC53*INDEX(Routes!$T$6:$T$9,$C53),INDEX(Routes!$V$6:$V$9,$C53))+INDEX(Routes!$O$6:$O$9,$C53)+AO53+MIN(AC53*INDEX(Routes!$U$6:$U$9,$C53),INDEX(Routes!$W$6:$W$9,$C53))+IF(P53=1,INDEX(Routes!$N$6:$N$9,$C53)+AN53+MIN(AD53*INDEX(Routes!$T$6:$T$9,$C53),INDEX(Routes!$V$6:$V$9,$C53))+INDEX(Routes!$O$6:$O$9,$C53)+AO53+MIN(AD53*INDEX(Routes!$U$6:$U$9,$C53),INDEX(Routes!$W$6:$W$9,$C53)),0))*J53 -> 266466.61 | AA53: =INDEX(Routes!$R$6:$R$9,$C53)+IF(P53=1,INDEX(Routes!$R$6:$R$9,$C53),INDEX(Routes!$S$6:$S$9,$C53)) -> 0 | AB53: =((R53*CO2_VLSFO+S53*CO2_MGO)*INDEX(Routes!$I$6:$I$9,$C53)+(U53*INDEX(Routes!$P$6:$P$9,$C53)+V53*INDEX(Routes!$Q$6:$Q$9,$C53))*ConsPort*CO2_MGO)*PhaseIn*K53*FX -> 129490.8 | AC53: =Capacity*G53 -> 30600 | AD53: =Capacity*H53 -> 18000 | AE53: =INDEX(Routes!$J$6:$J$9,$C53)*E53 -> 52 | AF53: =INDEX(Routes!$K$6:$K$9,$C53)*E53 -> 38 | AG53: =AC53*AE53+AD53*AF53 -> 2275200 | AH53: =AG53*Commission -> 56880 | AI53: =Y53+Z53+AA53+AB53+MiscVoy -> 1012394.4 | AJ53: =N53+U53+V53+W53 -> 57.907407 | AK53: =(AG53-AH53-AI53)/AJ53 -> 20825.066 | AL53: =AG53-AH53-AI53-Benchmark*AJ53 -> 163592.25 | AM53: =IF(AC53>0,((Benchmark*AJ53+AI53)/(1-Commission)-AD53*AF53)/AC53,0) -> 46.516767 | AN53: =LOA_ft*Port_Tariffs!$C$9*IF((INDEX(Routes!$L$6:$L$9,$C53)*INDEX(Routes!$X$6:$X$9,$C53)*F53)<=2,(INDEX(Routes!$L$6:$L$9,$C53)*INDEX(Routes!$X$6:$X$9,$C53)*F53),IF((INDEX(Routes!$L$6:$L$9,$C53)*INDEX(Routes!$X$6:$X$9,$C53)*F53)<=3,2+0.9*((INDEX(Routes!$L$6:$L$9,$C53)*INDEX(Routes!$X$6:$X$9,$C53)*F53)-2),IF((INDEX(Routes!$L$6:$L$9,$C53)*INDEX(Routes!$X$6:$X$9,$C53)*F53)<=4,2.9+0.75*((INDEX(Routes!$L$6:$L$9,$C53)*INDEX(Routes!$X$6:$X$9,$C53)*F53)-3),IF((INDEX(Routes!$L$6:$L$9,$C53)*INDEX(Routes!$X$6:$X$9,$C53)*F53)<=5,3.65+0.6*((INDEX(Routes!$L$6:$L$9,$C53)*INDEX(Routes!$X$6:$X$9,$C53)*F53)-4),4.25+0.5*((INDEX(Routes!$L$6:$L$9,$C53)*INDEX(Routes!$X$6:$X$9,$C53)*F53)-5))))) -> 26638.8 | AO53: =LOA_ft*Port_Tariffs!$C$9*IF((INDEX(Routes!$M$6:$M$9,$C53)*INDEX(Routes!$Y$6:$Y$9,$C53)*F53)<=2,(INDEX(Routes!$M$6:$M$9,$C53)*INDEX(Routes!$Y$6:$Y$9,$C53)*F53),IF((INDEX(Routes!$M$6:$M$9,$C53)*INDEX(Routes!$Y$6:$Y$9,$C53)*F53)<=3,2+0.9*((INDEX(Routes!$M$6:$M$9,$C53)*INDEX(Routes!$Y$6:$Y$9,$C53)*F53)-2),IF((INDEX(Routes!$M$6:$M$9,$C53)*INDEX(Routes!$Y$6:$Y$9,$C53)*F53)<=4,2.9+0.75*((INDEX(Routes!$M$6:$M$9,$C53)*INDEX(Routes!$Y$6:$Y$9,$C53)*F53)-3),IF((INDEX(Routes!$M$6:$M$9,$C53)*INDEX(Routes!$Y$6:$Y$9,$C53)*F53)<=5,3.65+0.6*((INDEX(Routes!$M$6:$M$9,$C53)*INDEX(Routes!$Y$6:$Y$9,$C53)*F53)-4),4.25+0.5*((INDEX(Routes!$M$6:$M$9,$C53)*INDEX(Routes!$Y$6:$Y$9,$C53)*F53)-5))))) -> 0
... A68: BE port 2.0x Brent 130 | B68: be_port | C68: =Sw_Route -> 1 | D68: 130 | E68: =FreightMult -> 1 | F68: 2 | G68: =UtilFH -> 0.85 | H68: =UtilBH -> 0.5 | I68: =Speed -> 13.5 | J68: =PortCostMult -> 1 | K68: =EUA -> 75 | L68: =INDEX(Routes!$E$6:$E$9,$C68) -> 5000 | M68: =INDEX(Routes!$F$6:$F$9,$C68)/L68 -> 0.13 | N68: =2*L68*(1+SeaMargin)/(I68*24) -> 32.407407 | O68: =(I68/RefSpeed)^SpeedExp -> 1 | P68: =IF(H68>0,1,0) -> 1 | Q68: =N68/2*O68*(ConsLaden+IF(P68=1,ConsLaden,ConsBallast)) -> 875 | R68: =Q68*(1-M68) -> 761.25 | S68: =Q68*M68 -> 113.75 | T68: =1+P68 -> 2 | U68: =INDEX(Routes!$L$6:$L$9,$C68)*T68*F68 -> 20 | V68: =INDEX(Routes!$M$6:$M$9,$C68)*T68*F68 -> 14 | W68: =INDEX(Routes!$H$6:$H$9,$C68)*2 -> 0 | X68: =(U68+V68+W68)*ConsPort -> 204 | Y68: =R68*D68*VLSFO_Mult+(S68+X68)*D68*MGO_Mult -> 1162694 | Z68: =(INDEX(Routes!$N$6:$N$9,$C68)+AN68+MIN(AC68*INDEX(Routes!$T$6:$T$9,$C68),INDEX(Routes!$V$6:$V$9,$C68))+INDEX(Routes!$O$6:$O$9,$C68)+AO68+MIN(AC68*INDEX(Routes!$U$6:$U$9,$C68),INDEX(Routes!$W$6:$W$9,$C68))+IF(P68=1,INDEX(Routes!$N$6:$N$9,$C68)+AN68+MIN(AD68*INDEX(Routes!$T$6:$T$9,$C68),INDEX(Routes!$V$6:$V$9,$C68))+INDEX(Routes!$O$6:$O$9,$C68)+AO68+MIN(AD68*INDEX(Routes!$U$6:$U$9,$C68),INDEX(Routes!$W$6:$W$9,$C68)),0))*J68 -> 277257.01 | AA68: =INDEX(Routes!$R$6:$R$9,$C68)+IF(P68=1,INDEX(Routes!$R$6:$R$9,$C68),INDEX(Routes!$S$6:$S$9,$C68)) -> 0 | AB68: =((R68*CO2_VLSFO+S68*CO2_MGO)*INDEX(Routes!$I$6:$I$9,$C68)+(U68*INDEX(Routes!$P$6:$P$9,$C68)+V68*INDEX(Routes!$Q$6:$Q$9,$C68))*ConsPort*CO2_MGO)*PhaseIn*K68*FX -> 135045.2 | AC68: =Capacity*G68 -> 30600 | AD68: =Capacity*H68 -> 18000 | AE68: =INDEX(Routes!$J$6:$J$9,$C68)*E68 -> 52 | AF68: =INDEX(Routes!$K$6:$K$9,$C68)*E68 -> 38 | AG68: =AC68*AE68+AD68*AF68 -> 2275200 | AH68: =AG68*Commission -> 56880 | AI68: =Y68+Z68+AA68+AB68+MiscVoy -> 1599996.2 | AJ68: =N68+U68+V68+W68 -> 66.407407 | AK68: =(AG68-AH68-AI68)/AJ68 -> 9311.0666 | AL68: =AG68-AH68-AI68-Benchmark*AJ68 -> -577009.54 | AM68: =IF(AC68>0,((Benchmark*AJ68+AI68)/(1-Commission)-AD68*AF68)/AC68,0) -> 71.340022 | AN68: =LOA_ft*Port_Tariffs!$C$9*IF((INDEX(Routes!$L$6:$L$9,$C68)*INDEX(Routes!$X$6:$X$9,$C68)*F68)<=2,(INDEX(Routes!$L$6:$L$9,$C68)*INDEX(Routes!$X$6:$X$9,$C68)*F68),IF((INDEX(Routes!$L$6:$L$9,$C68)*INDEX(Routes!$X$6:$X$9,$C68)*F68)<=3,2+0.9*((INDEX(Routes!$L$6:$L$9,$C68)*INDEX(Routes!$X$6:$X$9,$C68)*F68)-2),IF((INDEX(Routes!$L$6:$L$9,$C68)*INDEX(Routes!$X$6:$X$9,$C68)*F68)<=4,2.9+0.75*((INDEX(Routes!$L$6:$L$9,$C68)*INDEX(Routes!$X$6:$X$9,$C68)*F68)-3),IF((INDEX(Routes!$L$6:$L$9,$C68)*INDEX(Routes!$X$6:$X$9,$C68)*F68)<=5,3.65+0.6*((INDEX(Routes!$L$6:$L$9,$C68)*INDEX(Routes!$X$6:$X$9,$C68)*F68)-4),4.25+0.5*((INDEX(Routes!$L$6:$L$9,$C68)*INDEX(Routes!$X$6:$X$9,$C68)*F68)-5))))) -> 32034 | AO68: =LOA_ft*Port_Tariffs!$C$9*IF((INDEX(Routes!$M$6:$M$9,$C68)*INDEX(Routes!$Y$6:$Y$9,$C68)*F68)<=2,(INDEX(Routes!$M$6:$M$9,$C68)*INDEX(Routes!$Y$6:$Y$9,$C68)*F68),IF((INDEX(Routes!$M$6:$M$9,$C68)*INDEX(Routes!$Y$6:$Y$9,$C68)*F68)<=3,2+0.9*((INDEX(Routes!$M$6:$M$9,$C68)*INDEX(Routes!$Y$6:$Y$9,$C68)*F68)-2),IF((INDEX(Routes!$M$6:$M$9,$C68)*INDEX(Routes!$Y$6:$Y$9,$C68)*F68)<=4,2.9+0.75*((INDEX(Routes!$M$6:$M$9,$C68)*INDEX(Routes!$Y$6:$Y$9,$C68)*F68)-3),IF((INDEX(Routes!$M$6:$M$9,$C68)*INDEX(Routes!$Y$6:$Y$9,$C68)*F68)<=5,3.65+0.6*((INDEX(Routes!$M$6:$M$9,$C68)*INDEX(Routes!$Y$6:$Y$9,$C68)*F68)-4),4.25+0.5*((INDEX(Routes!$M$6:$M$9,$C68)*INDEX(Routes!$Y$6:$Y$9,$C68)*F68)-5))))) -> 0
A69: BE util 70% Brent 50 | B69: be_util | C69: =Sw_Route -> 1 | D69: 50 | E69: =FreightMult -> 1 | F69: =PortMult -> 1 | G69: 0.7 | H69: =UtilBH -> 0.5 | I69: =Speed -> 13.5 | J69: =PortCostMult -> 1 | K69: =EUA -> 75 | L69: =INDEX(Routes!$E$6:$E$9,$C69) -> 5000 | M69: =INDEX(Routes!$F$6:$F$9,$C69)/L69 -> 0.13 | N69: =2*L69*(1+SeaMargin)/(I69*24) -> 32.407407 | O69: =(I69/RefSpeed)^SpeedExp -> 1 | P69: =IF(H69>0,1,0) -> 1 | Q69: =N69/2*O69*(ConsLaden+IF(P69=1,ConsLaden,ConsBallast)) -> 875 | R69: =Q69*(1-M69) -> 761.25 | S69: =Q69*M69 -> 113.75 | T69: =1+P69 -> 2 | U69: =INDEX(Routes!$L$6:$L$9,$C69)*T69*F69 -> 10 | V69: =INDEX(Routes!$M$6:$M$9,$C69)*T69*F69 -> 7 | W69: =INDEX(Routes!$H$6:$H$9,$C69)*2 -> 0 | X69: =(U69+V69+W69)*ConsPort -> 102 | Y69: =R69*D69*VLSFO_Mult+(S69+X69)*D69*MGO_Mult -> 397720 | Z69: =(INDEX(Routes!$N$6:$N$9,$C69)+AN69+MIN(AC69*INDEX(Routes!$T$6:$T$9,$C69),INDEX(Routes!$V$6:$V$9,$C69))+INDEX(Routes!$O$6:$O$9,$C69)+AO69+MIN(AC69*INDEX(Routes!$U$6:$U$9,$C69),INDEX(Routes!$W$6:$W$9,$C69))+IF(P69=1,INDEX(Routes!$N$6:$N$9,$C69)+AN69+MIN(AD69*INDEX(Routes!$T$6:$T$9,$C69),INDEX(Routes!$V$6:$V$9,$C69))+INDEX(Routes!$O$6:$O$9,$C69)+AO69+MIN(AD69*INDEX(Routes!$U$6:$U$9,$C69),INDEX(Routes!$W$6:$W$9,$C69)),0))*J69 -> 248763.02 | AA69: =INDEX(Routes!$R$6:$R$9,$C69)+IF(P69=1,INDEX(Routes!$R$6:$R$9,$C69),INDEX(Routes!$S$6:$S$9,$C69)) -> 0 | AB69: =((R69*CO2_VLSFO+S69*CO2_MGO)*INDEX(Routes!$I$6:$I$9,$C69)+(U69*INDEX(Routes!$P$6:$P$9,$C69)+V69*INDEX(Routes!$Q$6:$Q$9,$C69))*ConsPort*CO2_MGO)*PhaseIn*K69*FX -> 123936.41 | AC69: =Capacity*G69 -> 25200 | AD69: =Capacity*H69 -> 18000 | AE69: =INDEX(Routes!$J$6:$J$9,$C69)*E69 -> 52 | AF69: =INDEX(Routes!$K$6:$K$9,$C69)*E69 -> 38 | AG69: =AC69*AE69+AD69*AF69 -> 1994400 | AH69: =AG69*Commission -> 49860 | AI69: =Y69+Z69+AA69+AB69+MiscVoy -> 795419.43 | AJ69: =N69+U69+V69+W69 -> 49.407407 | AK69: =(AG69-AH69-AI69)/AJ69 -> 23258.063 | AL69: =AG69-AH69-AI69-Benchmark*AJ69 -> 259787.24 | AM69: =IF(AC69>0,((Benchmark*AJ69+AI69)/(1-Commission)-AD69*AF69)/AC69,0) -> 41.426649 | AN69: =LOA_ft*Port_Tariffs!$C$9*IF((INDEX(Routes!$L$6:$L$9,$C69)*INDEX(Routes!$X$6:$X$9,$C69)*F69)<=2,(INDEX(Routes!$L$6:$L$9,$C69)*INDEX(Routes!$X$6:$X$9,$C69)*F69),IF((INDEX(Routes!$L$6:$L$9,$C69)*INDEX(Routes!$X$6:$X$9,$C69)*F69)<=3,2+0.9*((INDEX(Routes!$L$6:$L$9,$C69)*INDEX(Routes!$X$6:$X$9,$C69)*F69)-2),IF((INDEX(Routes!$L$6:$L$9,$C69)*INDEX(Routes!$X$6:$X$9,$C69)*F69)<=4,2.9+0.75*((INDEX(Routes!$L$6:$L$9,$C69)*INDEX(Routes!$X$6:$X$9,$C69)*F69)-3),IF((INDEX(Routes!$L$6:$L$9,$C69)*INDEX(Routes!$X$6:$X$9,$C69)*F69)<=5,3.65+0.6*((INDEX(Routes!$L$6:$L$9,$C69)*INDEX(Routes!$X$6:$X$9,$C69)*F69)-4),4.25+0.5*((INDEX(Routes!$L$6:$L$9,$C69)*INDEX(Routes!$X$6:$X$9,$C69)*F69)-5))))) -> 19557.6 | AO69: =LOA_ft*Port_Tariffs!$C$9*IF((INDEX(Routes!$M$6:$M$9,$C69)*INDEX(Routes!$Y$6:$Y$9,$C69)*F69)<=2,(INDEX(Routes!$M$6:$M$9,$C69)*INDEX(Routes!$Y$6:$Y$9,$C69)*F69),IF((INDEX(Routes!$M$6:$M$9,$C69)*INDEX(Routes!$Y$6:$Y$9,$C69)*F69)<=3,2+0.9*((INDEX(Routes!$M$6:$M$9,$C69)*INDEX(Routes!$Y$6:$Y$9,$C69)*F69)-2),IF((INDEX(Routes!$M$6:$M$9,$C69)*INDEX(Routes!$Y$6:$Y$9,$C69)*F69)<=4,2.9+0.75*((INDEX(Routes!$M$6:$M$9,$C69)*INDEX(Routes!$Y$6:$Y$9,$C69)*F69)-3),IF((INDEX(Routes!$M$6:$M$9,$C69)*INDEX(Routes!$Y$6:$Y$9,$C69)*F69)<=5,3.65+0.6*((INDEX(Routes!$M$6:$M$9,$C69)*INDEX(Routes!$Y$6:$Y$9,$C69)*F69)-4),4.25+0.5*((INDEX(Routes!$M$6:$M$9,$C69)*INDEX(Routes!$Y$6:$Y$9,$C69)*F69)-5))))) -> 0
